Workbook
Name Base_Annual_Salary_GBP: Inputs!$B$2
Name Bonus_Pct_Aug2026_to_Sep2026: Inputs!$B$61
Name Bonus_Pct_Oct2026_to_Sep2027: Inputs!$B$62
Name Bonus_Pct_Oct2027_to_Sep2028: Inputs!$B$63
Name Bonus_Pct_Oct2028_to_Sep2029: Inputs!$B$64
Name Bonus_Pct_Oct2029_onwards: Inputs!$B$65
Name FX_USD_per_GBP: Inputs!$B$13
Name Include_Pension_in_Cashflow: Inputs!$B$16
Name Living_Expenses_EGP_Monthly_2026: [1]Inputs!$B$24
Name Living_Expenses_EGP_Monthly_2027: [1]Inputs!$B$25
Name Living_Expenses_EGP_Monthly_2028: [1]Inputs!$B$26
Name Living_Expenses_EGP_Monthly_2029: [1]Inputs!$B$27
Name Living_Expenses_EGP_Monthly_2030: [1]Inputs!$B$28
Name Living_Expenses_GBP_Monthly_2026: Inputs!$B$50
Name Living_Expenses_GBP_Monthly_2027: Inputs!$B$51
Name Living_Expenses_GBP_Monthly_2028: Inputs!$B$52
Name Living_Expenses_GBP_Monthly_2029: Inputs!$B$53
Name Living_Expenses_GBP_Monthly_2030: Inputs!$B$54
Name New_Hire_Stock_Grant_USD: Inputs!$B$12
Name Raise_Pct_Apr2027: Inputs!$B$4
Name Raise_Pct_Apr2028: Inputs!$B$5
Name Raise_Pct_Apr2029: Inputs!$B$6
Name Raise_Pct_Apr2030: Inputs!$B$7
Name Raise_Pct_Nov2027: Inputs!$B$25
Name Raise_Pct_Nov2028: Inputs!$B$26
Name Raise_Pct_Nov2029: Inputs!$B$27
Name Raise_Pct_Nov2030: Inputs!$B$28
Name RSU_Grant_Nov2027_USD: Inputs!$B$31
Name RSU_Grant_Nov2028_USD: Inputs!$B$32
Name RSU_Grant_Nov2029_USD: Inputs!$B$33
Name RSU_Price_Change_Pct: Inputs!$B$15
Name Taxes_Pct: Inputs!#REF!
Name UK_Additional_Rate: Inputs!$B$41
Name UK_Basic_Band_Upper_Annual: Inputs!$B$37
Name UK_Basic_Rate: Inputs!$B$39
Name UK_Higher_Band_Upper_Annual: Inputs!$B$38
Name UK_Higher_Rate: Inputs!$B$40
Name UK_NI_Main_Rate: Inputs!$B$45
Name UK_NI_PT_Monthly: Inputs!$B$43
Name UK_NI_UEL_Monthly: Inputs!$B$44
Name UK_NI_Upper_Rate: Inputs!$B$46
Name UK_Personal_Allowance_Annual: Inputs!$B$36
Name UK_TaxYear_Start_Month: Inputs!$B$42
Name USD_to_EGP: [1]Inputs!$B$29

Sheet Inputs
A1: Key | B1: Value | C1: Notes
A2: Base_Annual_Salary_GBP | B2: 50000 | C2: Base salary (annual) in GBP
A4: Raise_Pct_Apr2027 | B4: 0.03 | C4: Annual salary review (March), effective April 2027.
A5: Raise_Pct_Apr2028 | B5: 0.03 | C5: Annual salary review (March), effective April 2028.
A6: Raise_Pct_Apr2029 | B6: 0.03 | C6: Annual salary review (March), effective April 2029.
A7: Raise_Pct_Apr2030 | B7: 0.03 | C7: Annual salary review (March), effective April 2030.
A8: Hiring_Bonus_GBP | B8: 3000 | C8: One-off hiring bonus
A9: Hiring_Bonus_Pay_Month_Offset | B9: 0 | C9: Months after Aug 2026 (0=Aug 2026)
A10: Relocation_Allowance_GBP | B10: 0 | C10: Relocation allowance
A11: Relocation_Pay_Month_Offset | B11: 0 | C11: Months after Aug 2026 (0=Aug 2026)
A12: New_Hire_Stock_Grant_USD | B12: 30000 | C12: New-hire RSU grant face value (USD)
A13: FX_USD_per_GBP | B13: 1.36 | C13: FX: RSU_GBP = USD / FX
A15: RSU_Assumed_Price_Change_Pct_per_year | B15: 0 | C15: Optional price change assumption for RSU (default 0%)
... A20: NI_Passback_Pct_of_Employee_Contrib | B20: 0.07 | C20: NI passback fraction of employee contrib
A24: Raises – Off-cycle (effective October)
A25: Raise_Pct_Nov2027 | B25: 0 | C25: Off-cycle review (Oct) effective Oct 2027 (optional).
A26: Raise_Pct_Nov2028 | B26: 0.03 | C26: Off-cycle review (Oct) effective Oct 2028 (optional).
A27: Raise_Pct_Nov2029 | B27: 0 | C27: Off-cycle review (Oct) effective Oct 2029 (optional).
A28: Raise_Pct_Nov2030 | B28: 0 | C28: Off-cycle review (Oct) effective Oct 2030 (optional).
A30: RSU Refresh Grants (Optional, USD)
A31: RSU_Grant_Nov2027_USD | B31: 0 | C31: Grant in Nov 2027 (no guarantee). First vest Nov 2028.
A32: RSU_Grant_Nov2028_USD | B32: 0 | C32: Grant in Nov 2028 (no guarantee). First vest Nov 2029.
A33: RSU_Grant_Nov2029_USD | B33: 0 | C33: Grant in Nov 2029 (no guarantee). First vest Nov 2030.
A35: UK Tax Settings (England/Wales/NI, 2026/27)
A36: UK_Personal_Allowance_Annual | B36: 12570 | C36: Personal Allowance (annual)
A37: UK_Basic_Band_Upper_Annual | B37: 50270 | C37: Upper limit of Basic rate band (annual, incl allowance)
A38: UK_Higher_Band_Upper_Annual | B38: 125140 | C38: Upper limit of Higher rate band (annual)
A39: UK_Basic_Rate | B39: 0.2 | C39: Income Tax basic rate
A40: UK_Higher_Rate | B40: 0.4 | C40: Income Tax higher rate
A41: UK_Additional_Rate | B41: 0.45 | C41: Income Tax additional rate
A42: UK_TaxYear_Start_Month | B42: 4 | C42: Tax year starts in April
A43: UK_NI_PT_Monthly | B43: 1048 | C43: NI Primary Threshold (per month)
A44: UK_NI_UEL_Monthly | B44: 4189 | C44: NI Upper Earnings Limit (per month)
A45: UK_NI_Main_Rate | B45: 0.08 | C45: NI rate between PT and UEL
A46: UK_NI_Upper_Rate | B46: 0.02 | C46: NI rate above UEL
A50: Living_Expenses_GBP_Monthly_2026 | B50: =2400 -> 2400
A51: Living_Expenses_GBP_Monthly_2027 | B51: =B50*1.02 -> 2448 | E51: Assumed living expenses
A52: Living_Expenses_GBP_Monthly_2028 | B52: =B51*1.02 -> 2496.96 | E52: Element | F52: Price | G52: Assumptions
A53: Living_Expenses_GBP_Monthly_2029 | B53: =B52*1.02 -> 2546.8992 | E53: Rent | F53: =1050+215 -> 1265 | G53: Rent + Council Tax
A54: Living_Expenses_GBP_Monthly_2030 | B54: =B53*1.02 -> 2597.8372 | E54: Utilities (electricity/gas) | F54: 160
E55: Home Internet | F55: 35
A56: RSU_Price_Change_2027 | B56: 0 | C56: Pct change of RSU stock price in 2027 vs 2026 (can be +/-) | E56: Mobile Internet | F56: 20
A57: RSU_Price_Change_2028 | B57: 0 | C57: Pct change of RSU stock price in 2028 vs 2026 (can be +/-) | E57: Groceries | F57: 300
A58: RSU_Price_Change_2029 | B58: 0 | C58: Pct change of RSU stock price in 2029 vs 2026 (can be +/-) | E58: Transportation | F58: 60 | G58: Working 3 days from office .. Hanging out 6 days per month
E59: Flight tickets to/from Egypt | F59: 135 | G59: Assuming 2 round trips per year with one costing 550 per person
A60: Bonus % by period (editable) | C60: Used by Monthly Schedule bonus calculation; change these when level/bonus target changes. | E60: Eating out | F60: 100 | G60: Assuming eating out twice per month
A61: Bonus_Pct_Aug2026_to_Sep2026 | B61: 0.08 | C61: Bonus target % for Aug 2026–Sep 2026 (Oct 2026 boundary). | E61: Cafes | F61: 20 | G61: Assuming going to a café twice per month
A62: Bonus_Pct_Oct2026_to_Sep2027 | B62: 0.08 | C62: Bonus target % for Oct 2026–Sep 2027. | E62: Entertainment | F62: 0
A63: Bonus_Pct_Oct2027_to_Sep2028 | B63: 0.08 | C63: Bonus target % for Oct 2027–Sep 2028. | E63: Clothes | F63: 0
A64: Bonus_Pct_Oct2028_to_Sep2029 | B64: 0.1 | C64: Bonus target % for Oct 2028–Sep 2029. | E64: Haircuts | F64: 35 | G64: Assuming cutting hair and beard every 3 weeks
A65: Bonus_Pct_Oct2029_onwards | B65: 0.1 | C65: Bonus target % for Oct 2029 onward (covers Oct 2029–Dec 2030 in this model). | E65: Gym | F65: 90
E66: Unexpected / Buffer | F66: 100
E67: Total | F67: =SUM(F53:F66) -> 2320

Sheet Monthly Schedule
A1: Month | B1: Base Salary (GBP) | C1: Bonus Paid (GBP) | D1: RSU Vest (GBP) | E1: Hiring Bonus (GBP) | F1: Relocation (GBP) | G1: Pension Employer (GBP) | H1: Total Gross Monthly Income | I1: Total Net Monthly Income | J1: Income Tax (PAYE, GBP) | K1: Employee NI (GBP) | L1: Bonus Target Pct (current)
A2: 46235 | B2: =(IF(YEAR($A2)=2026,Base_Annual_Salary_GBP,IF(YEAR($A2)=2027,Base_Annual_Salary_GBP*(IF(MONTH($A2)>=4,(1+Raise_Pct_Apr2027),1)*IF(MONTH($A2)>=10,(1+Raise_Pct_Nov2027),1)),IF(YEAR($A2)=2028,Base_Annual_Salary_GBP*((1+Raise_Pct_Apr2027)*(1+Raise_Pct_Nov2027))*(IF(MONTH($A2)>=4,(1+Raise_Pct_Apr2028),1)*IF(MONTH($A2)>=10,(1+Raise_Pct_Nov2028),1)),IF(YEAR($A2)=2029,Base_Annual_Salary_GBP*((1+Raise_Pct_Apr2027)*(1+Raise_Pct_Nov2027)*(1+Raise_Pct_Apr2028)*(1+Raise_Pct_Nov2028))*(IF(MONTH($A2)>=4,(1+Raise_Pct_Apr2029),1)*IF(MONTH($A2)>=10,(1+Raise_Pct_Nov2029),1)),Base_Annual_Salary_GBP*((1+Raise_Pct_Apr2027)*(1+Raise_Pct_Nov2027)*(1+Raise_Pct_Apr2028)*(1+Raise_Pct_Nov2028)*(1+Raise_Pct_Apr2029)*(1+Raise_Pct_Nov2029))*(IF(MONTH($A2)>=4,(1+Raise_Pct_Apr2030),1)*IF(MONTH($A2)>=10,(1+Raise_Pct_Nov2030),1)))))))/12 -> 4166.6667 | C2: =IF(MONTH($A2)=11,((IF(DATE(YEAR($A2),4,1)<DATE(2026,10,1),Bonus_Pct_Aug2026_to_Sep2026,IF(DATE(YEAR($A2),4,1)<DATE(2027,10,1),Bonus_Pct_Oct2026_to_Sep2027,IF(DATE(YEAR($A2),4,1)<DATE(2028,10,1),Bonus_Pct_Oct2027_to_Sep2028,IF(DATE(YEAR($A2),4,1)<DATE(2029,10,1),Bonus_Pct_Oct2028_to_Sep2029,Bonus_Pct_Oct2029_onwards)))))/2)*($B2*12) / (1 + IF(YEAR($A2)=2027,Raise_Pct_Nov2027,IF(YEAR($A2)=2028,Raise_Pct_Nov2028,IF(YEAR($A2)=2029,Raise_Pct_Nov2029,IF(YEAR($A2)=2030,Raise_Pct_Nov2030,0))))) * IF(YEAR($A2)=2026,2/6,1),IF(MONTH($A2)=5,((IF(DATE(YEAR($A2)-1,10,1)<DATE(2026,10,1),Bonus_Pct_Aug2026_to_Sep2026,IF(DATE(YEAR($A2)-1,10,1)<DATE(2027,10,1),Bonus_Pct_Oct2026_to_Sep2027,IF(DATE(YEAR($A2)-1,10,1)<DATE(2028,10,1),Bonus_Pct_Oct2027_to_Sep2028,IF(DATE(YEAR($A2)-1,10,1)<DATE(2029,10,1),Bonus_Pct_Oct2028_to_Sep2029,Bonus_Pct_Oct2029_onwards)))))/2)*($B2*12) / (1 + IF(YEAR($A2)=2027,Raise_Pct_Apr2027,IF(YEAR($A2)=2028,Raise_Pct_Apr2028,IF(YEAR($A2)=2029,Raise_Pct_Apr2029,IF(YEAR($A2)=2030,Raise_Pct_Apr2030,0))))),0)) -> 0 | D2: =IF(OR($A2=DATE(2027,9,1),$A2=EDATE(DATE(2027,9,1),12),$A2=EDATE(DATE(2027,9,1),24)),(New_Hire_Stock_Grant_USD/3)/FX_USD_per_GBP*(1+IF(YEAR($A2)=2027,Inputs!$B$56,IF(YEAR($A2)=2028,Inputs!$B$57,IF(YEAR($A2)=2029,Inputs!$B$58,0)))),0)+IF(OR($A2=DATE(2028,11,1),$A2=DATE(2029,11,1),$A2=DATE(2030,11,1)),(RSU_Grant_Nov2027_USD/3)/FX_USD_per_GBP*(1+RSU_Price_Change_Pct)^(YEAR($A2)-2028),0)+IF(OR($A2=DATE(2029,11,1),$A2=DATE(2030,11,1)),(RSU_Grant_Nov2028_USD/3)/FX_USD_per_GBP*(1+RSU_Price_Change_Pct)^(YEAR($A2)-2029),0)+IF($A2=DATE(2030,11,1),(RSU_Grant_Nov2029_USD/3)/FX_USD_per_GBP*(1+RSU_Price_Change_Pct)^(YEAR($A2)-2030),0) -> 0 | E2: =IF($A2=EDATE(DATE(2026,8,1),Inputs!$B$9),Inputs!$B$8,0) -> 3000 | F2: =IF($A2=EDATE(DATE(2026,8,1),Inputs!$B$11),Inputs!$B$10,0) -> 0 | G2: =IF(Inputs!$B$16=1,((IF(YEAR($A2)=2026,Inputs!$B$2,IF(YEAR($A2)=2027,IF(MONTH($A2)>=Inputs!#REF!,Inputs!$B$2*(1+Inputs!$B$4),Inputs!$B$2),IF(YEAR($A2)=2028,IF(MONTH($A2)>=Inputs!#REF!,Inputs!$B$2*(1+Inputs!$B$4)*(1+Inputs!$B$5),Inputs!$B$2*(1+Inputs!$B$4)),IF(YEAR($A2)=2029,IF(MONTH($A2)>=Inputs!#REF!,Inputs!$B$2*(1+Inputs!$B$4)*(1+Inputs!$B$5)*(1+Inputs!$B$6),Inputs!$B$2*(1+Inputs!$B$4)*(1+Inputs!$B$5)),IF(MONTH($A2)>=Inputs!#REF!,Inputs!$B$2*(1+Inputs!$B$4)*(1+Inputs!$B$5)*(1+Inputs!$B$6)*(1+Inputs!$B$7),Inputs!$B$2*(1+Inputs!$B$4)*(1+Inputs!$B$5)*(1+Inputs!$B$6)))))))/12)*(MIN(Inputs!$B$17,Inputs!$B$18)*(1+Inputs!$B$19)+Inputs!$B$17*Inputs!$B$20),0) -> 0 | H2: =SUM(B2:G2) -> 7166.6667 | I2: =$H2-J2-K2 -> 6470 | J2: =_xlfn.SINGLE(_xlfn.LET(_xlpm.d, $A2, _xlpm.ys, YEAR(_xlfn.SINGLE(_xlpm.d)) - IF(MONTH(_xlfn.SINGLE(_xlpm.d)) < UK_TaxYear_Start_Month, 1, 0), _xlpm.start, DATE(_xlfn.SINGLE(_xlpm.ys), UK_TaxYear_Start_Month, 1), _xlpm.m, DATEDIF(_xlfn.SINGLE(_xlpm.start), _xlfn.SINGLE(_xlpm.d), "m") + 1, _xlpm.cum, SUMIFS($H$2:$H$54, $A$2:$A$54, ">=" & _xlfn.SINGLE(_xlpm.start), $A$2:$A$54, "<=" & _xlfn.SINGLE(_xlpm.d)), _xlpm.pa, UK_Personal_Allowance_Annual / 12 * _xlfn.SINGLE(_xlpm.m), _xlpm.br, (UK_Basic_Band_Upper_Annual - UK_Personal_Allowance_Annual) / 12 * _xlfn.SINGLE(_xlpm.m), _xlpm.hr, (UK_Higher_Band_Upper_Annual - UK_Basic_Band_Upper_Annual) / 12 * _xlfn.SINGLE(_xlpm.m), _xlpm.taxable, MAX(0, _xlfn.SINGLE(_xlpm.cum) - _xlfn.SINGLE(_xlpm.pa)), _xlpm.tax_to_date, UK_Basic_Rate * MIN(_xlpm.taxable, _xlpm.br) + UK_Higher_Rate * MIN(MAX(_xlfn.SINGLE(_xlpm.taxable) - _xlfn.SINGLE(_xlpm.br), 0), _xlpm.hr) + UK_Additional_Rate * MAX(_xlfn.SINGLE(_xlpm.taxable) - _xlfn.SINGLE(_xlpm.br) - _xlfn.SINGLE(_xlpm.hr), 0), _xlpm.prior, SUMIFS($J$2:$J$54, $A$2:$A$54, ">=" & _xlfn.SINGLE(_xlpm.start), $A$2:$A$54, "<" & _xlfn.SINGLE(_xlpm.d)), MAX(0, _xlfn.SINGLE(_xlpm.tax_to_date) - _xlfn.SINGLE(_xlpm.prior)))) -> 385.83333 | K2: =_xlfn.SINGLE(_xlfn.LET(_xlpm.g, $H2, _xlpm.pt, UK_NI_PT_Monthly, _xlpm.uel, UK_NI_UEL_Monthly, IF(_xlfn.SINGLE(_xlpm.g) <= _xlfn.SINGLE(_xlpm.pt), 0, UK_NI_Main_Rate * MIN(_xlfn.SINGLE(_xlpm.g) - _xlfn.SINGLE(_xlpm.pt), _xlfn.SINGLE(_xlpm.uel) - _xlfn.SINGLE(_xlpm.pt)) + UK_NI_Upper_Rate * MAX(_xlfn.SINGLE(_xlpm.g) - _xlfn.SINGLE(_xlpm.uel), 0)))) -> 310.83333 | L2: =IF($A2<DATE(2026,10,1),Bonus_Pct_Aug2026_to_Sep2026,IF($A2<DATE(2027,10,1),Bonus_Pct_Oct2026_to_Sep2027,IF($A2<DATE(2028,10,1),Bonus_Pct_Oct2027_to_Sep2028,IF($A2<DATE(2029,10,1),Bonus_Pct_Oct2028_to_Sep2029,Bonus_Pct_Oct2029_onwards)))) -> 0.08
A3: 46266 | B3: =(IF(YEAR($A3)=2026,Base_Annual_Salary_GBP,IF(YEAR($A3)=2027,Base_Annual_Salary_GBP*(IF(MONTH($A3)>=4,(1+Raise_Pct_Apr2027),1)*IF(MONTH($A3)>=10,(1+Raise_Pct_Nov2027),1)),IF(YEAR($A3)=2028,Base_Annual_Salary_GBP*((1+Raise_Pct_Apr2027)*(1+Raise_Pct_Nov2027))*(IF(MONTH($A3)>=4,(1+Raise_Pct_Apr2028),1)*IF(MONTH($A3)>=10,(1+Raise_Pct_Nov2028),1)),IF(YEAR($A3)=2029,Base_Annual_Salary_GBP*((1+Raise_Pct_Apr2027)*(1+Raise_Pct_Nov2027)*(1+Raise_Pct_Apr2028)*(1+Raise_Pct_Nov2028))*(IF(MONTH($A3)>=4,(1+Raise_Pct_Apr2029),1)*IF(MONTH($A3)>=10,(1+Raise_Pct_Nov2029),1)),Base_Annual_Salary_GBP*((1+Raise_Pct_Apr2027)*(1+Raise_Pct_Nov2027)*(1+Raise_Pct_Apr2028)*(1+Raise_Pct_Nov2028)*(1+Raise_Pct_Apr2029)*(1+Raise_Pct_Nov2029))*(IF(MONTH($A3)>=4,(1+Raise_Pct_Apr2030),1)*IF(MONTH($A3)>=10,(1+Raise_Pct_Nov2030),1)))))))/12 -> 4166.6667 | C3: =IF(MONTH($A3)=11,((IF(DATE(YEAR($A3),4,1)<DATE(2026,10,1),Bonus_Pct_Aug2026_to_Sep2026,IF(DATE(YEAR($A3),4,1)<DATE(2027,10,1),Bonus_Pct_Oct2026_to_Sep2027,IF(DATE(YEAR($A3),4,1)<DATE(2028,10,1),Bonus_Pct_Oct2027_to_Sep2028,IF(DATE(YEAR($A3),4,1)<DATE(2029,10,1),Bonus_Pct_Oct2028_to_Sep2029,Bonus_Pct_Oct2029_onwards)))))/2)*($B3*12) / (1 + IF(YEAR($A3)=2027,Raise_Pct_Nov2027,IF(YEAR($A3)=2028,Raise_Pct_Nov2028,IF(YEAR($A3)=2029,Raise_Pct_Nov2029,IF(YEAR($A3)=2030,Raise_Pct_Nov2030,0))))) * IF(YEAR($A3)=2026,2/6,1),IF(MONTH($A3)=5,((IF(DATE(YEAR($A3)-1,10,1)<DATE(2026,10,1),Bonus_Pct_Aug2026_to_Sep2026,IF(DATE(YEAR($A3)-1,10,1)<DATE(2027,10,1),Bonus_Pct_Oct2026_to_Sep2027,IF(DATE(YEAR($A3)-1,10,1)<DATE(2028,10,1),Bonus_Pct_Oct2027_to_Sep2028,IF(DATE(YEAR($A3)-1,10,1)<DATE(2029,10,1),Bonus_Pct_Oct2028_to_Sep2029,Bonus_Pct_Oct2029_onwards)))))/2)*($B3*12) / (1 + IF(YEAR($A3)=2027,Raise_Pct_Apr2027,IF(YEAR($A3)=2028,Raise_Pct_Apr2028,IF(YEAR($A3)=2029,Raise_Pct_Apr2029,IF(YEAR($A3)=2030,Raise_Pct_Apr2030,0))))),0)) -> 0 | D3: =IF(OR($A3=DATE(2027,9,1),$A3=EDATE(DATE(2027,9,1),12),$A3=EDATE(DATE(2027,9,1),24)),(New_Hire_Stock_Grant_USD/3)/FX_USD_per_GBP*(1+IF(YEAR($A3)=2027,Inputs!$B$56,IF(YEAR($A3)=2028,Inputs!$B$57,IF(YEAR($A3)=2029,Inputs!$B$58,0)))),0)+IF(OR($A3=DATE(2028,11,1),$A3=DATE(2029,11,1),$A3=DATE(2030,11,1)),(RSU_Grant_Nov2027_USD/3)/FX_USD_per_GBP*(1+RSU_Price_Change_Pct)^(YEAR($A3)-2028),0)+IF(OR($A3=DATE(2029,11,1),$A3=DATE(2030,11,1)),(RSU_Grant_Nov2028_USD/3)/FX_USD_per_GBP*(1+RSU_Price_Change_Pct)^(YEAR($A3)-2029),0)+IF($A3=DATE(2030,11,1),(RSU_Grant_Nov2029_USD/3)/FX_USD_per_GBP*(1+RSU_Price_Change_Pct)^(YEAR($A3)-2030),0) -> 0 | E3: =IF($A3=EDATE(DATE(2026,8,1),Inputs!$B$9),Inputs!$B$8,0) -> 0 | F3: =IF($A3=EDATE(DATE(2026,8,1),Inputs!$B$11),Inputs!$B$10,0) -> 0 | G3: =IF(Inputs!$B$16=1,((IF(YEAR($A3)=2026,Inputs!$B$2,IF(YEAR($A3)=2027,IF(MONTH($A3)>=Inputs!#REF!,Inputs!$B$2*(1+Inputs!$B$4),Inputs!$B$2),IF(YEAR($A3)=2028,IF(MONTH($A3)>=Inputs!#REF!,Inputs!$B$2*(1+Inputs!$B$4)*(1+Inputs!$B$5),Inputs!$B$2*(1+Inputs!$B$4)),IF(YEAR($A3)=2029,IF(MONTH($A3)>=Inputs!#REF!,Inputs!$B$2*(1+Inputs!$B$4)*(1+Inputs!$B$5)*(1+Inputs!$B$6),Inputs!$B$2*(1+Inputs!$B$4)*(1+Inputs!$B$5)),IF(MONTH($A3)>=Inputs!#REF!,Inputs!$B$2*(1+Inputs!$B$4)*(1+Inputs!$B$5)*(1+Inputs!$B$6)*(1+Inputs!$B$7),Inputs!$B$2*(1+Inputs!$B$4)*(1+Inputs!$B$5)*(1+Inputs!$B$6)))))))/12)*(MIN(Inputs!$B$17,Inputs!$B$18)*(1+Inputs!$B$19)+Inputs!$B$17*Inputs!$B$20),0) -> 0 | H3: =SUM(B3:G3) -> 4166.6667 | I3: =$H3-J3-K3 -> 3293.34 | J3: =_xlfn.SINGLE(_xlfn.LET(_xlpm.d, $A3, _xlpm.ys, YEAR(_xlfn.SINGLE(_xlpm.d)) - IF(MONTH(_xlfn.SINGLE(_xlpm.d)) < UK_TaxYear_Start_Month, 1, 0), _xlpm.start, DATE(_xlfn.SINGLE(_xlpm.ys), UK_TaxYear_Start_Month, 1), _xlpm.m, DATEDIF(_xlfn.SINGLE(_xlpm.start), _xlfn.SINGLE(_xlpm.d), "m") + 1, _xlpm.cum, SUMIFS($H$2:$H$54, $A$2:$A$54, ">=" & _xlfn.SINGLE(_xlpm.start), $A$2:$A$54, "<=" & _xlfn.SINGLE(_xlpm.d)), _xlpm.pa, UK_Personal_Allowance_Annual / 12 * _xlfn.SINGLE(_xlpm.m), _xlpm.br, (UK_Basic_Band_Upper_Annual - UK_Personal_Allowance_Annual) / 12 * _xlfn.SINGLE(_xlpm.m), _xlpm.hr, (UK_Higher_Band_Upper_Annual - UK_Basic_Band_Upper_Annual) / 12 * _xlfn.SINGLE(_xlpm.m), _xlpm.taxable, MAX(0, _xlfn.SINGLE(_xlpm.cum) - _xlfn.SINGLE(_xlpm.pa)), _xlpm.tax_to_date, UK_Basic_Rate * MIN(_xlpm.taxable, _xlpm.br) + UK_Higher_Rate * MIN(MAX(_xlfn.SINGLE(_xlpm.taxable) - _xlfn.SINGLE(_xlpm.br), 0), _xlpm.hr) + UK_Additional_Rate * MAX(_xlfn.SINGLE(_xlpm.taxable) - _xlfn.SINGLE(_xlpm.br) - _xlfn.SINGLE(_xlpm.hr), 0), _xlpm.prior, SUMIFS($J$2:$J$54, $A$2:$A$54, ">=" & _xlfn.SINGLE(_xlpm.start), $A$2:$A$54, "<" & _xlfn.SINGLE(_xlpm.d)), MAX(0, _xlfn.SINGLE(_xlpm.tax_to_date) - _xlfn.SINGLE(_xlpm.prior)))) -> 623.83333 | K3: =_xlfn.SINGLE(_xlfn.LET(_xlpm.g, $H3, _xlpm.pt, UK_NI_PT_Monthly, _xlpm.uel, UK_NI_UEL_Monthly, IF(_xlfn.SINGLE(_xlpm.g) <= _xlfn.SINGLE(_xlpm.pt), 0, UK_NI_Main_Rate * MIN(_xlfn.SINGLE(_xlpm.g) - _xlfn.SINGLE(_xlpm.pt), _xlfn.SINGLE(_xlpm.uel) - _xlfn.SINGLE(_xlpm.pt)) + UK_NI_Upper_Rate * MAX(_xlfn.SINGLE(_xlpm.g) - _xlfn.SINGLE(_xlpm.uel), 0)))) -> 249.49333 | L3: =IF($A3<DATE(2026,10,1),Bonus_Pct_Aug2026_to_Sep2026,IF($A3<DATE(2027,10,1),Bonus_Pct_Oct2026_to_Sep2027,IF($A3<DATE(2028,10,1),Bonus_Pct_Oct2027_to_Sep2028,IF($A3<DATE(2029,10,1),Bonus_Pct_Oct2028_to_Sep2029,Bonus_Pct_Oct2029_onwards)))) -> 0.08
A4: 46296 | B4: =(IF(YEAR($A4)=2026,Base_Annual_Salary_GBP,IF(YEAR($A4)=2027,Base_Annual_Salary_GBP*(IF(MONTH($A4)>=4,(1+Raise_Pct_Apr2027),1)*IF(MONTH($A4)>=10,(1+Raise_Pct_Nov2027),1)),IF(YEAR($A4)=2028,Base_Annual_Salary_GBP*((1+Raise_Pct_Apr2027)*(1+Raise_Pct_Nov2027))*(IF(MONTH($A4)>=4,(1+Raise_Pct_Apr2028),1)*IF(MONTH($A4)>=10,(1+Raise_Pct_Nov2028),1)),IF(YEAR($A4)=2029,Base_Annual_Salary_GBP*((1+Raise_Pct_Apr2027)*(1+Raise_Pct_Nov2027)*(1+Raise_Pct_Apr2028)*(1+Raise_Pct_Nov2028))*(IF(MONTH($A4)>=4,(1+Raise_Pct_Apr2029),1)*IF(MONTH($A4)>=10,(1+Raise_Pct_Nov2029),1)),Base_Annual_Salary_GBP*((1+Raise_Pct_Apr2027)*(1+Raise_Pct_Nov2027)*(1+Raise_Pct_Apr2028)*(1+Raise_Pct_Nov2028)*(1+Raise_Pct_Apr2029)*(1+Raise_Pct_Nov2029))*(IF(MONTH($A4)>=4,(1+Raise_Pct_Apr2030),1)*IF(MONTH($A4)>=10,(1+Raise_Pct_Nov2030),1)))))))/12 -> 4166.6667 | C4: =IF(MONTH($A4)=11,((IF(DATE(YEAR($A4),4,1)<DATE(2026,10,1),Bonus_Pct_Aug2026_to_Sep2026,IF(DATE(YEAR($A4),4,1)<DATE(2027,10,1),Bonus_Pct_Oct2026_to_Sep2027,IF(DATE(YEAR($A4),4,1)<DATE(2028,10,1),Bonus_Pct_Oct2027_to_Sep2028,IF(DATE(YEAR($A4),4,1)<DATE(2029,10,1),Bonus_Pct_Oct2028_to_Sep2029,Bonus_Pct_Oct2029_onwards)))))/2)*($B4*12) / (1 + IF(YEAR($A4)=2027,Raise_Pct_Nov2027,IF(YEAR($A4)=2028,Raise_Pct_Nov2028,IF(YEAR($A4)=2029,Raise_Pct_Nov2029,IF(YEAR($A4)=2030,Raise_Pct_Nov2030,0))))) * IF(YEAR($A4)=2026,2/6,1),IF(MONTH($A4)=5,((IF(DATE(YEAR($A4)-1,10,1)<DATE(2026,10,1),Bonus_Pct_Aug2026_to_Sep2026,IF(DATE(YEAR($A4)-1,10,1)<DATE(2027,10,1),Bonus_Pct_Oct2026_to_Sep2027,IF(DATE(YEAR($A4)-1,10,1)<DATE(2028,10,1),Bonus_Pct_Oct2027_to_Sep2028,IF(DATE(YEAR($A4)-1,10,1)<DATE(2029,10,1),Bonus_Pct_Oct2028_to_Sep2029,Bonus_Pct_Oct2029_onwards)))))/2)*($B4*12) / (1 + IF(YEAR($A4)=2027,Raise_Pct_Apr2027,IF(YEAR($A4)=2028,Raise_Pct_Apr2028,IF(YEAR($A4)=2029,Raise_Pct_Apr2029,IF(YEAR($A4)=2030,Raise_Pct_Apr2030,0))))),0)) -> 0 | D4: =IF(OR($A4=DATE(2027,9,1),$A4=EDATE(DATE(2027,9,1),12),$A4=EDATE(DATE(2027,9,1),24)),(New_Hire_Stock_Grant_USD/3)/FX_USD_per_GBP*(1+IF(YEAR($A4)=2027,Inputs!$B$56,IF(YEAR($A4)=2028,Inputs!$B$57,IF(YEAR($A4)=2029,Inputs!$B$58,0)))),0)+IF(OR($A4=DATE(2028,11,1),$A4=DATE(2029,11,1),$A4=DATE(2030,11,1)),(RSU_Grant_Nov2027_USD/3)/FX_USD_per_GBP*(1+RSU_Price_Change_Pct)^(YEAR($A4)-2028),0)+IF(OR($A4=DATE(2029,11,1),$A4=DATE(2030,11,1)),(RSU_Grant_Nov2028_USD/3)/FX_USD_per_GBP*(1+RSU_Price_Change_Pct)^(YEAR($A4)-2029),0)+IF($A4=DATE(2030,11,1),(RSU_Grant_Nov2029_USD/3)/FX_USD_per_GBP*(1+RSU_Price_Change_Pct)^(YEAR($A4)-2030),0) -> 0 | E4: =IF($A4=EDATE(DATE(2026,8,1),Inputs!$B$9),Inputs!$B$8,0) -> 0 | F4: =IF($A4=EDATE(DATE(2026,8,1),Inputs!$B$11),Inputs!$B$10,0) -> 0 | G4: =IF(Inputs!$B$16=1,((IF(YEAR($A4)=2026,Inputs!$B$2,IF(YEAR($A4)=2027,IF(MONTH($A4)>=Inputs!#REF!,Inputs!$B$2*(1+Inputs!$B$4),Inputs!$B$2),IF(YEAR($A4)=2028,IF(MONTH($A4)>=Inputs!#REF!,Inputs!$B$2*(1+Inputs!$B$4)*(1+Inputs!$B$5),Inputs!$B$2*(1+Inputs!$B$4)),IF(YEAR($A4)=2029,IF(MONTH($A4)>=Inputs!#REF!,Inputs!$B$2*(1+Inputs!$B$4)*(1+Inputs!$B$5)*(1+Inputs!$B$6),Inputs!$B$2*(1+Inputs!$B$4)*(1+Inputs!$B$5)),IF(MONTH($A4)>=Inputs!#REF!,Inputs!$B$2*(1+Inputs!$B$4)*(1+Inputs!$B$5)*(1+Inputs!$B$6)*(1+Inputs!$B$7),Inputs!$B$2*(1+Inputs!$B$4)*(1+Inputs!$B$5)*(1+Inputs!$B$6)))))))/12)*(MIN(Inputs!$B$17,Inputs!$B$18)*(1+Inputs!$B$19)+Inputs!$B$17*Inputs!$B$20),0) -> 0 | H4: =SUM(B4:G4) -> 4166.6667 | I4: =$H4-J4-K4 -> 3293.34 | J4: =_xlfn.SINGLE(_xlfn.LET(_xlpm.d, $A4, _xlpm.ys, YEAR(_xlfn.SINGLE(_xlpm.d)) - IF(MONTH(_xlfn.SINGLE(_xlpm.d)) < UK_TaxYear_Start_Month, 1, 0), _xlpm.start, DATE(_xlfn.SINGLE(_xlpm.ys), UK_TaxYear_Start_Month, 1), _xlpm.m, DATEDIF(_xlfn.SINGLE(_xlpm.start), _xlfn.SINGLE(_xlpm.d), "m") + 1, _xlpm.cum, SUMIFS($H$2:$H$54, $A$2:$A$54, ">=" & _xlfn.SINGLE(_xlpm.start), $A$2:$A$54, "<=" & _xlfn.SINGLE(_xlpm.d)), _xlpm.pa, UK_Personal_Allowance_Annual / 12 * _xlfn.SINGLE(_xlpm.m), _xlpm.br, (UK_Basic_Band_Upper_Annual - UK_Personal_Allowance_Annual) / 12 * _xlfn.SINGLE(_xlpm.m), _xlpm.hr, (UK_Higher_Band_Upper_Annual - UK_Basic_Band_Upper_Annual) / 12 * _xlfn.SINGLE(_xlpm.m), _xlpm.taxable, MAX(0, _xlfn.SINGLE(_xlpm.cum) - _xlfn.SINGLE(_xlpm.pa)), _xlpm.tax_to_date, UK_Basic_Rate * MIN(_xlpm.taxable, _xlpm.br) + UK_Higher_Rate * MIN(MAX(_xlfn.SINGLE(_xlpm.taxable) - _xlfn.SINGLE(_xlpm.br), 0), _xlpm.hr) + UK_Additional_Rate * MAX(_xlfn.SINGLE(_xlpm.taxable) - _xlfn.SINGLE(_xlpm.br) - _xlfn.SINGLE(_xlpm.hr), 0), _xlpm.prior, SUMIFS($J$2:$J$54, $A$2:$A$54, ">=" & _xlfn.SINGLE(_xlpm.start), $A$2:$A$54, "<" & _xlfn.SINGLE(_xlpm.d)), MAX(0, _xlfn.SINGLE(_xlpm.tax_to_date) - _xlfn.SINGLE(_xlpm.prior)))) -> 623.83333 | K4: =_xlfn.SINGLE(_xlfn.LET(_xlpm.g, $H4, _xlpm.pt, UK_NI_PT_Monthly, _xlpm.uel, UK_NI_UEL_Monthly, IF(_xlfn.SINGLE(_xlpm.g) <= _xlfn.SINGLE(_xlpm.pt), 0, UK_NI_Main_Rate * MIN(_xlfn.SINGLE(_xlpm.g) - _xlfn.SINGLE(_xlpm.pt), _xlfn.SINGLE(_xlpm.uel) - _xlfn.SINGLE(_xlpm.pt)) + UK_NI_Upper_Rate * MAX(_xlfn.SINGLE(_xlpm.g) - _xlfn.SINGLE(_xlpm.uel), 0)))) -> 249.49333 | L4: =IF($A4<DATE(2026,10,1),Bonus_Pct_Aug2026_to_Sep2026,IF($A4<DATE(2027,10,1),Bonus_Pct_Oct2026_to_Sep2027,IF($A4<DATE(2028,10,1),Bonus_Pct_Oct2027_to_Sep2028,IF($A4<DATE(2029,10,1),Bonus_Pct_Oct2028_to_Sep2029,Bonus_Pct_Oct2029_onwards)))) -> 0.08
A5: 46327 | B5: =(IF(YEAR($A5)=2026,Base_Annual_Salary_GBP,IF(YEAR($A5)=2027,Base_Annual_Salary_GBP*(IF(MONTH($A5)>=4,(1+Raise_Pct_Apr2027),1)*IF(MONTH($A5)>=10,(1+Raise_Pct_Nov2027),1)),IF(YEAR($A5)=2028,Base_Annual_Salary_GBP*((1+Raise_Pct_Apr2027)*(1+Raise_Pct_Nov2027))*(IF(MONTH($A5)>=4,(1+Raise_Pct_Apr2028),1)*IF(MONTH($A5)>=10,(1+Raise_Pct_Nov2028),1)),IF(YEAR($A5)=2029,Base_Annual_Salary_GBP*((1+Raise_Pct_Apr2027)*(1+Raise_Pct_Nov2027)*(1+Raise_Pct_Apr2028)*(1+Raise_Pct_Nov2028))*(IF(MONTH($A5)>=4,(1+Raise_Pct_Apr2029),1)*IF(MONTH($A5)>=10,(1+Raise_Pct_Nov2029),1)),Base_Annual_Salary_GBP*((1+Raise_Pct_Apr2027)*(1+Raise_Pct_Nov2027)*(1+Raise_Pct_Apr2028)*(1+Raise_Pct_Nov2028)*(1+Raise_Pct_Apr2029)*(1+Raise_Pct_Nov2029))*(IF(MONTH($A5)>=4,(1+Raise_Pct_Apr2030),1)*IF(MONTH($A5)>=10,(1+Raise_Pct_Nov2030),1)))))))/12 -> 4166.6667 | C5: =IF(MONTH($A5)=11,((IF(DATE(YEAR($A5),4,1)<DATE(2026,10,1),Bonus_Pct_Aug2026_to_Sep2026,IF(DATE(YEAR($A5),4,1)<DATE(2027,10,1),Bonus_Pct_Oct2026_to_Sep2027,IF(DATE(YEAR($A5),4,1)<DATE(2028,10,1),Bonus_Pct_Oct2027_to_Sep2028,IF(DATE(YEAR($A5),4,1)<DATE(2029,10,1),Bonus_Pct_Oct2028_to_Sep2029,Bonus_Pct_Oct2029_onwards)))))/2)*($B5*12) / (1 + IF(YEAR($A5)=2027,Raise_Pct_Nov2027,IF(YEAR($A5)=2028,Raise_Pct_Nov2028,IF(YEAR($A5)=2029,Raise_Pct_Nov2029,IF(YEAR($A5)=2030,Raise_Pct_Nov2030,0))))) * IF(YEAR($A5)=2026,2/6,1),IF(MONTH($A5)=5,((IF(DATE(YEAR($A5)-1,10,1)<DATE(2026,10,1),Bonus_Pct_Aug2026_to_Sep2026,IF(DATE(YEAR($A5)-1,10,1)<DATE(2027,10,1),Bonus_Pct_Oct2026_to_Sep2027,IF(DATE(YEAR($A5)-1,10,1)<DATE(2028,10,1),Bonus_Pct_Oct2027_to_Sep2028,IF(DATE(YEAR($A5)-1,10,1)<DATE(2029,10,1),Bonus_Pct_Oct2028_to_Sep2029,Bonus_Pct_Oct2029_onwards)))))/2)*($B5*12) / (1 + IF(YEAR($A5)=2027,Raise_Pct_Apr2027,IF(YEAR($A5)=2028,Raise_Pct_Apr2028,IF(YEAR($A5)=2029,Raise_Pct_Apr2029,IF(YEAR($A5)=2030,Raise_Pct_Apr2030,0))))),0)) -> 666.66667 | D5: =IF(OR($A5=DATE(2027,9,1),$A5=EDATE(DATE(2027,9,1),12),$A5=EDATE(DATE(2027,9,1),24)),(New_Hire_Stock_Grant_USD/3)/FX_USD_per_GBP*(1+IF(YEAR($A5)=2027,Inputs!$B$56,IF(YEAR($A5)=2028,Inputs!$B$57,IF(YEAR($A5)=2029,Inputs!$B$58,0)))),0)+IF(OR($A5=DATE(2028,11,1),$A5=DATE(2029,11,1),$A5=DATE(2030,11,1)),(RSU_Grant_Nov2027_USD/3)/FX_USD_per_GBP*(1+RSU_Price_Change_Pct)^(YEAR($A5)-2028),0)+IF(OR($A5=DATE(2029,11,1),$A5=DATE(2030,11,1)),(RSU_Grant_Nov2028_USD/3)/FX_USD_per_GBP*(1+RSU_Price_Change_Pct)^(YEAR($A5)-2029),0)+IF($A5=DATE(2030,11,1),(RSU_Grant_Nov2029_USD/3)/FX_USD_per_GBP*(1+RSU_Price_Change_Pct)^(YEAR($A5)-2030),0) -> 0 | E5: =IF($A5=EDATE(DATE(2026,8,1),Inputs!$B$9),Inputs!$B$8,0) -> 0 | F5: =IF($A5=EDATE(DATE(2026,8,1),Inputs!$B$11),Inputs!$B$10,0) -> 0 | G5: =IF(Inputs!$B$16=1,((IF(YEAR($A5)=2026,Inputs!$B$2,IF(YEAR($A5)=2027,IF(MONTH($A5)>=Inputs!#REF!,Inputs!$B$2*(1+Inputs!$B$4),Inputs!$B$2),IF(YEAR($A5)=2028,IF(MONTH($A5)>=Inputs!#REF!,Inputs!$B$2*(1+Inputs!$B$4)*(1+Inputs!$B$5),Inputs!$B$2*(1+Inputs!$B$4)),IF(YEAR($A5)=2029,IF(MONTH($A5)>=Inputs!#REF!,Inputs!$B$2*(1+Inputs!$B$4)*(1+Inputs!$B$5)*(1+Inputs!$B$6),Inputs!$B$2*(1+Inputs!$B$4)*(1+Inputs!$B$5)),IF(MONTH($A5)>=Inputs!#REF!,Inputs!$B$2*(1+Inputs!$B$4)*(1+Inputs!$B$5)*(1+Inputs!$B$6)*(1+Inputs!$B$7),Inputs!$B$2*(1+Inputs!$B$4)*(1+Inputs!$B$5)*(1+Inputs!$B$6)))))))/12)*(MIN(Inputs!$B$17,Inputs!$B$18)*(1+Inputs!$B$19)+Inputs!$B$17*Inputs!$B$20),0) -> 0 | H5: =SUM(B5:G5) -> 4833.3333 | I5: =$H5-J5-K5 -> 3812 | J5: =_xlfn.SINGLE(_xlfn.LET(_xlpm.d, $A5, _xlpm.ys, YEAR(_xlfn.SINGLE(_xlpm.d)) - IF(MONTH(_xlfn.SINGLE(_xlpm.d)) < UK_TaxYear_Start_Month, 1, 0), _xlpm.start, DATE(_xlfn.SINGLE(_xlpm.ys), UK_TaxYear_Start_Month, 1), _xlpm.m, DATEDIF(_xlfn.SINGLE(_xlpm.start), _xlfn.SINGLE(_xlpm.d), "m") + 1, _xlpm.cum, SUMIFS($H$2:$H$54, $A$2:$A$54, ">=" & _xlfn.SINGLE(_xlpm.start), $A$2:$A$54, "<=" & _xlfn.SINGLE(_xlpm.d)), _xlpm.pa, UK_Personal_Allowance_Annual / 12 * _xlfn.SINGLE(_xlpm.m), _xlpm.br, (UK_Basic_Band_Upper_Annual - UK_Personal_Allowance_Annual) / 12 * _xlfn.SINGLE(_xlpm.m), _xlpm.hr, (UK_Higher_Band_Upper_Annual - UK_Basic_Band_Upper_Annual) / 12 * _xlfn.SINGLE(_xlpm.m), _xlpm.taxable, MAX(0, _xlfn.SINGLE(_xlpm.cum) - _xlfn.SINGLE(_xlpm.pa)), _xlpm.tax_to_date, UK_Basic_Rate * MIN(_xlpm.taxable, _xlpm.br) + UK_Higher_Rate * MIN(MAX(_xlfn.SINGLE(_xlpm.taxable) - _xlfn.SINGLE(_xlpm.br), 0), _xlpm.hr) + UK_Additional_Rate * MAX(_xlfn.SINGLE(_xlpm.taxable) - _xlfn.SINGLE(_xlpm.br) - _xlfn.SINGLE(_xlpm.hr), 0), _xlpm.prior, SUMIFS($J$2:$J$54, $A$2:$A$54, ">=" & _xlfn.SINGLE(_xlpm.start), $A$2:$A$54, "<" & _xlfn.SINGLE(_xlpm.d)), MAX(0, _xlfn.SINGLE(_xlpm.tax_to_date) - _xlfn.SINGLE(_xlpm.prior)))) -> 757.16667 | K5: =_xlfn.SINGLE(_xlfn.LET(_xlpm.g, $H5, _xlpm.pt, UK_NI_PT_Monthly, _xlpm.uel, UK_NI_UEL_Monthly, IF(_xlfn.SINGLE(_xlpm.g) <= _xlfn.SINGLE(_xlpm.pt), 0, UK_NI_Main_Rate * MIN(_xlfn.SINGLE(_xlpm.g) - _xlfn.SINGLE(_xlpm.pt), _xlfn.SINGLE(_xlpm.uel) - _xlfn.SINGLE(_xlpm.pt)) + UK_NI_Upper_Rate * MAX(_xlfn.SINGLE(_xlpm.g) - _xlfn.SINGLE(_xlpm.uel), 0)))) -> 264.16667 | L5: =IF($A5<DATE(2026,10,1),Bonus_Pct_Aug2026_to_Sep2026,IF($A5<DATE(2027,10,1),Bonus_Pct_Oct2026_to_Sep2027,IF($A5<DATE(2028,10,1),Bonus_Pct_Oct2027_to_Sep2028,IF($A5<DATE(2029,10,1),Bonus_Pct_Oct2028_to_Sep2029,Bonus_Pct_Oct2029_onwards)))) -> 0.08
A6: 46357 | B6: =(IF(YEAR($A6)=2026,Base_Annual_Salary_GBP,IF(YEAR($A6)=2027,Base_Annual_Salary_GBP*(IF(MONTH($A6)>=4,(1+Raise_Pct_Apr2027),1)*IF(MONTH($A6)>=10,(1+Raise_Pct_Nov2027),1)),IF(YEAR($A6)=2028,Base_Annual_Salary_GBP*((1+Raise_Pct_Apr2027)*(1+Raise_Pct_Nov2027))*(IF(MONTH($A6)>=4,(1+Raise_Pct_Apr2028),1)*IF(MONTH($A6)>=10,(1+Raise_Pct_Nov2028),1)),IF(YEAR($A6)=2029,Base_Annual_Salary_GBP*((1+Raise_Pct_Apr2027)*(1+Raise_Pct_Nov2027)*(1+Raise_Pct_Apr2028)*(1+Raise_Pct_Nov2028))*(IF(MONTH($A6)>=4,(1+Raise_Pct_Apr2029),1)*IF(MONTH($A6)>=10,(1+Raise_Pct_Nov2029),1)),Base_Annual_Salary_GBP*((1+Raise_Pct_Apr2027)*(1+Raise_Pct_Nov2027)*(1+Raise_Pct_Apr2028)*(1+Raise_Pct_Nov2028)*(1+Raise_Pct_Apr2029)*(1+Raise_Pct_Nov2029))*(IF(MONTH($A6)>=4,(1+Raise_Pct_Apr2030),1)*IF(MONTH($A6)>=10,(1+Raise_Pct_Nov2030),1)))))))/12 -> 4166.6667 | C6: =IF(MONTH($A6)=11,((IF(DATE(YEAR($A6),4,1)<DATE(2026,10,1),Bonus_Pct_Aug2026_to_Sep2026,IF(DATE(YEAR($A6),4,1)<DATE(2027,10,1),Bonus_Pct_Oct2026_to_Sep2027,IF(DATE(YEAR($A6),4,1)<DATE(2028,10,1),Bonus_Pct_Oct2027_to_Sep2028,IF(DATE(YEAR($A6),4,1)<DATE(2029,10,1),Bonus_Pct_Oct2028_to_Sep2029,Bonus_Pct_Oct2029_onwards)))))/2)*($B6*12) / (1 + IF(YEAR($A6)=2027,Raise_Pct_Nov2027,IF(YEAR($A6)=2028,Raise_Pct_Nov2028,IF(YEAR($A6)=2029,Raise_Pct_Nov2029,IF(YEAR($A6)=2030,Raise_Pct_Nov2030,0))))) * IF(YEAR($A6)=2026,2/6,1),IF(MONTH($A6)=5,((IF(DATE(YEAR($A6)-1,10,1)<DATE(2026,10,1),Bonus_Pct_Aug2026_to_Sep2026,IF(DATE(YEAR($A6)-1,10,1)<DATE(2027,10,1),Bonus_Pct_Oct2026_to_Sep2027,IF(DATE(YEAR($A6)-1,10,1)<DATE(2028,10,1),Bonus_Pct_Oct2027_to_Sep2028,IF(DATE(YEAR($A6)-1,10,1)<DATE(2029,10,1),Bonus_Pct_Oct2028_to_Sep2029,Bonus_Pct_Oct2029_onwards)))))/2)*($B6*12) / (1 + IF(YEAR($A6)=2027,Raise_Pct_Apr2027,IF(YEAR($A6)=2028,Raise_Pct_Apr2028,IF(YEAR($A6)=2029,Raise_Pct_Apr2029,IF(YEAR($A6)=2030,Raise_Pct_Apr2030,0))))),0)) -> 0 | D6: =IF(OR($A6=DATE(2027,9,1),$A6=EDATE(DATE(2027,9,1),12),$A6=EDATE(DATE(2027,9,1),24)),(New_Hire_Stock_Grant_USD/3)/FX_USD_per_GBP*(1+IF(YEAR($A6)=2027,Inputs!$B$56,IF(YEAR($A6)=2028,Inputs!$B$57,IF(YEAR($A6)=2029,Inputs!$B$58,0)))),0)+IF(OR($A6=DATE(2028,11,1),$A6=DATE(2029,11,1),$A6=DATE(2030,11,1)),(RSU_Grant_Nov2027_USD/3)/FX_USD_per_GBP*(1+RSU_Price_Change_Pct)^(YEAR($A6)-2028),0)+IF(OR($A6=DATE(2029,11,1),$A6=DATE(2030,11,1)),(RSU_Grant_Nov2028_USD/3)/FX_USD_per_GBP*(1+RSU_Price_Change_Pct)^(YEAR($A6)-2029),0)+IF($A6=DATE(2030,11,1),(RSU_Grant_Nov2029_USD/3)/FX_USD_per_GBP*(1+RSU_Price_Change_Pct)^(YEAR($A6)-2030),0) -> 0 | E6: =IF($A6=EDATE(DATE(2026,8,1),Inputs!$B$9),Inputs!$B$8,0) -> 0 | F6: =IF($A6=EDATE(DATE(2026,8,1),Inputs!$B$11),Inputs!$B$10,0) -> 0 | G6: =IF(Inputs!$B$16=1,((IF(YEAR($A6)=2026,Inputs!$B$2,IF(YEAR($A6)=2027,IF(MONTH($A6)>=Inputs!#REF!,Inputs!$B$2*(1+Inputs!$B$4),Inputs!$B$2),IF(YEAR($A6)=2028,IF(MONTH($A6)>=Inputs!#REF!,Inputs!$B$2*(1+Inputs!$B$4)*(1+Inputs!$B$5),Inputs!$B$2*(1+Inputs!$B$4)),IF(YEAR($A6)=2029,IF(MONTH($A6)>=Inputs!#REF!,Inputs!$B$2*(1+Inputs!$B$4)*(1+Inputs!$B$5)*(1+Inputs!$B$6),Inputs!$B$2*(1+Inputs!$B$4)*(1+Inputs!$B$5)),IF(MONTH($A6)>=Inputs!#REF!,Inputs!$B$2*(1+Inputs!$B$4)*(1+Inputs!$B$5)*(1+Inputs!$B$6)*(1+Inputs!$B$7),Inputs!$B$2*(1+Inputs!$B$4)*(1+Inputs!$B$5)*(1+Inputs!$B$6)))))))/12)*(MIN(Inputs!$B$17,Inputs!$B$18)*(1+Inputs!$B$19)+Inputs!$B$17*Inputs!$B$20),0) -> 0 | H6: =SUM(B6:G6) -> 4166.6667 | I6: =$H6-J6-K6 -> 3293.34 | J6: =_xlfn.SINGLE(_xlfn.LET(_xlpm.d, $A6, _xlpm.ys, YEAR(_xlfn.SINGLE(_xlpm.d)) - IF(MONTH(_xlfn.SINGLE(_xlpm.d)) < UK_TaxYear_Start_Month, 1, 0), _xlpm.start, DATE(_xlfn.SINGLE(_xlpm.ys), UK_TaxYear_Start_Month, 1), _xlpm.m, DATEDIF(_xlfn.SINGLE(_xlpm.start), _xlfn.SINGLE(_xlpm.d), "m") + 1, _xlpm.cum, SUMIFS($H$2:$H$54, $A$2:$A$54, ">=" & _xlfn.SINGLE(_xlpm.start), $A$2:$A$54, "<=" & _xlfn.SINGLE(_xlpm.d)), _xlpm.pa, UK_Personal_Allowance_Annual / 12 * _xlfn.SINGLE(_xlpm.m), _xlpm.br, (UK_Basic_Band_Upper_Annual - UK_Personal_Allowance_Annual) / 12 * _xlfn.SINGLE(_xlpm.m), _xlpm.hr, (UK_Higher_Band_Upper_Annual - UK_Basic_Band_Upper_Annual) / 12 * _xlfn.SINGLE(_xlpm.m), _xlpm.taxable, MAX(0, _xlfn.SINGLE(_xlpm.cum) - _xlfn.SINGLE(_xlpm.pa)), _xlpm.tax_to_date, UK_Basic_Rate * MIN(_xlpm.taxable, _xlpm.br) + UK_Higher_Rate * MIN(MAX(_xlfn.SINGLE(_xlpm.taxable) - _xlfn.SINGLE(_xlpm.br), 0), _xlpm.hr) + UK_Additional_Rate * MAX(_xlfn.SINGLE(_xlpm.taxable) - _xlfn.SINGLE(_xlpm.br) - _xlfn.SINGLE(_xlpm.hr), 0), _xlpm.prior, SUMIFS($J$2:$J$54, $A$2:$A$54, ">=" & _xlfn.SINGLE(_xlpm.start), $A$2:$A$54, "<" & _xlfn.SINGLE(_xlpm.d)), MAX(0, _xlfn.SINGLE(_xlpm.tax_to_date) - _xlfn.SINGLE(_xlpm.prior)))) -> 623.83333 | K6: =_xlfn.SINGLE(_xlfn.LET(_xlpm.g, $H6, _xlpm.pt, UK_NI_PT_Monthly, _xlpm.uel, UK_NI_UEL_Monthly, IF(_xlfn.SINGLE(_xlpm.g) <= _xlfn.SINGLE(_xlpm.pt), 0, UK_NI_Main_Rate * MIN(_xlfn.SINGLE(_xlpm.g) - _xlfn.SINGLE(_xlpm.pt), _xlfn.SINGLE(_xlpm.uel) - _xlfn.SINGLE(_xlpm.pt)) + UK_NI_Upper_Rate * MAX(_xlfn.SINGLE(_xlpm.g) - _xlfn.SINGLE(_xlpm.uel), 0)))) -> 249.49333 | L6: =IF($A6<DATE(2026,10,1),Bonus_Pct_Aug2026_to_Sep2026,IF($A6<DATE(2027,10,1),Bonus_Pct_Oct2026_to_Sep2027,IF($A6<DATE(2028,10,1),Bonus_Pct_Oct2027_to_Sep2028,IF($A6<DATE(2029,10,1),Bonus_Pct_Oct2028_to_Sep2029,Bonus_Pct_Oct2029_onwards)))) -> 0.08 | M6: Total Net in 2026 | N6: =SUM(I2:I6) -> 20162.02
A7: 46388 | B7: =(IF(YEAR($A7)=2026,Base_Annual_Salary_GBP,IF(YEAR($A7)=2027,Base_Annual_Salary_GBP*(IF(MONTH($A7)>=4,(1+Raise_Pct_Apr2027),1)*IF(MONTH($A7)>=10,(1+Raise_Pct_Nov2027),1)),IF(YEAR($A7)=2028,Base_Annual_Salary_GBP*((1+Raise_Pct_Apr2027)*(1+Raise_Pct_Nov2027))*(IF(MONTH($A7)>=4,(1+Raise_Pct_Apr2028),1)*IF(MONTH($A7)>=10,(1+Raise_Pct_Nov2028),1)),IF(YEAR($A7)=2029,Base_Annual_Salary_GBP*((1+Raise_Pct_Apr2027)*(1+Raise_Pct_Nov2027)*(1+Raise_Pct_Apr2028)*(1+Raise_Pct_Nov2028))*(IF(MONTH($A7)>=4,(1+Raise_Pct_Apr2029),1)*IF(MONTH($A7)>=10,(1+Raise_Pct_Nov2029),1)),Base_Annual_Salary_GBP*((1+Raise_Pct_Apr2027)*(1+Raise_Pct_Nov2027)*(1+Raise_Pct_Apr2028)*(1+Raise_Pct_Nov2028)*(1+Raise_Pct_Apr2029)*(1+Raise_Pct_Nov2029))*(IF(MONTH($A7)>=4,(1+Raise_Pct_Apr2030),1)*IF(MONTH($A7)>=10,(1+Raise_Pct_Nov2030),1)))))))/12 -> 4166.6667 | C7: =IF(MONTH($A7)=11,((IF(DATE(YEAR($A7),4,1)<DATE(2026,10,1),Bonus_Pct_Aug2026_to_Sep2026,IF(DATE(YEAR($A7),4,1)<DATE(2027,10,1),Bonus_Pct_Oct2026_to_Sep2027,IF(DATE(YEAR($A7),4,1)<DATE(2028,10,1),Bonus_Pct_Oct2027_to_Sep2028,IF(DATE(YEAR($A7),4,1)<DATE(2029,10,1),Bonus_Pct_Oct2028_to_Sep2029,Bonus_Pct_Oct2029_onwards)))))/2)*($B7*12) / (1 + IF(YEAR($A7)=2027,Raise_Pct_Nov2027,IF(YEAR($A7)=2028,Raise_Pct_Nov2028,IF(YEAR($A7)=2029,Raise_Pct_Nov2029,IF(YEAR($A7)=2030,Raise_Pct_Nov2030,0))))) * IF(YEAR($A7)=2026,2/6,1),IF(MONTH($A7)=5,((IF(DATE(YEAR($A7)-1,10,1)<DATE(2026,10,1),Bonus_Pct_Aug2026_to_Sep2026,IF(DATE(YEAR($A7)-1,10,1)<DATE(2027,10,1),Bonus_Pct_Oct2026_to_Sep2027,IF(DATE(YEAR($A7)-1,10,1)<DATE(2028,10,1),Bonus_Pct_Oct2027_to_Sep2028,IF(DATE(YEAR($A7)-1,10,1)<DATE(2029,10,1),Bonus_Pct_Oct2028_to_Sep2029,Bonus_Pct_Oct2029_onwards)))))/2)*($B7*12) / (1 + IF(YEAR($A7)=2027,Raise_Pct_Apr2027,IF(YEAR($A7)=2028,Raise_Pct_Apr2028,IF(YEAR($A7)=2029,Raise_Pct_Apr2029,IF(YEAR($A7)=2030,Raise_Pct_Apr2030,0))))),0)) -> 0 | D7: =IF(OR($A7=DATE(2027,9,1),$A7=EDATE(DATE(2027,9,1),12),$A7=EDATE(DATE(2027,9,1),24)),(New_Hire_Stock_Grant_USD/3)/FX_USD_per_GBP*(1+IF(YEAR($A7)=2027,Inputs!$B$56,IF(YEAR($A7)=2028,Inputs!$B$57,IF(YEAR($A7)=2029,Inputs!$B$58,0)))),0)+IF(OR($A7=DATE(2028,11,1),$A7=DATE(2029,11,1),$A7=DATE(2030,11,1)),(RSU_Grant_Nov2027_USD/3)/FX_USD_per_GBP*(1+RSU_Price_Change_Pct)^(YEAR($A7)-2028),0)+IF(OR($A7=DATE(2029,11,1),$A7=DATE(2030,11,1)),(RSU_Grant_Nov2028_USD/3)/FX_USD_per_GBP*(1+RSU_Price_Change_Pct)^(YEAR($A7)-2029),0)+IF($A7=DATE(2030,11,1),(RSU_Grant_Nov2029_USD/3)/FX_USD_per_GBP*(1+RSU_Price_Change_Pct)^(YEAR($A7)-2030),0) -> 0 | E7: =IF($A7=EDATE(DATE(2026,8,1),Inputs!$B$9),Inputs!$B$8,0) -> 0 | F7: =IF($A7=EDATE(DATE(2026,8,1),Inputs!$B$11),Inputs!$B$10,0) -> 0 | G7: =IF(Inputs!$B$16=1,((IF(YEAR($A7)=2026,Inputs!$B$2,IF(YEAR($A7)=2027,IF(MONTH($A7)>=Inputs!#REF!,Inputs!$B$2*(1+Inputs!$B$4),Inputs!$B$2),IF(YEAR($A7)=2028,IF(MONTH($A7)>=Inputs!#REF!,Inputs!$B$2*(1+Inputs!$B$4)*(1+Inputs!$B$5),Inputs!$B$2*(1+Inputs!$B$4)),IF(YEAR($A7)=2029,IF(MONTH($A7)>=Inputs!#REF!,Inputs!$B$2*(1+Inputs!$B$4)*(1+Inputs!$B$5)*(1+Inputs!$B$6),Inputs!$B$2*(1+Inputs!$B$4)*(1+Inputs!$B$5)),IF(MONTH($A7)>=Inputs!#REF!,Inputs!$B$2*(1+Inputs!$B$4)*(1+Inputs!$B$5)*(1+Inputs!$B$6)*(1+Inputs!$B$7),Inputs!$B$2*(1+Inputs!$B$4)*(1+Inputs!$B$5)*(1+Inputs!$B$6)))))))/12)*(MIN(Inputs!$B$17,Inputs!$B$18)*(1+Inputs!$B$19)+Inputs!$B$17*Inputs!$B$20),0) -> 0 | H7: =SUM(B7:G7) -> 4166.6667 | I7: =$H7-J7-K7 -> 3293.34 | J7: =_xlfn.SINGLE(_xlfn.LET(_xlpm.d, $A7, _xlpm.ys, YEAR(_xlfn.SINGLE(_xlpm.d)) - IF(MONTH(_xlfn.SINGLE(_xlpm.d)) < UK_TaxYear_Start_Month, 1, 0), _xlpm.start, DATE(_xlfn.SINGLE(_xlpm.ys), UK_TaxYear_Start_Month, 1), _xlpm.m, DATEDIF(_xlfn.SINGLE(_xlpm.start), _xlfn.SINGLE(_xlpm.d), "m") + 1, _xlpm.cum, SUMIFS($H$2:$H$54, $A$2:$A$54, ">=" & _xlfn.SINGLE(_xlpm.start), $A$2:$A$54, "<=" & _xlfn.SINGLE(_xlpm.d)), _xlpm.pa, UK_Personal_Allowance_Annual / 12 * _xlfn.SINGLE(_xlpm.m), _xlpm.br, (UK_Basic_Band_Upper_Annual - UK_Personal_Allowance_Annual) / 12 * _xlfn.SINGLE(_xlpm.m), _xlpm.hr, (UK_Higher_Band_Upper_Annual - UK_Basic_Band_Upper_Annual) / 12 * _xlfn.SINGLE(_xlpm.m), _xlpm.taxable, MAX(0, _xlfn.SINGLE(_xlpm.cum) - _xlfn.SINGLE(_xlpm.pa)), _xlpm.tax_to_date, UK_Basic_Rate * MIN(_xlpm.taxable, _xlpm.br) + UK_Higher_Rate * MIN(MAX(_xlfn.SINGLE(_xlpm.taxable) - _xlfn.SINGLE(_xlpm.br), 0), _xlpm.hr) + UK_Additional_Rate * MAX(_xlfn.SINGLE(_xlpm.taxable) - _xlfn.SINGLE(_xlpm.br) - _xlfn.SINGLE(_xlpm.hr), 0), _xlpm.prior, SUMIFS($J$2:$J$54, $A$2:$A$54, ">=" & _xlfn.SINGLE(_xlpm.start), $A$2:$A$54, "<" & _xlfn.SINGLE(_xlpm.d)), MAX(0, _xlfn.SINGLE(_xlpm.tax_to_date) - _xlfn.SINGLE(_xlpm.prior)))) -> 623.83333 | K7: =_xlfn.SINGLE(_xlfn.LET(_xlpm.g, $H7, _xlpm.pt, UK_NI_PT_Monthly, _xlpm.uel, UK_NI_UEL_Monthly, IF(_xlfn.SINGLE(_xlpm.g) <= _xlfn.SINGLE(_xlpm.pt), 0, UK_NI_Main_Rate * MIN(_xlfn.SINGLE(_xlpm.g) - _xlfn.SINGLE(_xlpm.pt), _xlfn.SINGLE(_xlpm.uel) - _xlfn.SINGLE(_xlpm.pt)) + UK_NI_Upper_Rate * MAX(_xlfn.SINGLE(_xlpm.g) - _xlfn.SINGLE(_xlpm.uel), 0)))) -> 249.49333 | L7: =IF($A7<DATE(2026,10,1),Bonus_Pct_Aug2026_to_Sep2026,IF($A7<DATE(2027,10,1),Bonus_Pct_Oct2026_to_Sep2027,IF($A7<DATE(2028,10,1),Bonus_Pct_Oct2027_to_Sep2028,IF($A7<DATE(2029,10,1),Bonus_Pct_Oct2028_to_Sep2029,Bonus_Pct_Oct2029_onwards)))) -> 0.08 | M7: Total Net in 2027 | N7: =SUM(I7:I18) -> 46820.526
A8: 46419 | B8: =(IF(YEAR($A8)=2026,Base_Annual_Salary_GBP,IF(YEAR($A8)=2027,Base_Annual_Salary_GBP*(IF(MONTH($A8)>=4,(1+Raise_Pct_Apr2027),1)*IF(MONTH($A8)>=10,(1+Raise_Pct_Nov2027),1)),IF(YEAR($A8)=2028,Base_Annual_Salary_GBP*((1+Raise_Pct_Apr2027)*(1+Raise_Pct_Nov2027))*(IF(MONTH($A8)>=4,(1+Raise_Pct_Apr2028),1)*IF(MONTH($A8)>=10,(1+Raise_Pct_Nov2028),1)),IF(YEAR($A8)=2029,Base_Annual_Salary_GBP*((1+Raise_Pct_Apr2027)*(1+Raise_Pct_Nov2027)*(1+Raise_Pct_Apr2028)*(1+Raise_Pct_Nov2028))*(IF(MONTH($A8)>=4,(1+Raise_Pct_Apr2029),1)*IF(MONTH($A8)>=10,(1+Raise_Pct_Nov2029),1)),Base_Annual_Salary_GBP*((1+Raise_Pct_Apr2027)*(1+Raise_Pct_Nov2027)*(1+Raise_Pct_Apr2028)*(1+Raise_Pct_Nov2028)*(1+Raise_Pct_Apr2029)*(1+Raise_Pct_Nov2029))*(IF(MONTH($A8)>=4,(1+Raise_Pct_Apr2030),1)*IF(MONTH($A8)>=10,(1+Raise_Pct_Nov2030),1)))))))/12 -> 4166.6667 | C8: =IF(MONTH($A8)=11,((IF(DATE(YEAR($A8),4,1)<DATE(2026,10,1),Bonus_Pct_Aug2026_to_Sep2026,IF(DATE(YEAR($A8),4,1)<DATE(2027,10,1),Bonus_Pct_Oct2026_to_Sep2027,IF(DATE(YEAR($A8),4,1)<DATE(2028,10,1),Bonus_Pct_Oct2027_to_Sep2028,IF(DATE(YEAR($A8),4,1)<DATE(2029,10,1),Bonus_Pct_Oct2028_to_Sep2029,Bonus_Pct_Oct2029_onwards)))))/2)*($B8*12) / (1 + IF(YEAR($A8)=2027,Raise_Pct_Nov2027,IF(YEAR($A8)=2028,Raise_Pct_Nov2028,IF(YEAR($A8)=2029,Raise_Pct_Nov2029,IF(YEAR($A8)=2030,Raise_Pct_Nov2030,0))))) * IF(YEAR($A8)=2026,2/6,1),IF(MONTH($A8)=5,((IF(DATE(YEAR($A8)-1,10,1)<DATE(2026,10,1),Bonus_Pct_Aug2026_to_Sep2026,IF(DATE(YEAR($A8)-1,10,1)<DATE(2027,10,1),Bonus_Pct_Oct2026_to_Sep2027,IF(DATE(YEAR($A8)-1,10,1)<DATE(2028,10,1),Bonus_Pct_Oct2027_to_Sep2028,IF(DATE(YEAR($A8)-1,10,1)<DATE(2029,10,1),Bonus_Pct_Oct2028_to_Sep2029,Bonus_Pct_Oct2029_onwards)))))/2)*($B8*12) / (1 + IF(YEAR($A8)=2027,Raise_Pct_Apr2027,IF(YEAR($A8)=2028,Raise_Pct_Apr2028,IF(YEAR($A8)=2029,Raise_Pct_Apr2029,IF(YEAR($A8)=2030,Raise_Pct_Apr2030,0))))),0)) -> 0 | D8: =IF(OR($A8=DATE(2027,9,1),$A8=EDATE(DATE(2027,9,1),12),$A8=EDATE(DATE(2027,9,1),24)),(New_Hire_Stock_Grant_USD/3)/FX_USD_per_GBP*(1+IF(YEAR($A8)=2027,Inputs!$B$56,IF(YEAR($A8)=2028,Inputs!$B$57,IF(YEAR($A8)=2029,Inputs!$B$58,0)))),0)+IF(OR($A8=DATE(2028,11,1),$A8=DATE(2029,11,1),$A8=DATE(2030,11,1)),(RSU_Grant_Nov2027_USD/3)/FX_USD_per_GBP*(1+RSU_Price_Change_Pct)^(YEAR($A8)-2028),0)+IF(OR($A8=DATE(2029,11,1),$A8=DATE(2030,11,1)),(RSU_Grant_Nov2028_USD/3)/FX_USD_per_GBP*(1+RSU_Price_Change_Pct)^(YEAR($A8)-2029),0)+IF($A8=DATE(2030,11,1),(RSU_Grant_Nov2029_USD/3)/FX_USD_per_GBP*(1+RSU_Price_Change_Pct)^(YEAR($A8)-2030),0) -> 0 | E8: =IF($A8=EDATE(DATE(2026,8,1),Inputs!$B$9),Inputs!$B$8,0) -> 0 | F8: =IF($A8=EDATE(DATE(2026,8,1),Inputs!$B$11),Inputs!$B$10,0) -> 0 | G8: =IF(Inputs!$B$16=1,((IF(YEAR($A8)=2026,Inputs!$B$2,IF(YEAR($A8)=2027,IF(MONTH($A8)>=Inputs!#REF!,Inputs!$B$2*(1+Inputs!$B$4),Inputs!$B$2),IF(YEAR($A8)=2028,IF(MONTH($A8)>=Inputs!#REF!,Inputs!$B$2*(1+Inputs!$B$4)*(1+Inputs!$B$5),Inputs!$B$2*(1+Inputs!$B$4)),IF(YEAR($A8)=2029,IF(MONTH($A8)>=Inputs!#REF!,Inputs!$B$2*(1+Inputs!$B$4)*(1+Inputs!$B$5)*(1+Inputs!$B$6),Inputs!$B$2*(1+Inputs!$B$4)*(1+Inputs!$B$5)),IF(MONTH($A8)>=Inputs!#REF!,Inputs!$B$2*(1+Inputs!$B$4)*(1+Inputs!$B$5)*(1+Inputs!$B$6)*(1+Inputs!$B$7),Inputs!$B$2*(1+Inputs!$B$4)*(1+Inputs!$B$5)*(1+Inputs!$B$6)))))))/12)*(MIN(Inputs!$B$17,Inputs!$B$18)*(1+Inputs!$B$19)+Inputs!$B$17*Inputs!$B$20),0) -> 0 | H8: =SUM(B8:G8) -> 4166.6667 | I8: =$H8-J8-K8 -> 3293.34 | J8: =_xlfn.SINGLE(_xlfn.LET(_xlpm.d, $A8, _xlpm.ys, YEAR(_xlfn.SINGLE(_xlpm.d)) - IF(MONTH(_xlfn.SINGLE(_xlpm.d)) < UK_TaxYear_Start_Month, 1, 0), _xlpm.start, DATE(_xlfn.SINGLE(_xlpm.ys), UK_TaxYear_Start_Month, 1), _xlpm.m, DATEDIF(_xlfn.SINGLE(_xlpm.start), _xlfn.SINGLE(_xlpm.d), "m") + 1, _xlpm.cum, SUMIFS($H$2:$H$54, $A$2:$A$54, ">=" & _xlfn.SINGLE(_xlpm.start), $A$2:$A$54, "<=" & _xlfn.SINGLE(_xlpm.d)), _xlpm.pa, UK_Personal_Allowance_Annual / 12 * _xlfn.SINGLE(_xlpm.m), _xlpm.br, (UK_Basic_Band_Upper_Annual - UK_Personal_Allowance_Annual) / 12 * _xlfn.SINGLE(_xlpm.m), _xlpm.hr, (UK_Higher_Band_Upper_Annual - UK_Basic_Band_Upper_Annual) / 12 * _xlfn.SINGLE(_xlpm.m), _xlpm.taxable, MAX(0, _xlfn.SINGLE(_xlpm.cum) - _xlfn.SINGLE(_xlpm.pa)), _xlpm.tax_to_date, UK_Basic_Rate * MIN(_xlpm.taxable, _xlpm.br) + UK_Higher_Rate * MIN(MAX(_xlfn.SINGLE(_xlpm.taxable) - _xlfn.SINGLE(_xlpm.br), 0), _xlpm.hr) + UK_Additional_Rate * MAX(_xlfn.SINGLE(_xlpm.taxable) - _xlfn.SINGLE(_xlpm.br) - _xlfn.SINGLE(_xlpm.hr), 0), _xlpm.prior, SUMIFS($J$2:$J$54, $A$2:$A$54, ">=" & _xlfn.SINGLE(_xlpm.start), $A$2:$A$54, "<" & _xlfn.SINGLE(_xlpm.d)), MAX(0, _xlfn.SINGLE(_xlpm.tax_to_date) - _xlfn.SINGLE(_xlpm.prior)))) -> 623.83333 | K8: =_xlfn.SINGLE(_xlfn.LET(_xlpm.g, $H8, _xlpm.pt, UK_NI_PT_Monthly, _xlpm.uel, UK_NI_UEL_Monthly, IF(_xlfn.SINGLE(_xlpm.g) <= _xlfn.SINGLE(_xlpm.pt), 0, UK_NI_Main_Rate * MIN(_xlfn.SINGLE(_xlpm.g) - _xlfn.SINGLE(_xlpm.pt), _xlfn.SINGLE(_xlpm.uel) - _xlfn.SINGLE(_xlpm.pt)) + UK_NI_Upper_Rate * MAX(_xlfn.SINGLE(_xlpm.g) - _xlfn.SINGLE(_xlpm.uel), 0)))) -> 249.49333 | L8: =IF($A8<DATE(2026,10,1),Bonus_Pct_Aug2026_to_Sep2026,IF($A8<DATE(2027,10,1),Bonus_Pct_Oct2026_to_Sep2027,IF($A8<DATE(2028,10,1),Bonus_Pct_Oct2027_to_Sep2028,IF($A8<DATE(2029,10,1),Bonus_Pct_Oct2028_to_Sep2029,Bonus_Pct_Oct2029_onwards)))) -> 0.08 | M8: Total Net in 2028 | N8: =SUM(I19:I30) -> 48020.971
A9: 46447 | B9: =(IF(YEAR($A9)=2026,Base_Annual_Salary_GBP,IF(YEAR($A9)=2027,Base_Annual_Salary_GBP*(IF(MONTH($A9)>=4,(1+Raise_Pct_Apr2027),1)*IF(MONTH($A9)>=10,(1+Raise_Pct_Nov2027),1)),IF(YEAR($A9)=2028,Base_Annual_Salary_GBP*((1+Raise_Pct_Apr2027)*(1+Raise_Pct_Nov2027))*(IF(MONTH($A9)>=4,(1+Raise_Pct_Apr2028),1)*IF(MONTH($A9)>=10,(1+Raise_Pct_Nov2028),1)),IF(YEAR($A9)=2029,Base_Annual_Salary_GBP*((1+Raise_Pct_Apr2027)*(1+Raise_Pct_Nov2027)*(1+Raise_Pct_Apr2028)*(1+Raise_Pct_Nov2028))*(IF(MONTH($A9)>=4,(1+Raise_Pct_Apr2029),1)*IF(MONTH($A9)>=10,(1+Raise_Pct_Nov2029),1)),Base_Annual_Salary_GBP*((1+Raise_Pct_Apr2027)*(1+Raise_Pct_Nov2027)*(1+Raise_Pct_Apr2028)*(1+Raise_Pct_Nov2028)*(1+Raise_Pct_Apr2029)*(1+Raise_Pct_Nov2029))*(IF(MONTH($A9)>=4,(1+Raise_Pct_Apr2030),1)*IF(MONTH($A9)>=10,(1+Raise_Pct_Nov2030),1)))))))/12 -> 4166.6667 | C9: =IF(MONTH($A9)=11,((IF(DATE(YEAR($A9),4,1)<DATE(2026,10,1),Bonus_Pct_Aug2026_to_Sep2026,IF(DATE(YEAR($A9),4,1)<DATE(2027,10,1),Bonus_Pct_Oct2026_to_Sep2027,IF(DATE(YEAR($A9),4,1)<DATE(2028,10,1),Bonus_Pct_Oct2027_to_Sep2028,IF(DATE(YEAR($A9),4,1)<DATE(2029,10,1),Bonus_Pct_Oct2028_to_Sep2029,Bonus_Pct_Oct2029_onwards)))))/2)*($B9*12) / (1 + IF(YEAR($A9)=2027,Raise_Pct_Nov2027,IF(YEAR($A9)=2028,Raise_Pct_Nov2028,IF(YEAR($A9)=2029,Raise_Pct_Nov2029,IF(YEAR($A9)=2030,Raise_Pct_Nov2030,0))))) * IF(YEAR($A9)=2026,2/6,1),IF(MONTH($A9)=5,((IF(DATE(YEAR($A9)-1,10,1)<DATE(2026,10,1),Bonus_Pct_Aug2026_to_Sep2026,IF(DATE(YEAR($A9)-1,10,1)<DATE(2027,10,1),Bonus_Pct_Oct2026_to_Sep2027,IF(DATE(YEAR($A9)-1,10,1)<DATE(2028,10,1),Bonus_Pct_Oct2027_to_Sep2028,IF(DATE(YEAR($A9)-1,10,1)<DATE(2029,10,1),Bonus_Pct_Oct2028_to_Sep2029,Bonus_Pct_Oct2029_onwards)))))/2)*($B9*12) / (1 + IF(YEAR($A9)=2027,Raise_Pct_Apr2027,IF(YEAR($A9)=2028,Raise_Pct_Apr2028,IF(YEAR($A9)=2029,Raise_Pct_Apr2029,IF(YEAR($A9)=2030,Raise_Pct_Apr2030,0))))),0)) -> 0 | D9: =IF(OR($A9=DATE(2027,9,1),$A9=EDATE(DATE(2027,9,1),12),$A9=EDATE(DATE(2027,9,1),24)),(New_Hire_Stock_Grant_USD/3)/FX_USD_per_GBP*(1+IF(YEAR($A9)=2027,Inputs!$B$56,IF(YEAR($A9)=2028,Inputs!$B$57,IF(YEAR($A9)=2029,Inputs!$B$58,0)))),0)+IF(OR($A9=DATE(2028,11,1),$A9=DATE(2029,11,1),$A9=DATE(2030,11,1)),(RSU_Grant_Nov2027_USD/3)/FX_USD_per_GBP*(1+RSU_Price_Change_Pct)^(YEAR($A9)-2028),0)+IF(OR($A9=DATE(2029,11,1),$A9=DATE(2030,11,1)),(RSU_Grant_Nov2028_USD/3)/FX_USD_per_GBP*(1+RSU_Price_Change_Pct)^(YEAR($A9)-2029),0)+IF($A9=DATE(2030,11,1),(RSU_Grant_Nov2029_USD/3)/FX_USD_per_GBP*(1+RSU_Price_Change_Pct)^(YEAR($A9)-2030),0) -> 0 | E9: =IF($A9=EDATE(DATE(2026,8,1),Inputs!$B$9),Inputs!$B$8,0) -> 0 | F9: =IF($A9=EDATE(DATE(2026,8,1),Inputs!$B$11),Inputs!$B$10,0) -> 0 | G9: =IF(Inputs!$B$16=1,((IF(YEAR($A9)=2026,Inputs!$B$2,IF(YEAR($A9)=2027,IF(MONTH($A9)>=Inputs!#REF!,Inputs!$B$2*(1+Inputs!$B$4),Inputs!$B$2),IF(YEAR($A9)=2028,IF(MONTH($A9)>=Inputs!#REF!,Inputs!$B$2*(1+Inputs!$B$4)*(1+Inputs!$B$5),Inputs!$B$2*(1+Inputs!$B$4)),IF(YEAR($A9)=2029,IF(MONTH($A9)>=Inputs!#REF!,Inputs!$B$2*(1+Inputs!$B$4)*(1+Inputs!$B$5)*(1+Inputs!$B$6),Inputs!$B$2*(1+Inputs!$B$4)*(1+Inputs!$B$5)),IF(MONTH($A9)>=Inputs!#REF!,Inputs!$B$2*(1+Inputs!$B$4)*(1+Inputs!$B$5)*(1+Inputs!$B$6)*(1+Inputs!$B$7),Inputs!$B$2*(1+Inputs!$B$4)*(1+Inputs!$B$5)*(1+Inputs!$B$6)))))))/12)*(MIN(Inputs!$B$17,Inputs!$B$18)*(1+Inputs!$B$19)+Inputs!$B$17*Inputs!$B$20),0) -> 0 | H9: =SUM(B9:G9) -> 4166.6667 | I9: =$H9-J9-K9 -> 3293.34 | J9: =_xlfn.SINGLE(_xlfn.LET(_xlpm.d, $A9, _xlpm.ys, YEAR(_xlfn.SINGLE(_xlpm.d)) - IF(MONTH(_xlfn.SINGLE(_xlpm.d)) < UK_TaxYear_Start_Month, 1, 0), _xlpm.start, DATE(_xlfn.SINGLE(_xlpm.ys), UK_TaxYear_Start_Month, 1), _xlpm.m, DATEDIF(_xlfn.SINGLE(_xlpm.start), _xlfn.SINGLE(_xlpm.d), "m") + 1, _xlpm.cum, SUMIFS($H$2:$H$54, $A$2:$A$54, ">=" & _xlfn.SINGLE(_xlpm.start), $A$2:$A$54, "<=" & _xlfn.SINGLE(_xlpm.d)), _xlpm.pa, UK_Personal_Allowance_Annual / 12 * _xlfn.SINGLE(_xlpm.m), _xlpm.br, (UK_Basic_Band_Upper_Annual - UK_Personal_Allowance_Annual) / 12 * _xlfn.SINGLE(_xlpm.m), _xlpm.hr, (UK_Higher_Band_Upper_Annual - UK_Basic_Band_Upper_Annual) / 12 * _xlfn.SINGLE(_xlpm.m), _xlpm.taxable, MAX(0, _xlfn.SINGLE(_xlpm.cum) - _xlfn.SINGLE(_xlpm.pa)), _xlpm.tax_to_date, UK_Basic_Rate * MIN(_xlpm.taxable, _xlpm.br) + UK_Higher_Rate * MIN(MAX(_xlfn.SINGLE(_xlpm.taxable) - _xlfn.SINGLE(_xlpm.br), 0), _xlpm.hr) + UK_Additional_Rate * MAX(_xlfn.SINGLE(_xlpm.taxable) - _xlfn.SINGLE(_xlpm.br) - _xlfn.SINGLE(_xlpm.hr), 0), _xlpm.prior, SUMIFS($J$2:$J$54, $A$2:$A$54, ">=" & _xlfn.SINGLE(_xlpm.start), $A$2:$A$54, "<" & _xlfn.SINGLE(_xlpm.d)), MAX(0, _xlfn.SINGLE(_xlpm.tax_to_date) - _xlfn.SINGLE(_xlpm.prior)))) -> 623.83333 | K9: =_xlfn.SINGLE(_xlfn.LET(_xlpm.g, $H9, _xlpm.pt, UK_NI_PT_Monthly, _xlpm.uel, UK_NI_UEL_Monthly, IF(_xlfn.SINGLE(_xlpm.g) <= _xlfn.SINGLE(_xlpm.pt), 0, UK_NI_Main_Rate * MIN(_xlfn.SINGLE(_xlpm.g) - _xlfn.SINGLE(_xlpm.pt), _xlfn.SINGLE(_xlpm.uel) - _xlfn.SINGLE(_xlpm.pt)) + UK_NI_Upper_Rate * MAX(_xlfn.SINGLE(_xlpm.g) - _xlfn.SINGLE(_xlpm.uel), 0)))) -> 249.49333 | L9: =IF($A9<DATE(2026,10,1),Bonus_Pct_Aug2026_to_Sep2026,IF($A9<DATE(2027,10,1),Bonus_Pct_Oct2026_to_Sep2027,IF($A9<DATE(2028,10,1),Bonus_Pct_Oct2027_to_Sep2028,IF($A9<DATE(2029,10,1),Bonus_Pct_Oct2028_to_Sep2029,Bonus_Pct_Oct2029_onwards)))) -> 0.08 | M9: Total Net in 2029 | N9: =SUM(I31:I42) -> 50441.235
A10: 46478 | B10: =(IF(YEAR($A10)=2026,Base_Annual_Salary_GBP,IF(YEAR($A10)=2027,Base_Annual_Salary_GBP*(IF(MONTH($A10)>=4,(1+Raise_Pct_Apr2027),1)*IF(MONTH($A10)>=10,(1+Raise_Pct_Nov2027),1)),IF(YEAR($A10)=2028,Base_Annual_Salary_GBP*((1+Raise_Pct_Apr2027)*(1+Raise_Pct_Nov2027))*(IF(MONTH($A10)>=4,(1+Raise_Pct_Apr2028),1)*IF(MONTH($A10)>=10,(1+Raise_Pct_Nov2028),1)),IF(YEAR($A10)=2029,Base_Annual_Salary_GBP*((1+Raise_Pct_Apr2027)*(1+Raise_Pct_Nov2027)*(1+Raise_Pct_Apr2028)*(1+Raise_Pct_Nov2028))*(IF(MONTH($A10)>=4,(1+Raise_Pct_Apr2029),1)*IF(MONTH($A10)>=10,(1+Raise_Pct_Nov2029),1)),Base_Annual_Salary_GBP*((1+Raise_Pct_Apr2027)*(1+Raise_Pct_Nov2027)*(1+Raise_Pct_Apr2028)*(1+Raise_Pct_Nov2028)*(1+Raise_Pct_Apr2029)*(1+Raise_Pct_Nov2029))*(IF(MONTH($A10)>=4,(1+Raise_Pct_Apr2030),1)*IF(MONTH($A10)>=10,(1+Raise_Pct_Nov2030),1)))))))/12 -> 4291.6667 | C10: =IF(MONTH($A10)=11,((IF(DATE(YEAR($A10),4,1)<DATE(2026,10,1),Bonus_Pct_Aug2026_to_Sep2026,IF(DATE(YEAR($A10),4,1)<DATE(2027,10,1),Bonus_Pct_Oct2026_to_Sep2027,IF(DATE(YEAR($A10),4,1)<DATE(2028,10,1),Bonus_Pct_Oct2027_to_Sep2028,IF(DATE(YEAR($A10),4,1)<DATE(2029,10,1),Bonus_Pct_Oct2028_to_Sep2029,Bonus_Pct_Oct2029_onwards)))))/2)*($B10*12) / (1 + IF(YEAR($A10)=2027,Raise_Pct_Nov2027,IF(YEAR($A10)=2028,Raise_Pct_Nov2028,IF(YEAR($A10)=2029,Raise_Pct_Nov2029,IF(YEAR($A10)=2030,Raise_Pct_Nov2030,0))))) * IF(YEAR($A10)=2026,2/6,1),IF(MONTH($A10)=5,((IF(DATE(YEAR($A10)-1,10,1)<DATE(2026,10,1),Bonus_Pct_Aug2026_to_Sep2026,IF(DATE(YEAR($A10)-1,10,1)<DATE(2027,10,1),Bonus_Pct_Oct2026_to_Sep2027,IF(DATE(YEAR($A10)-1,10,1)<DATE(2028,10,1),Bonus_Pct_Oct2027_to_Sep2028,IF(DATE(YEAR($A10)-1,10,1)<DATE(2029,10,1),Bonus_Pct_Oct2028_to_Sep2029,Bonus_Pct_Oct2029_onwards)))))/2)*($B10*12) / (1 + IF(YEAR($A10)=2027,Raise_Pct_Apr2027,IF(YEAR($A10)=2028,Raise_Pct_Apr2028,IF(YEAR($A10)=2029,Raise_Pct_Apr2029,IF(YEAR($A10)=2030,Raise_Pct_Apr2030,0))))),0)) -> 0 | D10: =IF(OR($A10=DATE(2027,9,1),$A10=EDATE(DATE(2027,9,1),12),$A10=EDATE(DATE(2027,9,1),24)),(New_Hire_Stock_Grant_USD/3)/FX_USD_per_GBP*(1+IF(YEAR($A10)=2027,Inputs!$B$56,IF(YEAR($A10)=2028,Inputs!$B$57,IF(YEAR($A10)=2029,Inputs!$B$58,0)))),0)+IF(OR($A10=DATE(2028,11,1),$A10=DATE(2029,11,1),$A10=DATE(2030,11,1)),(RSU_Grant_Nov2027_USD/3)/FX_USD_per_GBP*(1+RSU_Price_Change_Pct)^(YEAR($A10)-2028),0)+IF(OR($A10=DATE(2029,11,1),$A10=DATE(2030,11,1)),(RSU_Grant_Nov2028_USD/3)/FX_USD_per_GBP*(1+RSU_Price_Change_Pct)^(YEAR($A10)-2029),0)+IF($A10=DATE(2030,11,1),(RSU_Grant_Nov2029_USD/3)/FX_USD_per_GBP*(1+RSU_Price_Change_Pct)^(YEAR($A10)-2030),0) -> 0 | E10: =IF($A10=EDATE(DATE(2026,8,1),Inputs!$B$9),Inputs!$B$8,0) -> 0 | F10: =IF($A10=EDATE(DATE(2026,8,1),Inputs!$B$11),Inputs!$B$10,0) -> 0 | G10: =IF(Inputs!$B$16=1,((IF(YEAR($A10)=2026,Inputs!$B$2,IF(YEAR($A10)=2027,IF(MONTH($A10)>=Inputs!#REF!,Inputs!$B$2*(1+Inputs!$B$4),Inputs!$B$2),IF(YEAR($A10)=2028,IF(MONTH($A10)>=Inputs!#REF!,Inputs!$B$2*(1+Inputs!$B$4)*(1+Inputs!$B$5),Inputs!$B$2*(1+Inputs!$B$4)),IF(YEAR($A10)=2029,IF(MONTH($A10)>=Inputs!#REF!,Inputs!$B$2*(1+Inputs!$B$4)*(1+Inputs!$B$5)*(1+Inputs!$B$6),Inputs!$B$2*(1+Inputs!$B$4)*(1+Inputs!$B$5)),IF(MONTH($A10)>=Inputs!#REF!,Inputs!$B$2*(1+Inputs!$B$4)*(1+Inputs!$B$5)*(1+Inputs!$B$6)*(1+Inputs!$B$7),Inputs!$B$2*(1+Inputs!$B$4)*(1+Inputs!$B$5)*(1+Inputs!$B$6)))))))/12)*(MIN(Inputs!$B$17,Inputs!$B$18)*(1+Inputs!$B$19)+Inputs!$B$17*Inputs!$B$20),0) -> 0 | H10: =SUM(B10:G10) -> 4291.6667 | I10: =$H10-J10-K10 -> 3369 | J10: =_xlfn.SINGLE(_xlfn.LET(_xlpm.d, $A10, _xlpm.ys, YEAR(_xlfn.SINGLE(_xlpm.d)) - IF(MONTH(_xlfn.SINGLE(_xlpm.d)) < UK_TaxYear_Start_Month, 1, 0), _xlpm.start, DATE(_xlfn.SINGLE(_xlpm.ys), UK_TaxYear_Start_Month, 1), _xlpm.m, DATEDIF(_xlfn.SINGLE(_xlpm.start), _xlfn.SINGLE(_xlpm.d), "m") + 1, _xlpm.cum, SUMIFS($H$2:$H$54, $A$2:$A$54, ">=" & _xlfn.SINGLE(_xlpm.start), $A$2:$A$54, "<=" & _xlfn.SINGLE(_xlpm.d)), _xlpm.pa, UK_Personal_Allowance_Annual / 12 * _xlfn.SINGLE(_xlpm.m), _xlpm.br, (UK_Basic_Band_Upper_Annual - UK_Personal_Allowance_Annual) / 12 * _xlfn.SINGLE(_xlpm.m), _xlpm.hr, (UK_Higher_Band_Upper_Annual - UK_Basic_Band_Upper_Annual) / 12 * _xlfn.SINGLE(_xlpm.m), _xlpm.taxable, MAX(0, _xlfn.SINGLE(_xlpm.cum) - _xlfn.SINGLE(_xlpm.pa)), _xlpm.tax_to_date, UK_Basic_Rate * MIN(_xlpm.taxable, _xlpm.br) + UK_Higher_Rate * MIN(MAX(_xlfn.SINGLE(_xlpm.taxable) - _xlfn.SINGLE(_xlpm.br), 0), _xlpm.hr) + UK_Additional_Rate * MAX(_xlfn.SINGLE(_xlpm.taxable) - _xlfn.SINGLE(_xlpm.br) - _xlfn.SINGLE(_xlpm.hr), 0), _xlpm.prior, SUMIFS($J$2:$J$54, $A$2:$A$54, ">=" & _xlfn.SINGLE(_xlpm.start), $A$2:$A$54, "<" & _xlfn.SINGLE(_xlpm.d)), MAX(0, _xlfn.SINGLE(_xlpm.tax_to_date) - _xlfn.SINGLE(_xlpm.prior)))) -> 669.33333 | K10: =_xlfn.SINGLE(_xlfn.LET(_xlpm.g, $H10, _xlpm.pt, UK_NI_PT_Monthly, _xlpm.uel, UK_NI_UEL_Monthly, IF(_xlfn.SINGLE(_xlpm.g) <= _xlfn.SINGLE(_xlpm.pt), 0, UK_NI_Main_Rate * MIN(_xlfn.SINGLE(_xlpm.g) - _xlfn.SINGLE(_xlpm.pt), _xlfn.SINGLE(_xlpm.uel) - _xlfn.SINGLE(_xlpm.pt)) + UK_NI_Upper_Rate * MAX(_xlfn.SINGLE(_xlpm.g) - _xlfn.SINGLE(_xlpm.uel), 0)))) -> 253.33333 | L10: =IF($A10<DATE(2026,10,1),Bonus_Pct_Aug2026_to_Sep2026,IF($A10<DATE(2027,10,1),Bonus_Pct_Oct2026_to_Sep2027,IF($A10<DATE(2028,10,1),Bonus_Pct_Oct2027_to_Sep2028,IF($A10<DATE(2029,10,1),Bonus_Pct_Oct2028_to_Sep2029,Bonus_Pct_Oct2029_onwards)))) -> 0.08 | M10: Total Net in 2030 | N10: =SUM(I43:I54) -> 47245.085
A11: 46508 | B11: =(IF(YEAR($A11)=2026,Base_Annual_Salary_GBP,IF(YEAR($A11)=2027,Base_Annual_Salary_GBP*(IF(MONTH($A11)>=4,(1+Raise_Pct_Apr2027),1)*IF(MONTH($A11)>=10,(1+Raise_Pct_Nov2027),1)),IF(YEAR($A11)=2028,Base_Annual_Salary_GBP*((1+Raise_Pct_Apr2027)*(1+Raise_Pct_Nov2027))*(IF(MONTH($A11)>=4,(1+Raise_Pct_Apr2028),1)*IF(MONTH($A11)>=10,(1+Raise_Pct_Nov2028),1)),IF(YEAR($A11)=2029,Base_Annual_Salary_GBP*((1+Raise_Pct_Apr2027)*(1+Raise_Pct_Nov2027)*(1+Raise_Pct_Apr2028)*(1+Raise_Pct_Nov2028))*(IF(MONTH($A11)>=4,(1+Raise_Pct_Apr2029),1)*IF(MONTH($A11)>=10,(1+Raise_Pct_Nov2029),1)),Base_Annual_Salary_GBP*((1+Raise_Pct_Apr2027)*(1+Raise_Pct_Nov2027)*(1+Raise_Pct_Apr2028)*(1+Raise_Pct_Nov2028)*(1+Raise_Pct_Apr2029)*(1+Raise_Pct_Nov2029))*(IF(MONTH($A11)>=4,(1+Raise_Pct_Apr2030),1)*IF(MONTH($A11)>=10,(1+Raise_Pct_Nov2030),1)))))))/12 -> 4291.6667 | C11: =IF(MONTH($A11)=11,((IF(DATE(YEAR($A11),4,1)<DATE(2026,10,1),Bonus_Pct_Aug2026_to_Sep2026,IF(DATE(YEAR($A11),4,1)<DATE(2027,10,1),Bonus_Pct_Oct2026_to_Sep2027,IF(DATE(YEAR($A11),4,1)<DATE(2028,10,1),Bonus_Pct_Oct2027_to_Sep2028,IF(DATE(YEAR($A11),4,1)<DATE(2029,10,1),Bonus_Pct_Oct2028_to_Sep2029,Bonus_Pct_Oct2029_onwards)))))/2)*($B11*12) / (1 + IF(YEAR($A11)=2027,Raise_Pct_Nov2027,IF(YEAR($A11)=2028,Raise_Pct_Nov2028,IF(YEAR($A11)=2029,Raise_Pct_Nov2029,IF(YEAR($A11)=2030,Raise_Pct_Nov2030,0))))) * IF(YEAR($A11)=2026,2/6,1),IF(MONTH($A11)=5,((IF(DATE(YEAR($A11)-1,10,1)<DATE(2026,10,1),Bonus_Pct_Aug2026_to_Sep2026,IF(DATE(YEAR($A11)-1,10,1)<DATE(2027,10,1),Bonus_Pct_Oct2026_to_Sep2027,IF(DATE(YEAR($A11)-1,10,1)<DATE(2028,10,1),Bonus_Pct_Oct2027_to_Sep2028,IF(DATE(YEAR($A11)-1,10,1)<DATE(2029,10,1),Bonus_Pct_Oct2028_to_Sep2029,Bonus_Pct_Oct2029_onwards)))))/2)*($B11*12) / (1 + IF(YEAR($A11)=2027,Raise_Pct_Apr2027,IF(YEAR($A11)=2028,Raise_Pct_Apr2028,IF(YEAR($A11)=2029,Raise_Pct_Apr2029,IF(YEAR($A11)=2030,Raise_Pct_Apr2030,0))))),0)) -> 2000 | D11: =IF(OR($A11=DATE(2027,9,1),$A11=EDATE(DATE(2027,9,1),12),$A11=EDATE(DATE(2027,9,1),24)),(New_Hire_Stock_Grant_USD/3)/FX_USD_per_GBP*(1+IF(YEAR($A11)=2027,Inputs!$B$56,IF(YEAR($A11)=2028,Inputs!$B$57,IF(YEAR($A11)=2029,Inputs!$B$58,0)))),0)+IF(OR($A11=DATE(2028,11,1),$A11=DATE(2029,11,1),$A11=DATE(2030,11,1)),(RSU_Grant_Nov2027_USD/3)/FX_USD_per_GBP*(1+RSU_Price_Change_Pct)^(YEAR($A11)-2028),0)+IF(OR($A11=DATE(2029,11,1),$A11=DATE(2030,11,1)),(RSU_Grant_Nov2028_USD/3)/FX_USD_per_GBP*(1+RSU_Price_Change_Pct)^(YEAR($A11)-2029),0)+IF($A11=DATE(2030,11,1),(RSU_Grant_Nov2029_USD/3)/FX_USD_per_GBP*(1+RSU_Price_Change_Pct)^(YEAR($A11)-2030),0) -> 0 | E11: =IF($A11=EDATE(DATE(2026,8,1),Inputs!$B$9),Inputs!$B$8,0) -> 0 | F11: =IF($A11=EDATE(DATE(2026,8,1),Inputs!$B$11),Inputs!$B$10,0) -> 0 | G11: =IF(Inputs!$B$16=1,((IF(YEAR($A11)=2026,Inputs!$B$2,IF(YEAR($A11)=2027,IF(MONTH($A11)>=Inputs!#REF!,Inputs!$B$2*(1+Inputs!$B$4),Inputs!$B$2),IF(YEAR($A11)=2028,IF(MONTH($A11)>=Inputs!#REF!,Inputs!$B$2*(1+Inputs!$B$4)*(1+Inputs!$B$5),Inputs!$B$2*(1+Inputs!$B$4)),IF(YEAR($A11)=2029,IF(MONTH($A11)>=Inputs!#REF!,Inputs!$B$2*(1+Inputs!$B$4)*(1+Inputs!$B$5)*(1+Inputs!$B$6),Inputs!$B$2*(1+Inputs!$B$4)*(1+Inputs!$B$5)),IF(MONTH($A11)>=Inputs!#REF!,Inputs!$B$2*(1+Inputs!$B$4)*(1+Inputs!$B$5)*(1+Inputs!$B$6)*(1+Inputs!$B$7),Inputs!$B$2*(1+Inputs!$B$4)*(1+Inputs!$B$5)*(1+Inputs!$B$6)))))))/12)*(MIN(Inputs!$B$17,Inputs!$B$18)*(1+Inputs!$B$19)+Inputs!$B$17*Inputs!$B$20),0) -> 0 | H11: =SUM(B11:G11) -> 6291.6667 | I11: =$H11-J11-K11 -> 4529 | J11: =_xlfn.SINGLE(_xlfn.LET(_xlpm.d, $A11, _xlpm.ys, YEAR(_xlfn.SINGLE(_xlpm.d)) - IF(MONTH(_xlfn.SINGLE(_xlpm.d)) < UK_TaxYear_Start_Month, 1, 0), _xlpm.start, DATE(_xlfn.SINGLE(_xlpm.ys), UK_TaxYear_Start_Month, 1), _xlpm.m, DATEDIF(_xlfn.SINGLE(_xlpm.start), _xlfn.SINGLE(_xlpm.d), "m") + 1, _xlpm.cum, SUMIFS($H$2:$H$54, $A$2:$A$54, ">=" & _xlfn.SINGLE(_xlpm.start), $A$2:$A$54, "<=" & _xlfn.SINGLE(_xlpm.d)), _xlpm.pa, UK_Personal_Allowance_Annual / 12 * _xlfn.SINGLE(_xlpm.m), _xlpm.br, (UK_Basic_Band_Upper_Annual - UK_Personal_Allowance_Annual) / 12 * _xlfn.SINGLE(_xlpm.m), _xlpm.hr, (UK_Higher_Band_Upper_Annual - UK_Basic_Band_Upper_Annual) / 12 * _xlfn.SINGLE(_xlpm.m), _xlpm.taxable, MAX(0, _xlfn.SINGLE(_xlpm.cum) - _xlfn.SINGLE(_xlpm.pa)), _xlpm.tax_to_date, UK_Basic_Rate * MIN(_xlpm.taxable, _xlpm.br) + UK_Higher_Rate * MIN(MAX(_xlfn.SINGLE(_xlpm.taxable) - _xlfn.SINGLE(_xlpm.br), 0), _xlpm.hr) + UK_Additional_Rate * MAX(_xlfn.SINGLE(_xlpm.taxable) - _xlfn.SINGLE(_xlpm.br) - _xlfn.SINGLE(_xlpm.hr), 0), _xlpm.prior, SUMIFS($J$2:$J$54, $A$2:$A$54, ">=" & _xlfn.SINGLE(_xlpm.start), $A$2:$A$54, "<" & _xlfn.SINGLE(_xlpm.d)), MAX(0, _xlfn.SINGLE(_xlpm.tax_to_date) - _xlfn.SINGLE(_xlpm.prior)))) -> 1469.3333 | K11: =_xlfn.SINGLE(_xlfn.LET(_xlpm.g, $H11, _xlpm.pt, UK_NI_PT_Monthly, _xlpm.uel, UK_NI_UEL_Monthly, IF(_xlfn.SINGLE(_xlpm.g) <= _xlfn.SINGLE(_xlpm.pt), 0, UK_NI_Main_Rate * MIN(_xlfn.SINGLE(_xlpm.g) - _xlfn.SINGLE(_xlpm.pt), _xlfn.SINGLE(_xlpm.uel) - _xlfn.SINGLE(_xlpm.pt)) + UK_NI_Upper_Rate * MAX(_xlfn.SINGLE(_xlpm.g) - _xlfn.SINGLE(_xlpm.uel), 0)))) -> 293.33333 | L11: =IF($A11<DATE(2026,10,1),Bonus_Pct_Aug2026_to_Sep2026,IF($A11<DATE(2027,10,1),Bonus_Pct_Oct2026_to_Sep2027,IF($A11<DATE(2028,10,1),Bonus_Pct_Oct2027_to_Sep2028,IF($A11<DATE(2029,10,1),Bonus_Pct_Oct2028_to_Sep2029,Bonus_Pct_Oct2029_onwards)))) -> 0.08
A12: 46539 | B12: =(IF(YEAR($A12)=2026,Base_Annual_Salary_GBP,IF(YEAR($A12)=2027,Base_Annual_Salary_GBP*(IF(MONTH($A12)>=4,(1+Raise_Pct_Apr2027),1)*IF(MONTH($A12)>=10,(1+Raise_Pct_Nov2027),1)),IF(YEAR($A12)=2028,Base_Annual_Salary_GBP*((1+Raise_Pct_Apr2027)*(1+Raise_Pct_Nov2027))*(IF(MONTH($A12)>=4,(1+Raise_Pct_Apr2028),1)*IF(MONTH($A12)>=10,(1+Raise_Pct_Nov2028),1)),IF(YEAR($A12)=2029,Base_Annual_Salary_GBP*((1+Raise_Pct_Apr2027)*(1+Raise_Pct_Nov2027)*(1+Raise_Pct_Apr2028)*(1+Raise_Pct_Nov2028))*(IF(MONTH($A12)>=4,(1+Raise_Pct_Apr2029),1)*IF(MONTH($A12)>=10,(1+Raise_Pct_Nov2029),1)),Base_Annual_Salary_GBP*((1+Raise_Pct_Apr2027)*(1+Raise_Pct_Nov2027)*(1+Raise_Pct_Apr2028)*(1+Raise_Pct_Nov2028)*(1+Raise_Pct_Apr2029)*(1+Raise_Pct_Nov2029))*(IF(MONTH($A12)>=4,(1+Raise_Pct_Apr2030),1)*IF(MONTH($A12)>=10,(1+Raise_Pct_Nov2030),1)))))))/12 -> 4291.6667 | C12: =IF(MONTH($A12)=11,((IF(DATE(YEAR($A12),4,1)<DATE(2026,10,1),Bonus_Pct_Aug2026_to_Sep2026,IF(DATE(YEAR($A12),4,1)<DATE(2027,10,1),Bonus_Pct_Oct2026_to_Sep2027,IF(DATE(YEAR($A12),4,1)<DATE(2028,10,1),Bonus_Pct_Oct2027_to_Sep2028,IF(DATE(YEAR($A12),4,1)<DATE(2029,10,1),Bonus_Pct_Oct2028_to_Sep2029,Bonus_Pct_Oct2029_onwards)))))/2)*($B12*12) / (1 + IF(YEAR($A12)=2027,Raise_Pct_Nov2027,IF(YEAR($A12)=2028,Raise_Pct_Nov2028,IF(YEAR($A12)=2029,Raise_Pct_Nov2029,IF(YEAR($A12)=2030,Raise_Pct_Nov2030,0))))) * IF(YEAR($A12)=2026,2/6,1),IF(MONTH($A12)=5,((IF(DATE(YEAR($A12)-1,10,1)<DATE(2026,10,1),Bonus_Pct_Aug2026_to_Sep2026,IF(DATE(YEAR($A12)-1,10,1)<DATE(2027,10,1),Bonus_Pct_Oct2026_to_Sep2027,IF(DATE(YEAR($A12)-1,10,1)<DATE(2028,10,1),Bonus_Pct_Oct2027_to_Sep2028,IF(DATE(YEAR($A12)-1,10,1)<DATE(2029,10,1),Bonus_Pct_Oct2028_to_Sep2029,Bonus_Pct_Oct2029_onwards)))))/2)*($B12*12) / (1 + IF(YEAR($A12)=2027,Raise_Pct_Apr2027,IF(YEAR($A12)=2028,Raise_Pct_Apr2028,IF(YEAR($A12)=2029,Raise_Pct_Apr2029,IF(YEAR($A12)=2030,Raise_Pct_Apr2030,0))))),0)) -> 0 | D12: =IF(OR($A12=DATE(2027,9,1),$A12=EDATE(DATE(2027,9,1),12),$A12=EDATE(DATE(2027,9,1),24)),(New_Hire_Stock_Grant_USD/3)/FX_USD_per_GBP*(1+IF(YEAR($A12)=2027,Inputs!$B$56,IF(YEAR($A12)=2028,Inputs!$B$57,IF(YEAR($A12)=2029,Inputs!$B$58,0)))),0)+IF(OR($A12=DATE(2028,11,1),$A12=DATE(2029,11,1),$A12=DATE(2030,11,1)),(RSU_Grant_Nov2027_USD/3)/FX_USD_per_GBP*(1+RSU_Price_Change_Pct)^(YEAR($A12)-2028),0)+IF(OR($A12=DATE(2029,11,1),$A12=DATE(2030,11,1)),(RSU_Grant_Nov2028_USD/3)/FX_USD_per_GBP*(1+RSU_Price_Change_Pct)^(YEAR($A12)-2029),0)+IF($A12=DATE(2030,11,1),(RSU_Grant_Nov2029_USD/3)/FX_USD_per_GBP*(1+RSU_Price_Change_Pct)^(YEAR($A12)-2030),0) -> 0 | E12: =IF($A12=EDATE(DATE(2026,8,1),Inputs!$B$9),Inputs!$B$8,0) -> 0 | F12: =IF($A12=EDATE(DATE(2026,8,1),Inputs!$B$11),Inputs!$B$10,0) -> 0 | G12: =IF(Inputs!$B$16=1,((IF(YEAR($A12)=2026,Inputs!$B$2,IF(YEAR($A12)=2027,IF(MONTH($A12)>=Inputs!#REF!,Inputs!$B$2*(1+Inputs!$B$4),Inputs!$B$2),IF(YEAR($A12)=2028,IF(MONTH($A12)>=Inputs!#REF!,Inputs!$B$2*(1+Inputs!$B$4)*(1+Inputs!$B$5),Inputs!$B$2*(1+Inputs!$B$4)),IF(YEAR($A12)=2029,IF(MONTH($A12)>=Inputs!#REF!,Inputs!$B$2*(1+Inputs!$B$4)*(1+Inputs!$B$5)*(1+Inputs!$B$6),Inputs!$B$2*(1+Inputs!$B$4)*(1+Inputs!$B$5)),IF(MONTH($A12)>=Inputs!#REF!,Inputs!$B$2*(1+Inputs!$B$4)*(1+Inputs!$B$5)*(1+Inputs!$B$6)*(1+Inputs!$B$7),Inputs!$B$2*(1+Inputs!$B$4)*(1+Inputs!$B$5)*(1+Inputs!$B$6)))))))/12)*(MIN(Inputs!$B$17,Inputs!$B$18)*(1+Inputs!$B$19)+Inputs!$B$17*Inputs!$B$20),0) -> 0 | H12: =SUM(B12:G12) -> 4291.6667 | I12: =$H12-J12-K12 -> 3369 | J12: =_xlfn.SINGLE(_xlfn.LET(_xlpm.d, $A12, _xlpm.ys, YEAR(_xlfn.SINGLE(_xlpm.d)) - IF(MONTH(_xlfn.SINGLE(_xlpm.d)) < UK_TaxYear_Start_Month, 1, 0), _xlpm.start, DATE(_xlfn.SINGLE(_xlpm.ys), UK_TaxYear_Start_Month, 1), _xlpm.m, DATEDIF(_xlfn.SINGLE(_xlpm.start), _xlfn.SINGLE(_xlpm.d), "m") + 1, _xlpm.cum, SUMIFS($H$2:$H$54, $A$2:$A$54, ">=" & _xlfn.SINGLE(_xlpm.start), $A$2:$A$54, "<=" & _xlfn.SINGLE(_xlpm.d)), _xlpm.pa, UK_Personal_Allowance_Annual / 12 * _xlfn.SINGLE(_xlpm.m), _xlpm.br, (UK_Basic_Band_Upper_Annual - UK_Personal_Allowance_Annual) / 12 * _xlfn.SINGLE(_xlpm.m), _xlpm.hr, (UK_Higher_Band_Upper_Annual - UK_Basic_Band_Upper_Annual) / 12 * _xlfn.SINGLE(_xlpm.m), _xlpm.taxable, MAX(0, _xlfn.SINGLE(_xlpm.cum) - _xlfn.SINGLE(_xlpm.pa)), _xlpm.tax_to_date, UK_Basic_Rate * MIN(_xlpm.taxable, _xlpm.br) + UK_Higher_Rate * MIN(MAX(_xlfn.SINGLE(_xlpm.taxable) - _xlfn.SINGLE(_xlpm.br), 0), _xlpm.hr) + UK_Additional_Rate * MAX(_xlfn.SINGLE(_xlpm.taxable) - _xlfn.SINGLE(_xlpm.br) - _xlfn.SINGLE(_xlpm.hr), 0), _xlpm.prior, SUMIFS($J$2:$J$54, $A$2:$A$54, ">=" & _xlfn.SINGLE(_xlpm.start), $A$2:$A$54, "<" & _xlfn.SINGLE(_xlpm.d)), MAX(0, _xlfn.SINGLE(_xlpm.tax_to_date) - _xlfn.SINGLE(_xlpm.prior)))) -> 669.33333 | K12: =_xlfn.SINGLE(_xlfn.LET(_xlpm.g, $H12, _xlpm.pt, UK_NI_PT_Monthly, _xlpm.uel, UK_NI_UEL_Monthly, IF(_xlfn.SINGLE(_xlpm.g) <= _xlfn.SINGLE(_xlpm.pt), 0, UK_NI_Main_Rate * MIN(_xlfn.SINGLE(_xlpm.g) - _xlfn.SINGLE(_xlpm.pt), _xlfn.SINGLE(_xlpm.uel) - _xlfn.SINGLE(_xlpm.pt)) + UK_NI_Upper_Rate * MAX(_xlfn.SINGLE(_xlpm.g) - _xlfn.SINGLE(_xlpm.uel), 0)))) -> 253.33333 | L12: =IF($A12<DATE(2026,10,1),Bonus_Pct_Aug2026_to_Sep2026,IF($A12<DATE(2027,10,1),Bonus_Pct_Oct2026_to_Sep2027,IF($A12<DATE(2028,10,1),Bonus_Pct_Oct2027_to_Sep2028,IF($A12<DATE(2029,10,1),Bonus_Pct_Oct2028_to_Sep2029,Bonus_Pct_Oct2029_onwards)))) -> 0.08 | M12: Take-Home Estimate in 2026 | N12: =(N6-Living_Expenses_GBP_Monthly_2026*5)*FX_USD_per_GBP -> 11100.347
A13: 46569 | B13: =(IF(YEAR($A13)=2026,Base_Annual_Salary_GBP,IF(YEAR($A13)=2027,Base_Annual_Salary_GBP*(IF(MONTH($A13)>=4,(1+Raise_Pct_Apr2027),1)*IF(MONTH($A13)>=10,(1+Raise_Pct_Nov2027),1)),IF(YEAR($A13)=2028,Base_Annual_Salary_GBP*((1+Raise_Pct_Apr2027)*(1+Raise_Pct_Nov2027))*(IF(MONTH($A13)>=4,(1+Raise_Pct_Apr2028),1)*IF(MONTH($A13)>=10,(1+Raise_Pct_Nov2028),1)),IF(YEAR($A13)=2029,Base_Annual_Salary_GBP*((1+Raise_Pct_Apr2027)*(1+Raise_Pct_Nov2027)*(1+Raise_Pct_Apr2028)*(1+Raise_Pct_Nov2028))*(IF(MONTH($A13)>=4,(1+Raise_Pct_Apr2029),1)*IF(MONTH($A13)>=10,(1+Raise_Pct_Nov2029),1)),Base_Annual_Salary_GBP*((1+Raise_Pct_Apr2027)*(1+Raise_Pct_Nov2027)*(1+Raise_Pct_Apr2028)*(1+Raise_Pct_Nov2028)*(1+Raise_Pct_Apr2029)*(1+Raise_Pct_Nov2029))*(IF(MONTH($A13)>=4,(1+Raise_Pct_Apr2030),1)*IF(MONTH($A13)>=10,(1+Raise_Pct_Nov2030),1)))))))/12 -> 4291.6667 | C13: =IF(MONTH($A13)=11,((IF(DATE(YEAR($A13),4,1)<DATE(2026,10,1),Bonus_Pct_Aug2026_to_Sep2026,IF(DATE(YEAR($A13),4,1)<DATE(2027,10,1),Bonus_Pct_Oct2026_to_Sep2027,IF(DATE(YEAR($A13),4,1)<DATE(2028,10,1),Bonus_Pct_Oct2027_to_Sep2028,IF(DATE(YEAR($A13),4,1)<DATE(2029,10,1),Bonus_Pct_Oct2028_to_Sep2029,Bonus_Pct_Oct2029_onwards)))))/2)*($B13*12) / (1 + IF(YEAR($A13)=2027,Raise_Pct_Nov2027,IF(YEAR($A13)=2028,Raise_Pct_Nov2028,IF(YEAR($A13)=2029,Raise_Pct_Nov2029,IF(YEAR($A13)=2030,Raise_Pct_Nov2030,0))))) * IF(YEAR($A13)=2026,2/6,1),IF(MONTH($A13)=5,((IF(DATE(YEAR($A13)-1,10,1)<DATE(2026,10,1),Bonus_Pct_Aug2026_to_Sep2026,IF(DATE(YEAR($A13)-1,10,1)<DATE(2027,10,1),Bonus_Pct_Oct2026_to_Sep2027,IF(DATE(YEAR($A13)-1,10,1)<DATE(2028,10,1),Bonus_Pct_Oct2027_to_Sep2028,IF(DATE(YEAR($A13)-1,10,1)<DATE(2029,10,1),Bonus_Pct_Oct2028_to_Sep2029,Bonus_Pct_Oct2029_onwards)))))/2)*($B13*12) / (1 + IF(YEAR($A13)=2027,Raise_Pct_Apr2027,IF(YEAR($A13)=2028,Raise_Pct_Apr2028,IF(YEAR($A13)=2029,Raise_Pct_Apr2029,IF(YEAR($A13)=2030,Raise_Pct_Apr2030,0))))),0)) -> 0 | D13: =IF(OR($A13=DATE(2027,9,1),$A13=EDATE(DATE(2027,9,1),12),$A13=EDATE(DATE(2027,9,1),24)),(New_Hire_Stock_Grant_USD/3)/FX_USD_per_GBP*(1+IF(YEAR($A13)=2027,Inputs!$B$56,IF(YEAR($A13)=2028,Inputs!$B$57,IF(YEAR($A13)=2029,Inputs!$B$58,0)))),0)+IF(OR($A13=DATE(2028,11,1),$A13=DATE(2029,11,1),$A13=DATE(2030,11,1)),(RSU_Grant_Nov2027_USD/3)/FX_USD_per_GBP*(1+RSU_Price_Change_Pct)^(YEAR($A13)-2028),0)+IF(OR($A13=DATE(2029,11,1),$A13=DATE(2030,11,1)),(RSU_Grant_Nov2028_USD/3)/FX_USD_per_GBP*(1+RSU_Price_Change_Pct)^(YEAR($A13)-2029),0)+IF($A13=DATE(2030,11,1),(RSU_Grant_Nov2029_USD/3)/FX_USD_per_GBP*(1+RSU_Price_Change_Pct)^(YEAR($A13)-2030),0) -> 0 | E13: =IF($A13=EDATE(DATE(2026,8,1),Inputs!$B$9),Inputs!$B$8,0) -> 0 | F13: =IF($A13=EDATE(DATE(2026,8,1),Inputs!$B$11),Inputs!$B$10,0) -> 0 | G13: =IF(Inputs!$B$16=1,((IF(YEAR($A13)=2026,Inputs!$B$2,IF(YEAR($A13)=2027,IF(MONTH($A13)>=Inputs!#REF!,Inputs!$B$2*(1+Inputs!$B$4),Inputs!$B$2),IF(YEAR($A13)=2028,IF(MONTH($A13)>=Inputs!#REF!,Inputs!$B$2*(1+Inputs!$B$4)*(1+Inputs!$B$5),Inputs!$B$2*(1+Inputs!$B$4)),IF(YEAR($A13)=2029,IF(MONTH($A13)>=Inputs!#REF!,Inputs!$B$2*(1+Inputs!$B$4)*(1+Inputs!$B$5)*(1+Inputs!$B$6),Inputs!$B$2*(1+Inputs!$B$4)*(1+Inputs!$B$5)),IF(MONTH($A13)>=Inputs!#REF!,Inputs!$B$2*(1+Inputs!$B$4)*(1+Inputs!$B$5)*(1+Inputs!$B$6)*(1+Inputs!$B$7),Inputs!$B$2*(1+Inputs!$B$4)*(1+Inputs!$B$5)*(1+Inputs!$B$6)))))))/12)*(MIN(Inputs!$B$17,Inputs!$B$18)*(1+Inputs!$B$19)+Inputs!$B$17*Inputs!$B$20),0) -> 0 | H13: =SUM(B13:G13) -> 4291.6667 | I13: =$H13-J13-K13 -> 3369 | J13: =_xlfn.SINGLE(_xlfn.LET(_xlpm.d, $A13, _xlpm.ys, YEAR(_xlfn.SINGLE(_xlpm.d)) - IF(MONTH(_xlfn.SINGLE(_xlpm.d)) < UK_TaxYear_Start_Month, 1, 0), _xlpm.start, DATE(_xlfn.SINGLE(_xlpm.ys), UK_TaxYear_Start_Month, 1), _xlpm.m, DATEDIF(_xlfn.SINGLE(_xlpm.start), _xlfn.SINGLE(_xlpm.d), "m") + 1, _xlpm.cum, SUMIFS($H$2:$H$54, $A$2:$A$54, ">=" & _xlfn.SINGLE(_xlpm.start), $A$2:$A$54, "<=" & _xlfn.SINGLE(_xlpm.d)), _xlpm.pa, UK_Personal_Allowance_Annual / 12 * _xlfn.SINGLE(_xlpm.m), _xlpm.br, (UK_Basic_Band_Upper_Annual - UK_Personal_Allowance_Annual) / 12 * _xlfn.SINGLE(_xlpm.m), _xlpm.hr, (UK_Higher_Band_Upper_Annual - UK_Basic_Band_Upper_Annual) / 12 * _xlfn.SINGLE(_xlpm.m), _xlpm.taxable, MAX(0, _xlfn.SINGLE(_xlpm.cum) - _xlfn.SINGLE(_xlpm.pa)), _xlpm.tax_to_date, UK_Basic_Rate * MIN(_xlpm.taxable, _xlpm.br) + UK_Higher_Rate * MIN(MAX(_xlfn.SINGLE(_xlpm.taxable) - _xlfn.SINGLE(_xlpm.br), 0), _xlpm.hr) + UK_Additional_Rate * MAX(_xlfn.SINGLE(_xlpm.taxable) - _xlfn.SINGLE(_xlpm.br) - _xlfn.SINGLE(_xlpm.hr), 0), _xlpm.prior, SUMIFS($J$2:$J$54, $A$2:$A$54, ">=" & _xlfn.SINGLE(_xlpm.start), $A$2:$A$54, "<" & _xlfn.SINGLE(_xlpm.d)), MAX(0, _xlfn.SINGLE(_xlpm.tax_to_date) - _xlfn.SINGLE(_xlpm.prior)))) -> 669.33333 | K13: =_xlfn.SINGLE(_xlfn.LET(_xlpm.g, $H13, _xlpm.pt, UK_NI_PT_Monthly, _xlpm.uel, UK_NI_UEL_Monthly, IF(_xlfn.SINGLE(_xlpm.g) <= _xlfn.SINGLE(_xlpm.pt), 0, UK_NI_Main_Rate * MIN(_xlfn.SINGLE(_xlpm.g) - _xlfn.SINGLE(_xlpm.pt), _xlfn.SINGLE(_xlpm.uel) - _xlfn.SINGLE(_xlpm.pt)) + UK_NI_Upper_Rate * MAX(_xlfn.SINGLE(_xlpm.g) - _xlfn.SINGLE(_xlpm.uel), 0)))) -> 253.33333 | L13: =IF($A13<DATE(2026,10,1),Bonus_Pct_Aug2026_to_Sep2026,IF($A13<DATE(2027,10,1),Bonus_Pct_Oct2026_to_Sep2027,IF($A13<DATE(2028,10,1),Bonus_Pct_Oct2027_to_Sep2028,IF($A13<DATE(2029,10,1),Bonus_Pct_Oct2028_to_Sep2029,Bonus_Pct_Oct2029_onwards)))) -> 0.08 | M13: Take-Home Estimate in 2027 | N13: =(N7-Living_Expenses_GBP_Monthly_2027*12)*FX_USD_per_GBP -> 23724.555
A14: 46600 | B14: =(IF(YEAR($A14)=2026,Base_Annual_Salary_GBP,IF(YEAR($A14)=2027,Base_Annual_Salary_GBP*(IF(MONTH($A14)>=4,(1+Raise_Pct_Apr2027),1)*IF(MONTH($A14)>=10,(1+Raise_Pct_Nov2027),1)),IF(YEAR($A14)=2028,Base_Annual_Salary_GBP*((1+Raise_Pct_Apr2027)*(1+Raise_Pct_Nov2027))*(IF(MONTH($A14)>=4,(1+Raise_Pct_Apr2028),1)*IF(MONTH($A14)>=10,(1+Raise_Pct_Nov2028),1)),IF(YEAR($A14)=2029,Base_Annual_Salary_GBP*((1+Raise_Pct_Apr2027)*(1+Raise_Pct_Nov2027)*(1+Raise_Pct_Apr2028)*(1+Raise_Pct_Nov2028))*(IF(MONTH($A14)>=4,(1+Raise_Pct_Apr2029),1)*IF(MONTH($A14)>=10,(1+Raise_Pct_Nov2029),1)),Base_Annual_Salary_GBP*((1+Raise_Pct_Apr2027)*(1+Raise_Pct_Nov2027)*(1+Raise_Pct_Apr2028)*(1+Raise_Pct_Nov2028)*(1+Raise_Pct_Apr2029)*(1+Raise_Pct_Nov2029))*(IF(MONTH($A14)>=4,(1+Raise_Pct_Apr2030),1)*IF(MONTH($A14)>=10,(1+Raise_Pct_Nov2030),1)))))))/12 -> 4291.6667 | C14: =IF(MONTH($A14)=11,((IF(DATE(YEAR($A14),4,1)<DATE(2026,10,1),Bonus_Pct_Aug2026_to_Sep2026,IF(DATE(YEAR($A14),4,1)<DATE(2027,10,1),Bonus_Pct_Oct2026_to_Sep2027,IF(DATE(YEAR($A14),4,1)<DATE(2028,10,1),Bonus_Pct_Oct2027_to_Sep2028,IF(DATE(YEAR($A14),4,1)<DATE(2029,10,1),Bonus_Pct_Oct2028_to_Sep2029,Bonus_Pct_Oct2029_onwards)))))/2)*($B14*12) / (1 + IF(YEAR($A14)=2027,Raise_Pct_Nov2027,IF(YEAR($A14)=2028,Raise_Pct_Nov2028,IF(YEAR($A14)=2029,Raise_Pct_Nov2029,IF(YEAR($A14)=2030,Raise_Pct_Nov2030,0))))) * IF(YEAR($A14)=2026,2/6,1),IF(MONTH($A14)=5,((IF(DATE(YEAR($A14)-1,10,1)<DATE(2026,10,1),Bonus_Pct_Aug2026_to_Sep2026,IF(DATE(YEAR($A14)-1,10,1)<DATE(2027,10,1),Bonus_Pct_Oct2026_to_Sep2027,IF(DATE(YEAR($A14)-1,10,1)<DATE(2028,10,1),Bonus_Pct_Oct2027_to_Sep2028,IF(DATE(YEAR($A14)-1,10,1)<DATE(2029,10,1),Bonus_Pct_Oct2028_to_Sep2029,Bonus_Pct_Oct2029_onwards)))))/2)*($B14*12) / (1 + IF(YEAR($A14)=2027,Raise_Pct_Apr2027,IF(YEAR($A14)=2028,Raise_Pct_Apr2028,IF(YEAR($A14)=2029,Raise_Pct_Apr2029,IF(YEAR($A14)=2030,Raise_Pct_Apr2030,0))))),0)) -> 0 | D14: =IF(OR($A14=DATE(2027,9,1),$A14=EDATE(DATE(2027,9,1),12),$A14=EDATE(DATE(2027,9,1),24)),(New_Hire_Stock_Grant_USD/3)/FX_USD_per_GBP*(1+IF(YEAR($A14)=2027,Inputs!$B$56,IF(YEAR($A14)=2028,Inputs!$B$57,IF(YEAR($A14)=2029,Inputs!$B$58,0)))),0)+IF(OR($A14=DATE(2028,11,1),$A14=DATE(2029,11,1),$A14=DATE(2030,11,1)),(RSU_Grant_Nov2027_USD/3)/FX_USD_per_GBP*(1+RSU_Price_Change_Pct)^(YEAR($A14)-2028),0)+IF(OR($A14=DATE(2029,11,1),$A14=DATE(2030,11,1)),(RSU_Grant_Nov2028_USD/3)/FX_USD_per_GBP*(1+RSU_Price_Change_Pct)^(YEAR($A14)-2029),0)+IF($A14=DATE(2030,11,1),(RSU_Grant_Nov2029_USD/3)/FX_USD_per_GBP*(1+RSU_Price_Change_Pct)^(YEAR($A14)-2030),0) -> 0 | E14: =IF($A14=EDATE(DATE(2026,8,1),Inputs!$B$9),Inputs!$B$8,0) -> 0 | F14: =IF($A14=EDATE(DATE(2026,8,1),Inputs!$B$11),Inputs!$B$10,0) -> 0 | G14: =IF(Inputs!$B$16=1,((IF(YEAR($A14)=2026,Inputs!$B$2,IF(YEAR($A14)=2027,IF(MONTH($A14)>=Inputs!#REF!,Inputs!$B$2*(1+Inputs!$B$4),Inputs!$B$2),IF(YEAR($A14)=2028,IF(MONTH($A14)>=Inputs!#REF!,Inputs!$B$2*(1+Inputs!$B$4)*(1+Inputs!$B$5),Inputs!$B$2*(1+Inputs!$B$4)),IF(YEAR($A14)=2029,IF(MONTH($A14)>=Inputs!#REF!,Inputs!$B$2*(1+Inputs!$B$4)*(1+Inputs!$B$5)*(1+Inputs!$B$6),Inputs!$B$2*(1+Inputs!$B$4)*(1+Inputs!$B$5)),IF(MONTH($A14)>=Inputs!#REF!,Inputs!$B$2*(1+Inputs!$B$4)*(1+Inputs!$B$5)*(1+Inputs!$B$6)*(1+Inputs!$B$7),Inputs!$B$2*(1+Inputs!$B$4)*(1+Inputs!$B$5)*(1+Inputs!$B$6)))))))/12)*(MIN(Inputs!$B$17,Inputs!$B$18)*(1+Inputs!$B$19)+Inputs!$B$17*Inputs!$B$20),0) -> 0 | H14: =SUM(B14:G14) -> 4291.6667 | I14: =$H14-J14-K14 -> 3369 | J14: =_xlfn.SINGLE(_xlfn.LET(_xlpm.d, $A14, _xlpm.ys, YEAR(_xlfn.SINGLE(_xlpm.d)) - IF(MONTH(_xlfn.SINGLE(_xlpm.d)) < UK_TaxYear_Start_Month, 1, 0), _xlpm.start, DATE(_xlfn.SINGLE(_xlpm.ys), UK_TaxYear_Start_Month, 1), _xlpm.m, DATEDIF(_xlfn.SINGLE(_xlpm.start), _xlfn.SINGLE(_xlpm.d), "m") + 1, _xlpm.cum, SUMIFS($H$2:$H$54, $A$2:$A$54, ">=" & _xlfn.SINGLE(_xlpm.start), $A$2:$A$54, "<=" & _xlfn.SINGLE(_xlpm.d)), _xlpm.pa, UK_Personal_Allowance_Annual / 12 * _xlfn.SINGLE(_xlpm.m), _xlpm.br, (UK_Basic_Band_Upper_Annual - UK_Personal_Allowance_Annual) / 12 * _xlfn.SINGLE(_xlpm.m), _xlpm.hr, (UK_Higher_Band_Upper_Annual - UK_Basic_Band_Upper_Annual) / 12 * _xlfn.SINGLE(_xlpm.m), _xlpm.taxable, MAX(0, _xlfn.SINGLE(_xlpm.cum) - _xlfn.SINGLE(_xlpm.pa)), _xlpm.tax_to_date, UK_Basic_Rate * MIN(_xlpm.taxable, _xlpm.br) + UK_Higher_Rate * MIN(MAX(_xlfn.SINGLE(_xlpm.taxable) - _xlfn.SINGLE(_xlpm.br), 0), _xlpm.hr) + UK_Additional_Rate * MAX(_xlfn.SINGLE(_xlpm.taxable) - _xlfn.SINGLE(_xlpm.br) - _xlfn.SINGLE(_xlpm.hr), 0), _xlpm.prior, SUMIFS($J$2:$J$54, $A$2:$A$54, ">=" & _xlfn.SINGLE(_xlpm.start), $A$2:$A$54, "<" & _xlfn.SINGLE(_xlpm.d)), MAX(0, _xlfn.SINGLE(_xlpm.tax_to_date) - _xlfn.SINGLE(_xlpm.prior)))) -> 669.33333 | K14: =_xlfn.SINGLE(_xlfn.LET(_xlpm.g, $H14, _xlpm.pt, UK_NI_PT_Monthly, _xlpm.uel, UK_NI_UEL_Monthly, IF(_xlfn.SINGLE(_xlpm.g) <= _xlfn.SINGLE(_xlpm.pt), 0, UK_NI_Main_Rate * MIN(_xlfn.SINGLE(_xlpm.g) - _xlfn.SINGLE(_xlpm.pt), _xlfn.SINGLE(_xlpm.uel) - _xlfn.SINGLE(_xlpm.pt)) + UK_NI_Upper_Rate * MAX(_xlfn.SINGLE(_xlpm.g) - _xlfn.SINGLE(_xlpm.uel), 0)))) -> 253.33333 | L14: =IF($A14<DATE(2026,10,1),Bonus_Pct_Aug2026_to_Sep2026,IF($A14<DATE(2027,10,1),Bonus_Pct_Oct2026_to_Sep2027,IF($A14<DATE(2028,10,1),Bonus_Pct_Oct2027_to_Sep2028,IF($A14<DATE(2029,10,1),Bonus_Pct_Oct2028_to_Sep2029,Bonus_Pct_Oct2029_onwards)))) -> 0.08 | M14: Take-Home Estimate in 2028 | N14: =(N8-Living_Expenses_GBP_Monthly_2028*12)*FX_USD_per_GBP -> 24558.133
A15: 46631 | B15: =(IF(YEAR($A15)=2026,Base_Annual_Salary_GBP,IF(YEAR($A15)=2027,Base_Annual_Salary_GBP*(IF(MONTH($A15)>=4,(1+Raise_Pct_Apr2027),1)*IF(MONTH($A15)>=10,(1+Raise_Pct_Nov2027),1)),IF(YEAR($A15)=2028,Base_Annual_Salary_GBP*((1+Raise_Pct_Apr2027)*(1+Raise_Pct_Nov2027))*(IF(MONTH($A15)>=4,(1+Raise_Pct_Apr2028),1)*IF(MONTH($A15)>=10,(1+Raise_Pct_Nov2028),1)),IF(YEAR($A15)=2029,Base_Annual_Salary_GBP*((1+Raise_Pct_Apr2027)*(1+Raise_Pct_Nov2027)*(1+Raise_Pct_Apr2028)*(1+Raise_Pct_Nov2028))*(IF(MONTH($A15)>=4,(1+Raise_Pct_Apr2029),1)*IF(MONTH($A15)>=10,(1+Raise_Pct_Nov2029),1)),Base_Annual_Salary_GBP*((1+Raise_Pct_Apr2027)*(1+Raise_Pct_Nov2027)*(1+Raise_Pct_Apr2028)*(1+Raise_Pct_Nov2028)*(1+Raise_Pct_Apr2029)*(1+Raise_Pct_Nov2029))*(IF(MONTH($A15)>=4,(1+Raise_Pct_Apr2030),1)*IF(MONTH($A15)>=10,(1+Raise_Pct_Nov2030),1)))))))/12 -> 4291.6667 | C15: =IF(MONTH($A15)=11,((IF(DATE(YEAR($A15),4,1)<DATE(2026,10,1),Bonus_Pct_Aug2026_to_Sep2026,IF(DATE(YEAR($A15),4,1)<DATE(2027,10,1),Bonus_Pct_Oct2026_to_Sep2027,IF(DATE(YEAR($A15),4,1)<DATE(2028,10,1),Bonus_Pct_Oct2027_to_Sep2028,IF(DATE(YEAR($A15),4,1)<DATE(2029,10,1),Bonus_Pct_Oct2028_to_Sep2029,Bonus_Pct_Oct2029_onwards)))))/2)*($B15*12) / (1 + IF(YEAR($A15)=2027,Raise_Pct_Nov2027,IF(YEAR($A15)=2028,Raise_Pct_Nov2028,IF(YEAR($A15)=2029,Raise_Pct_Nov2029,IF(YEAR($A15)=2030,Raise_Pct_Nov2030,0))))) * IF(YEAR($A15)=2026,2/6,1),IF(MONTH($A15)=5,((IF(DATE(YEAR($A15)-1,10,1)<DATE(2026,10,1),Bonus_Pct_Aug2026_to_Sep2026,IF(DATE(YEAR($A15)-1,10,1)<DATE(2027,10,1),Bonus_Pct_Oct2026_to_Sep2027,IF(DATE(YEAR($A15)-1,10,1)<DATE(2028,10,1),Bonus_Pct_Oct2027_to_Sep2028,IF(DATE(YEAR($A15)-1,10,1)<DATE(2029,10,1),Bonus_Pct_Oct2028_to_Sep2029,Bonus_Pct_Oct2029_onwards)))))/2)*($B15*12) / (1 + IF(YEAR($A15)=2027,Raise_Pct_Apr2027,IF(YEAR($A15)=2028,Raise_Pct_Apr2028,IF(YEAR($A15)=2029,Raise_Pct_Apr2029,IF(YEAR($A15)=2030,Raise_Pct_Apr2030,0))))),0)) -> 0 | D15: =IF(OR($A15=DATE(2027,9,1),$A15=EDATE(DATE(2027,9,1),12),$A15=EDATE(DATE(2027,9,1),24)),(New_Hire_Stock_Grant_USD/3)/FX_USD_per_GBP*(1+IF(YEAR($A15)=2027,Inputs!$B$56,IF(YEAR($A15)=2028,Inputs!$B$57,IF(YEAR($A15)=2029,Inputs!$B$58,0)))),0)+IF(OR($A15=DATE(2028,11,1),$A15=DATE(2029,11,1),$A15=DATE(2030,11,1)),(RSU_Grant_Nov2027_USD/3)/FX_USD_per_GBP*(1+RSU_Price_Change_Pct)^(YEAR($A15)-2028),0)+IF(OR($A15=DATE(2029,11,1),$A15=DATE(2030,11,1)),(RSU_Grant_Nov2028_USD/3)/FX_USD_per_GBP*(1+RSU_Price_Change_Pct)^(YEAR($A15)-2029),0)+IF($A15=DATE(2030,11,1),(RSU_Grant_Nov2029_USD/3)/FX_USD_per_GBP*(1+RSU_Price_Change_Pct)^(YEAR($A15)-2030),0) -> 7352.9412 | E15: =IF($A15=EDATE(DATE(2026,8,1),Inputs!$B$9),Inputs!$B$8,0) -> 0 | F15: =IF($A15=EDATE(DATE(2026,8,1),Inputs!$B$11),Inputs!$B$10,0) -> 0 | G15: =IF(Inputs!$B$16=1,((IF(YEAR($A15)=2026,Inputs!$B$2,IF(YEAR($A15)=2027,IF(MONTH($A15)>=Inputs!#REF!,Inputs!$B$2*(1+Inputs!$B$4),Inputs!$B$2),IF(YEAR($A15)=2028,IF(MONTH($A15)>=Inputs!#REF!,Inputs!$B$2*(1+Inputs!$B$4)*(1+Inputs!$B$5),Inputs!$B$2*(1+Inputs!$B$4)),IF(YEAR($A15)=2029,IF(MONTH($A15)>=Inputs!#REF!,Inputs!$B$2*(1+Inputs!$B$4)*(1+Inputs!$B$5)*(1+Inputs!$B$6),Inputs!$B$2*(1+Inputs!$B$4)*(1+Inputs!$B$5)),IF(MONTH($A15)>=Inputs!#REF!,Inputs!$B$2*(1+Inputs!$B$4)*(1+Inputs!$B$5)*(1+Inputs!$B$6)*(1+Inputs!$B$7),Inputs!$B$2*(1+Inputs!$B$4)*(1+Inputs!$B$5)*(1+Inputs!$B$6)))))))/12)*(MIN(Inputs!$B$17,Inputs!$B$18)*(1+Inputs!$B$19)+Inputs!$B$17*Inputs!$B$20),0) -> 0 | H15: =SUM(B15:G15) -> 11644.608 | I15: =$H15-J15-K15 -> 7633.7059 | J15: =_xlfn.SINGLE(_xlfn.LET(_xlpm.d, $A15, _xlpm.ys, YEAR(_xlfn.SINGLE(_xlpm.d)) - IF(MONTH(_xlfn.SINGLE(_xlpm.d)) < UK_TaxYear_Start_Month, 1, 0), _xlpm.start, DATE(_xlfn.SINGLE(_xlpm.ys), UK_TaxYear_Start_Month, 1), _xlpm.m, DATEDIF(_xlfn.SINGLE(_xlpm.start), _xlfn.SINGLE(_xlpm.d), "m") + 1, _xlpm.cum, SUMIFS($H$2:$H$54, $A$2:$A$54, ">=" & _xlfn.SINGLE(_xlpm.start), $A$2:$A$54, "<=" & _xlfn.SINGLE(_xlpm.d)), _xlpm.pa, UK_Personal_Allowance_Annual / 12 * _xlfn.SINGLE(_xlpm.m), _xlpm.br, (UK_Basic_Band_Upper_Annual - UK_Personal_Allowance_Annual) / 12 * _xlfn.SINGLE(_xlpm.m), _xlpm.hr, (UK_Higher_Band_Upper_Annual - UK_Basic_Band_Upper_Annual) / 12 * _xlfn.SINGLE(_xlpm.m), _xlpm.taxable, MAX(0, _xlfn.SINGLE(_xlpm.cum) - _xlfn.SINGLE(_xlpm.pa)), _xlpm.tax_to_date, UK_Basic_Rate * MIN(_xlpm.taxable, _xlpm.br) + UK_Higher_Rate * MIN(MAX(_xlfn.SINGLE(_xlpm.taxable) - _xlfn.SINGLE(_xlpm.br), 0), _xlpm.hr) + UK_Additional_Rate * MAX(_xlfn.SINGLE(_xlpm.taxable) - _xlfn.SINGLE(_xlpm.br) - _xlfn.SINGLE(_xlpm.hr), 0), _xlpm.prior, SUMIFS($J$2:$J$54, $A$2:$A$54, ">=" & _xlfn.SINGLE(_xlpm.start), $A$2:$A$54, "<" & _xlfn.SINGLE(_xlpm.d)), MAX(0, _xlfn.SINGLE(_xlpm.tax_to_date) - _xlfn.SINGLE(_xlpm.prior)))) -> 3610.5098 | K15: =_xlfn.SINGLE(_xlfn.LET(_xlpm.g, $H15, _xlpm.pt, UK_NI_PT_Monthly, _xlpm.uel, UK_NI_UEL_Monthly, IF(_xlfn.SINGLE(_xlpm.g) <= _xlfn.SINGLE(_xlpm.pt), 0, UK_NI_Main_Rate * MIN(_xlfn.SINGLE(_xlpm.g) - _xlfn.SINGLE(_xlpm.pt), _xlfn.SINGLE(_xlpm.uel) - _xlfn.SINGLE(_xlpm.pt)) + UK_NI_Upper_Rate * MAX(_xlfn.SINGLE(_xlpm.g) - _xlfn.SINGLE(_xlpm.uel), 0)))) -> 400.39216 | L15: =IF($A15<DATE(2026,10,1),Bonus_Pct_Aug2026_to_Sep2026,IF($A15<DATE(2027,10,1),Bonus_Pct_Oct2026_to_Sep2027,IF($A15<DATE(2028,10,1),Bonus_Pct_Oct2027_to_Sep2028,IF($A15<DATE(2029,10,1),Bonus_Pct_Oct2028_to_Sep2029,Bonus_Pct_Oct2029_onwards)))) -> 0.08 | M15: Take-Home Estimate in 2029 | N15: =(N9-Living_Expenses_GBP_Monthly_2029*12)*FX_USD_per_GBP -> 27034.685
A16: 46661 | B16: =(IF(YEAR($A16)=2026,Base_Annual_Salary_GBP,IF(YEAR($A16)=2027,Base_Annual_Salary_GBP*(IF(MONTH($A16)>=4,(1+Raise_Pct_Apr2027),1)*IF(MONTH($A16)>=10,(1+Raise_Pct_Nov2027),1)),IF(YEAR($A16)=2028,Base_Annual_Salary_GBP*((1+Raise_Pct_Apr2027)*(1+Raise_Pct_Nov2027))*(IF(MONTH($A16)>=4,(1+Raise_Pct_Apr2028),1)*IF(MONTH($A16)>=10,(1+Raise_Pct_Nov2028),1)),IF(YEAR($A16)=2029,Base_Annual_Salary_GBP*((1+Raise_Pct_Apr2027)*(1+Raise_Pct_Nov2027)*(1+Raise_Pct_Apr2028)*(1+Raise_Pct_Nov2028))*(IF(MONTH($A16)>=4,(1+Raise_Pct_Apr2029),1)*IF(MONTH($A16)>=10,(1+Raise_Pct_Nov2029),1)),Base_Annual_Salary_GBP*((1+Raise_Pct_Apr2027)*(1+Raise_Pct_Nov2027)*(1+Raise_Pct_Apr2028)*(1+Raise_Pct_Nov2028)*(1+Raise_Pct_Apr2029)*(1+Raise_Pct_Nov2029))*(IF(MONTH($A16)>=4,(1+Raise_Pct_Apr2030),1)*IF(MONTH($A16)>=10,(1+Raise_Pct_Nov2030),1)))))))/12 -> 4291.6667 | C16: =IF(MONTH($A16)=11,((IF(DATE(YEAR($A16),4,1)<DATE(2026,10,1),Bonus_Pct_Aug2026_to_Sep2026,IF(DATE(YEAR($A16),4,1)<DATE(2027,10,1),Bonus_Pct_Oct2026_to_Sep2027,IF(DATE(YEAR($A16),4,1)<DATE(2028,10,1),Bonus_Pct_Oct2027_to_Sep2028,IF(DATE(YEAR($A16),4,1)<DATE(2029,10,1),Bonus_Pct_Oct2028_to_Sep2029,Bonus_Pct_Oct2029_onwards)))))/2)*($B16*12) / (1 + IF(YEAR($A16)=2027,Raise_Pct_Nov2027,IF(YEAR($A16)=2028,Raise_Pct_Nov2028,IF(YEAR($A16)=2029,Raise_Pct_Nov2029,IF(YEAR($A16)=2030,Raise_Pct_Nov2030,0))))) * IF(YEAR($A16)=2026,2/6,1),IF(MONTH($A16)=5,((IF(DATE(YEAR($A16)-1,10,1)<DATE(2026,10,1),Bonus_Pct_Aug2026_to_Sep2026,IF(DATE(YEAR($A16)-1,10,1)<DATE(2027,10,1),Bonus_Pct_Oct2026_to_Sep2027,IF(DATE(YEAR($A16)-1,10,1)<DATE(2028,10,1),Bonus_Pct_Oct2027_to_Sep2028,IF(DATE(YEAR($A16)-1,10,1)<DATE(2029,10,1),Bonus_Pct_Oct2028_to_Sep2029,Bonus_Pct_Oct2029_onwards)))))/2)*($B16*12) / (1 + IF(YEAR($A16)=2027,Raise_Pct_Apr2027,IF(YEAR($A16)=2028,Raise_Pct_Apr2028,IF(YEAR($A16)=2029,Raise_Pct_Apr2029,IF(YEAR($A16)=2030,Raise_Pct_Apr2030,0))))),0)) -> 0 | D16: =IF(OR($A16=DATE(2027,9,1),$A16=EDATE(DATE(2027,9,1),12),$A16=EDATE(DATE(2027,9,1),24)),(New_Hire_Stock_Grant_USD/3)/FX_USD_per_GBP*(1+IF(YEAR($A16)=2027,Inputs!$B$56,IF(YEAR($A16)=2028,Inputs!$B$57,IF(YEAR($A16)=2029,Inputs!$B$58,0)))),0)+IF(OR($A16=DATE(2028,11,1),$A16=DATE(2029,11,1),$A16=DATE(2030,11,1)),(RSU_Grant_Nov2027_USD/3)/FX_USD_per_GBP*(1+RSU_Price_Change_Pct)^(YEAR($A16)-2028),0)+IF(OR($A16=DATE(2029,11,1),$A16=DATE(2030,11,1)),(RSU_Grant_Nov2028_USD/3)/FX_USD_per_GBP*(1+RSU_Price_Change_Pct)^(YEAR($A16)-2029),0)+IF($A16=DATE(2030,11,1),(RSU_Grant_Nov2029_USD/3)/FX_USD_per_GBP*(1+RSU_Price_Change_Pct)^(YEAR($A16)-2030),0) -> 0 | E16: =IF($A16=EDATE(DATE(2026,8,1),Inputs!$B$9),Inputs!$B$8,0) -> 0 | F16: =IF($A16=EDATE(DATE(2026,8,1),Inputs!$B$11),Inputs!$B$10,0) -> 0 | G16: =IF(Inputs!$B$16=1,((IF(YEAR($A16)=2026,Inputs!$B$2,IF(YEAR($A16)=2027,IF(MONTH($A16)>=Inputs!#REF!,Inputs!$B$2*(1+Inputs!$B$4),Inputs!$B$2),IF(YEAR($A16)=2028,IF(MONTH($A16)>=Inputs!#REF!,Inputs!$B$2*(1+Inputs!$B$4)*(1+Inputs!$B$5),Inputs!$B$2*(1+Inputs!$B$4)),IF(YEAR($A16)=2029,IF(MONTH($A16)>=Inputs!#REF!,Inputs!$B$2*(1+Inputs!$B$4)*(1+Inputs!$B$5)*(1+Inputs!$B$6),Inputs!$B$2*(1+Inputs!$B$4)*(1+Inputs!$B$5)),IF(MONTH($A16)>=Inputs!#REF!,Inputs!$B$2*(1+Inputs!$B$4)*(1+Inputs!$B$5)*(1+Inputs!$B$6)*(1+Inputs!$B$7),Inputs!$B$2*(1+Inputs!$B$4)*(1+Inputs!$B$5)*(1+Inputs!$B$6)))))))/12)*(MIN(Inputs!$B$17,Inputs!$B$18)*(1+Inputs!$B$19)+Inputs!$B$17*Inputs!$B$20),0) -> 0 | H16: =SUM(B16:G16) -> 4291.6667 | I16: =$H16-J16-K16 -> 3369 | J16: =_xlfn.SINGLE(_xlfn.LET(_xlpm.d, $A16, _xlpm.ys, YEAR(_xlfn.SINGLE(_xlpm.d)) - IF(MONTH(_xlfn.SINGLE(_xlpm.d)) < UK_TaxYear_Start_Month, 1, 0), _xlpm.start, DATE(_xlfn.SINGLE(_xlpm.ys), UK_TaxYear_Start_Month, 1), _xlpm.m, DATEDIF(_xlfn.SINGLE(_xlpm.start), _xlfn.SINGLE(_xlpm.d), "m") + 1, _xlpm.cum, SUMIFS($H$2:$H$54, $A$2:$A$54, ">=" & _xlfn.SINGLE(_xlpm.start), $A$2:$A$54, "<=" & _xlfn.SINGLE(_xlpm.d)), _xlpm.pa, UK_Personal_Allowance_Annual / 12 * _xlfn.SINGLE(_xlpm.m), _xlpm.br, (UK_Basic_Band_Upper_Annual - UK_Personal_Allowance_Annual) / 12 * _xlfn.SINGLE(_xlpm.m), _xlpm.hr, (UK_Higher_Band_Upper_Annual - UK_Basic_Band_Upper_Annual) / 12 * _xlfn.SINGLE(_xlpm.m), _xlpm.taxable, MAX(0, _xlfn.SINGLE(_xlpm.cum) - _xlfn.SINGLE(_xlpm.pa)), _xlpm.tax_to_date, UK_Basic_Rate * MIN(_xlpm.taxable, _xlpm.br) + UK_Higher_Rate * MIN(MAX(_xlfn.SINGLE(_xlpm.taxable) - _xlfn.SINGLE(_xlpm.br), 0), _xlpm.hr) + UK_Additional_Rate * MAX(_xlfn.SINGLE(_xlpm.taxable) - _xlfn.SINGLE(_xlpm.br) - _xlfn.SINGLE(_xlpm.hr), 0), _xlpm.prior, SUMIFS($J$2:$J$54, $A$2:$A$54, ">=" & _xlfn.SINGLE(_xlpm.start), $A$2:$A$54, "<" & _xlfn.SINGLE(_xlpm.d)), MAX(0, _xlfn.SINGLE(_xlpm.tax_to_date) - _xlfn.SINGLE(_xlpm.prior)))) -> 669.33333 | K16: =_xlfn.SINGLE(_xlfn.LET(_xlpm.g, $H16, _xlpm.pt, UK_NI_PT_Monthly, _xlpm.uel, UK_NI_UEL_Monthly, IF(_xlfn.SINGLE(_xlpm.g) <= _xlfn.SINGLE(_xlpm.pt), 0, UK_NI_Main_Rate * MIN(_xlfn.SINGLE(_xlpm.g) - _xlfn.SINGLE(_xlpm.pt), _xlfn.SINGLE(_xlpm.uel) - _xlfn.SINGLE(_xlpm.pt)) + UK_NI_Upper_Rate * MAX(_xlfn.SINGLE(_xlpm.g) - _xlfn.SINGLE(_xlpm.uel), 0)))) -> 253.33333 | L16: =IF($A16<DATE(2026,10,1),Bonus_Pct_Aug2026_to_Sep2026,IF($A16<DATE(2027,10,1),Bonus_Pct_Oct2026_to_Sep2027,IF($A16<DATE(2028,10,1),Bonus_Pct_Oct2027_to_Sep2028,IF($A16<DATE(2029,10,1),Bonus_Pct_Oct2028_to_Sep2029,Bonus_Pct_Oct2029_onwards)))) -> 0.08 | M16: Take-Home Estimate in 2030 | N16: =(N10-Living_Expenses_GBP_Monthly_2030*12)*FX_USD_per_GBP -> 21856.613
A17: 46692 | B17: =(IF(YEAR($A17)=2026,Base_Annual_Salary_GBP,IF(YEAR($A17)=2027,Base_Annual_Salary_GBP*(IF(MONTH($A17)>=4,(1+Raise_Pct_Apr2027),1)*IF(MONTH($A17)>=10,(1+Raise_Pct_Nov2027),1)),IF(YEAR($A17)=2028,Base_Annual_Salary_GBP*((1+Raise_Pct_Apr2027)*(1+Raise_Pct_Nov2027))*(IF(MONTH($A17)>=4,(1+Raise_Pct_Apr2028),1)*IF(MONTH($A17)>=10,(1+Raise_Pct_Nov2028),1)),IF(YEAR($A17)=2029,Base_Annual_Salary_GBP*((1+Raise_Pct_Apr2027)*(1+Raise_Pct_Nov2027)*(1+Raise_Pct_Apr2028)*(1+Raise_Pct_Nov2028))*(IF(MONTH($A17)>=4,(1+Raise_Pct_Apr2029),1)*IF(MONTH($A17)>=10,(1+Raise_Pct_Nov2029),1)),Base_Annual_Salary_GBP*((1+Raise_Pct_Apr2027)*(1+Raise_Pct_Nov2027)*(1+Raise_Pct_Apr2028)*(1+Raise_Pct_Nov2028)*(1+Raise_Pct_Apr2029)*(1+Raise_Pct_Nov2029))*(IF(MONTH($A17)>=4,(1+Raise_Pct_Apr2030),1)*IF(MONTH($A17)>=10,(1+Raise_Pct_Nov2030),1)))))))/12 -> 4291.6667 | C17: =IF(MONTH($A17)=11,((IF(DATE(YEAR($A17),4,1)<DATE(2026,10,1),Bonus_Pct_Aug2026_to_Sep2026,IF(DATE(YEAR($A17),4,1)<DATE(2027,10,1),Bonus_Pct_Oct2026_to_Sep2027,IF(DATE(YEAR($A17),4,1)<DATE(2028,10,1),Bonus_Pct_Oct2027_to_Sep2028,IF(DATE(YEAR($A17),4,1)<DATE(2029,10,1),Bonus_Pct_Oct2028_to_Sep2029,Bonus_Pct_Oct2029_onwards)))))/2)*($B17*12) / (1 + IF(YEAR($A17)=2027,Raise_Pct_Nov2027,IF(YEAR($A17)=2028,Raise_Pct_Nov2028,IF(YEAR($A17)=2029,Raise_Pct_Nov2029,IF(YEAR($A17)=2030,Raise_Pct_Nov2030,0))))) * IF(YEAR($A17)=2026,2/6,1),IF(MONTH($A17)=5,((IF(DATE(YEAR($A17)-1,10,1)<DATE(2026,10,1),Bonus_Pct_Aug2026_to_Sep2026,IF(DATE(YEAR($A17)-1,10,1)<DATE(2027,10,1),Bonus_Pct_Oct2026_to_Sep2027,IF(DATE(YEAR($A17)-1,10,1)<DATE(2028,10,1),Bonus_Pct_Oct2027_to_Sep2028,IF(DATE(YEAR($A17)-1,10,1)<DATE(2029,10,1),Bonus_Pct_Oct2028_to_Sep2029,Bonus_Pct_Oct2029_onwards)))))/2)*($B17*12) / (1 + IF(YEAR($A17)=2027,Raise_Pct_Apr2027,IF(YEAR($A17)=2028,Raise_Pct_Apr2028,IF(YEAR($A17)=2029,Raise_Pct_Apr2029,IF(YEAR($A17)=2030,Raise_Pct_Apr2030,0))))),0)) -> 2060 | D17: =IF(OR($A17=DATE(2027,9,1),$A17=EDATE(DATE(2027,9,1),12),$A17=EDATE(DATE(2027,9,1),24)),(New_Hire_Stock_Grant_USD/3)/FX_USD_per_GBP*(1+IF(YEAR($A17)=2027,Inputs!$B$56,IF(YEAR($A17)=2028,Inputs!$B$57,IF(YEAR($A17)=2029,Inputs!$B$58,0)))),0)+IF(OR($A17=DATE(2028,11,1),$A17=DATE(2029,11,1),$A17=DATE(2030,11,1)),(RSU_Grant_Nov2027_USD/3)/FX_USD_per_GBP*(1+RSU_Price_Change_Pct)^(YEAR($A17)-2028),0)+IF(OR($A17=DATE(2029,11,1),$A17=DATE(2030,11,1)),(RSU_Grant_Nov2028_USD/3)/FX_USD_per_GBP*(1+RSU_Price_Change_Pct)^(YEAR($A17)-2029),0)+IF($A17=DATE(2030,11,1),(RSU_Grant_Nov2029_USD/3)/FX_USD_per_GBP*(1+RSU_Price_Change_Pct)^(YEAR($A17)-2030),0) -> 0 | E17: =IF($A17=EDATE(DATE(2026,8,1),Inputs!$B$9),Inputs!$B$8,0) -> 0 | F17: =IF($A17=EDATE(DATE(2026,8,1),Inputs!$B$11),Inputs!$B$10,0) -> 0 | G17: =IF(Inputs!$B$16=1,((IF(YEAR($A17)=2026,Inputs!$B$2,IF(YEAR($A17)=2027,IF(MONTH($A17)>=Inputs!#REF!,Inputs!$B$2*(1+Inputs!$B$4),Inputs!$B$2),IF(YEAR($A17)=2028,IF(MONTH($A17)>=Inputs!#REF!,Inputs!$B$2*(1+Inputs!$B$4)*(1+Inputs!$B$5),Inputs!$B$2*(1+Inputs!$B$4)),IF(YEAR($A17)=2029,IF(MONTH($A17)>=Inputs!#REF!,Inputs!$B$2*(1+Inputs!$B$4)*(1+Inputs!$B$5)*(1+Inputs!$B$6),Inputs!$B$2*(1+Inputs!$B$4)*(1+Inputs!$B$5)),IF(MONTH($A17)>=Inputs!#REF!,Inputs!$B$2*(1+Inputs!$B$4)*(1+Inputs!$B$5)*(1+Inputs!$B$6)*(1+Inputs!$B$7),Inputs!$B$2*(1+Inputs!$B$4)*(1+Inputs!$B$5)*(1+Inputs!$B$6)))))))/12)*(MIN(Inputs!$B$17,Inputs!$B$18)*(1+Inputs!$B$19)+Inputs!$B$17*Inputs!$B$20),0) -> 0 | H17: =SUM(B17:G17) -> 6351.6667 | I17: =$H17-J17-K17 -> 4563.8 | J17: =_xlfn.SINGLE(_xlfn.LET(_xlpm.d, $A17, _xlpm.ys, YEAR(_xlfn.SINGLE(_xlpm.d)) - IF(MONTH(_xlfn.SINGLE(_xlpm.d)) < UK_TaxYear_Start_Month, 1, 0), _xlpm.start, DATE(_xlfn.SINGLE(_xlpm.ys), UK_TaxYear_Start_Month, 1), _xlpm.m, DATEDIF(_xlfn.SINGLE(_xlpm.start), _xlfn.SINGLE(_xlpm.d), "m") + 1, _xlpm.cum, SUMIFS($H$2:$H$54, $A$2:$A$54, ">=" & _xlfn.SINGLE(_xlpm.start), $A$2:$A$54, "<=" & _xlfn.SINGLE(_xlpm.d)), _xlpm.pa, UK_Personal_Allowance_Annual / 12 * _xlfn.SINGLE(_xlpm.m), _xlpm.br, (UK_Basic_Band_Upper_Annual - UK_Personal_Allowance_Annual) / 12 * _xlfn.SINGLE(_xlpm.m), _xlpm.hr, (UK_Higher_Band_Upper_Annual - UK_Basic_Band_Upper_Annual) / 12 * _xlfn.SINGLE(_xlpm.m), _xlpm.taxable, MAX(0, _xlfn.SINGLE(_xlpm.cum) - _xlfn.SINGLE(_xlpm.pa)), _xlpm.tax_to_date, UK_Basic_Rate * MIN(_xlpm.taxable, _xlpm.br) + UK_Higher_Rate * MIN(MAX(_xlfn.SINGLE(_xlpm.taxable) - _xlfn.SINGLE(_xlpm.br), 0), _xlpm.hr) + UK_Additional_Rate * MAX(_xlfn.SINGLE(_xlpm.taxable) - _xlfn.SINGLE(_xlpm.br) - _xlfn.SINGLE(_xlpm.hr), 0), _xlpm.prior, SUMIFS($J$2:$J$54, $A$2:$A$54, ">=" & _xlfn.SINGLE(_xlpm.start), $A$2:$A$54, "<" & _xlfn.SINGLE(_xlpm.d)), MAX(0, _xlfn.SINGLE(_xlpm.tax_to_date) - _xlfn.SINGLE(_xlpm.prior)))) -> 1493.3333 | K17: =_xlfn.SINGLE(_xlfn.LET(_xlpm.g, $H17, _xlpm.pt, UK_NI_PT_Monthly, _xlpm.uel, UK_NI_UEL_Monthly, IF(_xlfn.SINGLE(_xlpm.g) <= _xlfn.SINGLE(_xlpm.pt), 0, UK_NI_Main_Rate * MIN(_xlfn.SINGLE(_xlpm.g) - _xlfn.SINGLE(_xlpm.pt), _xlfn.SINGLE(_xlpm.uel) - _xlfn.SINGLE(_xlpm.pt)) + UK_NI_Upper_Rate * MAX(_xlfn.SINGLE(_xlpm.g) - _xlfn.SINGLE(_xlpm.uel), 0)))) -> 294.53333 | L17: =IF($A17<DATE(2026,10,1),Bonus_Pct_Aug2026_to_Sep2026,IF($A17<DATE(2027,10,1),Bonus_Pct_Oct2026_to_Sep2027,IF($A17<DATE(2028,10,1),Bonus_Pct_Oct2027_to_Sep2028,IF($A17<DATE(2029,10,1),Bonus_Pct_Oct2028_to_Sep2029,Bonus_Pct_Oct2029_onwards)))) -> 0.08
A18: 46722 | B18: =(IF(YEAR($A18)=2026,Base_Annual_Salary_GBP,IF(YEAR($A18)=2027,Base_Annual_Salary_GBP*(IF(MONTH($A18)>=4,(1+Raise_Pct_Apr2027),1)*IF(MONTH($A18)>=10,(1+Raise_Pct_Nov2027),1)),IF(YEAR($A18)=2028,Base_Annual_Salary_GBP*((1+Raise_Pct_Apr2027)*(1+Raise_Pct_Nov2027))*(IF(MONTH($A18)>=4,(1+Raise_Pct_Apr2028),1)*IF(MONTH($A18)>=10,(1+Raise_Pct_Nov2028),1)),IF(YEAR($A18)=2029,Base_Annual_Salary_GBP*((1+Raise_Pct_Apr2027)*(1+Raise_Pct_Nov2027)*(1+Raise_Pct_Apr2028)*(1+Raise_Pct_Nov2028))*(IF(MONTH($A18)>=4,(1+Raise_Pct_Apr2029),1)*IF(MONTH($A18)>=10,(1+Raise_Pct_Nov2029),1)),Base_Annual_Salary_GBP*((1+Raise_Pct_Apr2027)*(1+Raise_Pct_Nov2027)*(1+Raise_Pct_Apr2028)*(1+Raise_Pct_Nov2028)*(1+Raise_Pct_Apr2029)*(1+Raise_Pct_Nov2029))*(IF(MONTH($A18)>=4,(1+Raise_Pct_Apr2030),1)*IF(MONTH($A18)>=10,(1+Raise_Pct_Nov2030),1)))))))/12 -> 4291.6667 | C18: =IF(MONTH($A18)=11,((IF(DATE(YEAR($A18),4,1)<DATE(2026,10,1),Bonus_Pct_Aug2026_to_Sep2026,IF(DATE(YEAR($A18),4,1)<DATE(2027,10,1),Bonus_Pct_Oct2026_to_Sep2027,IF(DATE(YEAR($A18),4,1)<DATE(2028,10,1),Bonus_Pct_Oct2027_to_Sep2028,IF(DATE(YEAR($A18),4,1)<DATE(2029,10,1),Bonus_Pct_Oct2028_to_Sep2029,Bonus_Pct_Oct2029_onwards)))))/2)*($B18*12) / (1 + IF(YEAR($A18)=2027,Raise_Pct_Nov2027,IF(YEAR($A18)=2028,Raise_Pct_Nov2028,IF(YEAR($A18)=2029,Raise_Pct_Nov2029,IF(YEAR($A18)=2030,Raise_Pct_Nov2030,0))))) * IF(YEAR($A18)=2026,2/6,1),IF(MONTH($A18)=5,((IF(DATE(YEAR($A18)-1,10,1)<DATE(2026,10,1),Bonus_Pct_Aug2026_to_Sep2026,IF(DATE(YEAR($A18)-1,10,1)<DATE(2027,10,1),Bonus_Pct_Oct2026_to_Sep2027,IF(DATE(YEAR($A18)-1,10,1)<DATE(2028,10,1),Bonus_Pct_Oct2027_to_Sep2028,IF(DATE(YEAR($A18)-1,10,1)<DATE(2029,10,1),Bonus_Pct_Oct2028_to_Sep2029,Bonus_Pct_Oct2029_onwards)))))/2)*($B18*12) / (1 + IF(YEAR($A18)=2027,Raise_Pct_Apr2027,IF(YEAR($A18)=2028,Raise_Pct_Apr2028,IF(YEAR($A18)=2029,Raise_Pct_Apr2029,IF(YEAR($A18)=2030,Raise_Pct_Apr2030,0))))),0)) -> 0 | D18: =IF(OR($A18=DATE(2027,9,1),$A18=EDATE(DATE(2027,9,1),12),$A18=EDATE(DATE(2027,9,1),24)),(New_Hire_Stock_Grant_USD/3)/FX_USD_per_GBP*(1+IF(YEAR($A18)=2027,Inputs!$B$56,IF(YEAR($A18)=2028,Inputs!$B$57,IF(YEAR($A18)=2029,Inputs!$B$58,0)))),0)+IF(OR($A18=DATE(2028,11,1),$A18=DATE(2029,11,1),$A18=DATE(2030,11,1)),(RSU_Grant_Nov2027_USD/3)/FX_USD_per_GBP*(1+RSU_Price_Change_Pct)^(YEAR($A18)-2028),0)+IF(OR($A18=DATE(2029,11,1),$A18=DATE(2030,11,1)),(RSU_Grant_Nov2028_USD/3)/FX_USD_per_GBP*(1+RSU_Price_Change_Pct)^(YEAR($A18)-2029),0)+IF($A18=DATE(2030,11,1),(RSU_Grant_Nov2029_USD/3)/FX_USD_per_GBP*(1+RSU_Price_Change_Pct)^(YEAR($A18)-2030),0) -> 0 | E18: =IF($A18=EDATE(DATE(2026,8,1),Inputs!$B$9),Inputs!$B$8,0) -> 0 | F18: =IF($A18=EDATE(DATE(2026,8,1),Inputs!$B$11),Inputs!$B$10,0) -> 0 | G18: =IF(Inputs!$B$16=1,((IF(YEAR($A18)=2026,Inputs!$B$2,IF(YEAR($A18)=2027,IF(MONTH($A18)>=Inputs!#REF!,Inputs!$B$2*(1+Inputs!$B$4),Inputs!$B$2),IF(YEAR($A18)=2028,IF(MONTH($A18)>=Inputs!#REF!,Inputs!$B$2*(1+Inputs!$B$4)*(1+Inputs!$B$5),Inputs!$B$2*(1+Inputs!$B$4)),IF(YEAR($A18)=2029,IF(MONTH($A18)>=Inputs!#REF!,Inputs!$B$2*(1+Inputs!$B$4)*(1+Inputs!$B$5)*(1+Inputs!$B$6),Inputs!$B$2*(1+Inputs!$B$4)*(1+Inputs!$B$5)),IF(MONTH($A18)>=Inputs!#REF!,Inputs!$B$2*(1+Inputs!$B$4)*(1+Inputs!$B$5)*(1+Inputs!$B$6)*(1+Inputs!$B$7),Inputs!$B$2*(1+Inputs!$B$4)*(1+Inputs!$B$5)*(1+Inputs!$B$6)))))))/12)*(MIN(Inputs!$B$17,Inputs!$B$18)*(1+Inputs!$B$19)+Inputs!$B$17*Inputs!$B$20),0) -> 0 | H18: =SUM(B18:G18) -> 4291.6667 | I18: =$H18-J18-K18 -> 3369 | J18: =_xlfn.SINGLE(_xlfn.LET(_xlpm.d, $A18, _xlpm.ys, YEAR(_xlfn.SINGLE(_xlpm.d)) - IF(MONTH(_xlfn.SINGLE(_xlpm.d)) < UK_TaxYear_Start_Month, 1, 0), _xlpm.start, DATE(_xlfn.SINGLE(_xlpm.ys), UK_TaxYear_Start_Month, 1), _xlpm.m, DATEDIF(_xlfn.SINGLE(_xlpm.start), _xlfn.SINGLE(_xlpm.d), "m") + 1, _xlpm.cum, SUMIFS($H$2:$H$54, $A$2:$A$54, ">=" & _xlfn.SINGLE(_xlpm.start), $A$2:$A$54, "<=" & _xlfn.SINGLE(_xlpm.d)), _xlpm.pa, UK_Personal_Allowance_Annual / 12 * _xlfn.SINGLE(_xlpm.m), _xlpm.br, (UK_Basic_Band_Upper_Annual - UK_Personal_Allowance_Annual) / 12 * _xlfn.SINGLE(_xlpm.m), _xlpm.hr, (UK_Higher_Band_Upper_Annual - UK_Basic_Band_Upper_Annual) / 12 * _xlfn.SINGLE(_xlpm.m), _xlpm.taxable, MAX(0, _xlfn.SINGLE(_xlpm.cum) - _xlfn.SINGLE(_xlpm.pa)), _xlpm.tax_to_date, UK_Basic_Rate * MIN(_xlpm.taxable, _xlpm.br) + UK_Higher_Rate * MIN(MAX(_xlfn.SINGLE(_xlpm.taxable) - _xlfn.SINGLE(_xlpm.br), 0), _xlpm.hr) + UK_Additional_Rate * MAX(_xlfn.SINGLE(_xlpm.taxable) - _xlfn.SINGLE(_xlpm.br) - _xlfn.SINGLE(_xlpm.hr), 0), _xlpm.prior, SUMIFS($J$2:$J$54, $A$2:$A$54, ">=" & _xlfn.SINGLE(_xlpm.start), $A$2:$A$54, "<" & _xlfn.SINGLE(_xlpm.d)), MAX(0, _xlfn.SINGLE(_xlpm.tax_to_date) - _xlfn.SINGLE(_xlpm.prior)))) -> 669.33333 | K18: =_xlfn.SINGLE(_xlfn.LET(_xlpm.g, $H18, _xlpm.pt, UK_NI_PT_Monthly, _xlpm.uel, UK_NI_UEL_Monthly, IF(_xlfn.SINGLE(_xlpm.g) <= _xlfn.SINGLE(_xlpm.pt), 0, UK_NI_Main_Rate * MIN(_xlfn.SINGLE(_xlpm.g) - _xlfn.SINGLE(_xlpm.pt), _xlfn.SINGLE(_xlpm.uel) - _xlfn.SINGLE(_xlpm.pt)) + UK_NI_Upper_Rate * MAX(_xlfn.SINGLE(_xlpm.g) - _xlfn.SINGLE(_xlpm.uel), 0)))) -> 253.33333 | L18: =IF($A18<DATE(2026,10,1),Bonus_Pct_Aug2026_to_Sep2026,IF($A18<DATE(2027,10,1),Bonus_Pct_Oct2026_to_Sep2027,IF($A18<DATE(2028,10,1),Bonus_Pct_Oct2027_to_Sep2028,IF($A18<DATE(2029,10,1),Bonus_Pct_Oct2028_to_Sep2029,Bonus_Pct_Oct2029_onwards)))) -> 0.08 | M18: Total Take-Home Estimate in All Years | N18: =SUM(N12:N16) -> 108274.33
A19: 46753 | B19: =(IF(YEAR($A19)=2026,Base_Annual_Salary_GBP,IF(YEAR($A19)=2027,Base_Annual_Salary_GBP*(IF(MONTH($A19)>=4,(1+Raise_Pct_Apr2027),1)*IF(MONTH($A19)>=10,(1+Raise_Pct_Nov2027),1)),IF(YEAR($A19)=2028,Base_Annual_Salary_GBP*((1+Raise_Pct_Apr2027)*(1+Raise_Pct_Nov2027))*(IF(MONTH($A19)>=4,(1+Raise_Pct_Apr2028),1)*IF(MONTH($A19)>=10,(1+Raise_Pct_Nov2028),1)),IF(YEAR($A19)=2029,Base_Annual_Salary_GBP*((1+Raise_Pct_Apr2027)*(1+Raise_Pct_Nov2027)*(1+Raise_Pct_Apr2028)*(1+Raise_Pct_Nov2028))*(IF(MONTH($A19)>=4,(1+Raise_Pct_Apr2029),1)*IF(MONTH($A19)>=10,(1+Raise_Pct_Nov2029),1)),Base_Annual_Salary_GBP*((1+Raise_Pct_Apr2027)*(1+Raise_Pct_Nov2027)*(1+Raise_Pct_Apr2028)*(1+Raise_Pct_Nov2028)*(1+Raise_Pct_Apr2029)*(1+Raise_Pct_Nov2029))*(IF(MONTH($A19)>=4,(1+Raise_Pct_Apr2030),1)*IF(MONTH($A19)>=10,(1+Raise_Pct_Nov2030),1)))))))/12 -> 4291.6667 | C19: =IF(MONTH($A19)=11,((IF(DATE(YEAR($A19),4,1)<DATE(2026,10,1),Bonus_Pct_Aug2026_to_Sep2026,IF(DATE(YEAR($A19),4,1)<DATE(2027,10,1),Bonus_Pct_Oct2026_to_Sep2027,IF(DATE(YEAR($A19),4,1)<DATE(2028,10,1),Bonus_Pct_Oct2027_to_Sep2028,IF(DATE(YEAR($A19),4,1)<DATE(2029,10,1),Bonus_Pct_Oct2028_to_Sep2029,Bonus_Pct_Oct2029_onwards)))))/2)*($B19*12) / (1 + IF(YEAR($A19)=2027,Raise_Pct_Nov2027,IF(YEAR($A19)=2028,Raise_Pct_Nov2028,IF(YEAR($A19)=2029,Raise_Pct_Nov2029,IF(YEAR($A19)=2030,Raise_Pct_Nov2030,0))))) * IF(YEAR($A19)=2026,2/6,1),IF(MONTH($A19)=5,((IF(DATE(YEAR($A19)-1,10,1)<DATE(2026,10,1),Bonus_Pct_Aug2026_to_Sep2026,IF(DATE(YEAR($A19)-1,10,1)<DATE(2027,10,1),Bonus_Pct_Oct2026_to_Sep2027,IF(DATE(YEAR($A19)-1,10,1)<DATE(2028,10,1),Bonus_Pct_Oct2027_to_Sep2028,IF(DATE(YEAR($A19)-1,10,1)<DATE(2029,10,1),Bonus_Pct_Oct2028_to_Sep2029,Bonus_Pct_Oct2029_onwards)))))/2)*($B19*12) / (1 + IF(YEAR($A19)=2027,Raise_Pct_Apr2027,IF(YEAR($A19)=2028,Raise_Pct_Apr2028,IF(YEAR($A19)=2029,Raise_Pct_Apr2029,IF(YEAR($A19)=2030,Raise_Pct_Apr2030,0))))),0)) -> 0 | D19: =IF(OR($A19=DATE(2027,9,1),$A19=EDATE(DATE(2027,9,1),12),$A19=EDATE(DATE(2027,9,1),24)),(New_Hire_Stock_Grant_USD/3)/FX_USD_per_GBP*(1+IF(YEAR($A19)=2027,Inputs!$B$56,IF(YEAR($A19)=2028,Inputs!$B$57,IF(YEAR($A19)=2029,Inputs!$B$58,0)))),0)+IF(OR($A19=DATE(2028,11,1),$A19=DATE(2029,11,1),$A19=DATE(2030,11,1)),(RSU_Grant_Nov2027_USD/3)/FX_USD_per_GBP*(1+RSU_Price_Change_Pct)^(YEAR($A19)-2028),0)+IF(OR($A19=DATE(2029,11,1),$A19=DATE(2030,11,1)),(RSU_Grant_Nov2028_USD/3)/FX_USD_per_GBP*(1+RSU_Price_Change_Pct)^(YEAR($A19)-2029),0)+IF($A19=DATE(2030,11,1),(RSU_Grant_Nov2029_USD/3)/FX_USD_per_GBP*(1+RSU_Price_Change_Pct)^(YEAR($A19)-2030),0) -> 0 | E19: =IF($A19=EDATE(DATE(2026,8,1),Inputs!$B$9),Inputs!$B$8,0) -> 0 | F19: =IF($A19=EDATE(DATE(2026,8,1),Inputs!$B$11),Inputs!$B$10,0) -> 0 | G19: =IF(Inputs!$B$16=1,((IF(YEAR($A19)=2026,Inputs!$B$2,IF(YEAR($A19)=2027,IF(MONTH($A19)>=Inputs!#REF!,Inputs!$B$2*(1+Inputs!$B$4),Inputs!$B$2),IF(YEAR($A19)=2028,IF(MONTH($A19)>=Inputs!#REF!,Inputs!$B$2*(1+Inputs!$B$4)*(1+Inputs!$B$5),Inputs!$B$2*(1+Inputs!$B$4)),IF(YEAR($A19)=2029,IF(MONTH($A19)>=Inputs!#REF!,Inputs!$B$2*(1+Inputs!$B$4)*(1+Inputs!$B$5)*(1+Inputs!$B$6),Inputs!$B$2*(1+Inputs!$B$4)*(1+Inputs!$B$5)),IF(MONTH($A19)>=Inputs!#REF!,Inputs!$B$2*(1+Inputs!$B$4)*(1+Inputs!$B$5)*(1+Inputs!$B$6)*(1+Inputs!$B$7),Inputs!$B$2*(1+Inputs!$B$4)*(1+Inputs!$B$5)*(1+Inputs!$B$6)))))))/12)*(MIN(Inputs!$B$17,Inputs!$B$18)*(1+Inputs!$B$19)+Inputs!$B$17*Inputs!$B$20),0) -> 0 | H19: =SUM(B19:G19) -> 4291.6667 | I19: =$H19-J19-K19 -> 3369 | J19: =_xlfn.SINGLE(_xlfn.LET(_xlpm.d, $A19, _xlpm.ys, YEAR(_xlfn.SINGLE(_xlpm.d)) - IF(MONTH(_xlfn.SINGLE(_xlpm.d)) < UK_TaxYear_Start_Month, 1, 0), _xlpm.start, DATE(_xlfn.SINGLE(_xlpm.ys), UK_TaxYear_Start_Month, 1), _xlpm.m, DATEDIF(_xlfn.SINGLE(_xlpm.start), _xlfn.SINGLE(_xlpm.d), "m") + 1, _xlpm.cum, SUMIFS($H$2:$H$54, $A$2:$A$54, ">=" & _xlfn.SINGLE(_xlpm.start), $A$2:$A$54, "<=" & _xlfn.SINGLE(_xlpm.d)), _xlpm.pa, UK_Personal_Allowance_Annual / 12 * _xlfn.SINGLE(_xlpm.m), _xlpm.br, (UK_Basic_Band_Upper_Annual - UK_Personal_Allowance_Annual) / 12 * _xlfn.SINGLE(_xlpm.m), _xlpm.hr, (UK_Higher_Band_Upper_Annual - UK_Basic_Band_Upper_Annual) / 12 * _xlfn.SINGLE(_xlpm.m), _xlpm.taxable, MAX(0, _xlfn.SINGLE(_xlpm.cum) - _xlfn.SINGLE(_xlpm.pa)), _xlpm.tax_to_date, UK_Basic_Rate * MIN(_xlpm.taxable, _xlpm.br) + UK_Higher_Rate * MIN(MAX(_xlfn.SINGLE(_xlpm.taxable) - _xlfn.SINGLE(_xlpm.br), 0), _xlpm.hr) + UK_Additional_Rate * MAX(_xlfn.SINGLE(_xlpm.taxable) - _xlfn.SINGLE(_xlpm.br) - _xlfn.SINGLE(_xlpm.hr), 0), _xlpm.prior, SUMIFS($J$2:$J$54, $A$2:$A$54, ">=" & _xlfn.SINGLE(_xlpm.start), $A$2:$A$54, "<" & _xlfn.SINGLE(_xlpm.d)), MAX(0, _xlfn.SINGLE(_xlpm.tax_to_date) - _xlfn.SINGLE(_xlpm.prior)))) -> 669.33333 | K19: =_xlfn.SINGLE(_xlfn.LET(_xlpm.g, $H19, _xlpm.pt, UK_NI_PT_Monthly, _xlpm.uel, UK_NI_UEL_Monthly, IF(_xlfn.SINGLE(_xlpm.g) <= _xlfn.SINGLE(_xlpm.pt), 0, UK_NI_Main_Rate * MIN(_xlfn.SINGLE(_xlpm.g) - _xlfn.SINGLE(_xlpm.pt), _xlfn.SINGLE(_xlpm.uel) - _xlfn.SINGLE(_xlpm.pt)) + UK_NI_Upper_Rate * MAX(_xlfn.SINGLE(_xlpm.g) - _xlfn.SINGLE(_xlpm.uel), 0)))) -> 253.33333 | L19: =IF($A19<DATE(2026,10,1),Bonus_Pct_Aug2026_to_Sep2026,IF($A19<DATE(2027,10,1),Bonus_Pct_Oct2026_to_Sep2027,IF($A19<DATE(2028,10,1),Bonus_Pct_Oct2027_to_Sep2028,IF($A19<DATE(2029,10,1),Bonus_Pct_Oct2028_to_Sep2029,Bonus_Pct_Oct2029_onwards)))) -> 0.08
A20: 46784 | B20: =(IF(YEAR($A20)=2026,Base_Annual_Salary_GBP,IF(YEAR($A20)=2027,Base_Annual_Salary_GBP*(IF(MONTH($A20)>=4,(1+Raise_Pct_Apr2027),1)*IF(MONTH($A20)>=10,(1+Raise_Pct_Nov2027),1)),IF(YEAR($A20)=2028,Base_Annual_Salary_GBP*((1+Raise_Pct_Apr2027)*(1+Raise_Pct_Nov2027))*(IF(MONTH($A20)>=4,(1+Raise_Pct_Apr2028),1)*IF(MONTH($A20)>=10,(1+Raise_Pct_Nov2028),1)),IF(YEAR($A20)=2029,Base_Annual_Salary_GBP*((1+Raise_Pct_Apr2027)*(1+Raise_Pct_Nov2027)*(1+Raise_Pct_Apr2028)*(1+Raise_Pct_Nov2028))*(IF(MONTH($A20)>=4,(1+Raise_Pct_Apr2029),1)*IF(MONTH($A20)>=10,(1+Raise_Pct_Nov2029),1)),Base_Annual_Salary_GBP*((1+Raise_Pct_Apr2027)*(1+Raise_Pct_Nov2027)*(1+Raise_Pct_Apr2028)*(1+Raise_Pct_Nov2028)*(1+Raise_Pct_Apr2029)*(1+Raise_Pct_Nov2029))*(IF(MONTH($A20)>=4,(1+Raise_Pct_Apr2030),1)*IF(MONTH($A20)>=10,(1+Raise_Pct_Nov2030),1)))))))/12 -> 4291.6667 | C20: =IF(MONTH($A20)=11,((IF(DATE(YEAR($A20),4,1)<DATE(2026,10,1),Bonus_Pct_Aug2026_to_Sep2026,IF(DATE(YEAR($A20),4,1)<DATE(2027,10,1),Bonus_Pct_Oct2026_to_Sep2027,IF(DATE(YEAR($A20),4,1)<DATE(2028,10,1),Bonus_Pct_Oct2027_to_Sep2028,IF(DATE(YEAR($A20),4,1)<DATE(2029,10,1),Bonus_Pct_Oct2028_to_Sep2029,Bonus_Pct_Oct2029_onwards)))))/2)*($B20*12) / (1 + IF(YEAR($A20)=2027,Raise_Pct_Nov2027,IF(YEAR($A20)=2028,Raise_Pct_Nov2028,IF(YEAR($A20)=2029,Raise_Pct_Nov2029,IF(YEAR($A20)=2030,Raise_Pct_Nov2030,0))))) * IF(YEAR($A20)=2026,2/6,1),IF(MONTH($A20)=5,((IF(DATE(YEAR($A20)-1,10,1)<DATE(2026,10,1),Bonus_Pct_Aug2026_to_Sep2026,IF(DATE(YEAR($A20)-1,10,1)<DATE(2027,10,1),Bonus_Pct_Oct2026_to_Sep2027,IF(DATE(YEAR($A20)-1,10,1)<DATE(2028,10,1),Bonus_Pct_Oct2027_to_Sep2028,IF(DATE(YEAR($A20)-1,10,1)<DATE(2029,10,1),Bonus_Pct_Oct2028_to_Sep2029,Bonus_Pct_Oct2029_onwards)))))/2)*($B20*12) / (1 + IF(YEAR($A20)=2027,Raise_Pct_Apr2027,IF(YEAR($A20)=2028,Raise_Pct_Apr2028,IF(YEAR($A20)=2029,Raise_Pct_Apr2029,IF(YEAR($A20)=2030,Raise_Pct_Apr2030,0))))),0)) -> 0 | D20: =IF(OR($A20=DATE(2027,9,1),$A20=EDATE(DATE(2027,9,1),12),$A20=EDATE(DATE(2027,9,1),24)),(New_Hire_Stock_Grant_USD/3)/FX_USD_per_GBP*(1+IF(YEAR($A20)=2027,Inputs!$B$56,IF(YEAR($A20)=2028,Inputs!$B$57,IF(YEAR($A20)=2029,Inputs!$B$58,0)))),0)+IF(OR($A20=DATE(2028,11,1),$A20=DATE(2029,11,1),$A20=DATE(2030,11,1)),(RSU_Grant_Nov2027_USD/3)/FX_USD_per_GBP*(1+RSU_Price_Change_Pct)^(YEAR($A20)-2028),0)+IF(OR($A20=DATE(2029,11,1),$A20=DATE(2030,11,1)),(RSU_Grant_Nov2028_USD/3)/FX_USD_per_GBP*(1+RSU_Price_Change_Pct)^(YEAR($A20)-2029),0)+IF($A20=DATE(2030,11,1),(RSU_Grant_Nov2029_USD/3)/FX_USD_per_GBP*(1+RSU_Price_Change_Pct)^(YEAR($A20)-2030),0) -> 0 | E20: =IF($A20=EDATE(DATE(2026,8,1),Inputs!$B$9),Inputs!$B$8,0) -> 0 | F20: =IF($A20=EDATE(DATE(2026,8,1),Inputs!$B$11),Inputs!$B$10,0) -> 0 | G20: =IF(Inputs!$B$16=1,((IF(YEAR($A20)=2026,Inputs!$B$2,IF(YEAR($A20)=2027,IF(MONTH($A20)>=Inputs!#REF!,Inputs!$B$2*(1+Inputs!$B$4),Inputs!$B$2),IF(YEAR($A20)=2028,IF(MONTH($A20)>=Inputs!#REF!,Inputs!$B$2*(1+Inputs!$B$4)*(1+Inputs!$B$5),Inputs!$B$2*(1+Inputs!$B$4)),IF(YEAR($A20)=2029,IF(MONTH($A20)>=Inputs!#REF!,Inputs!$B$2*(1+Inputs!$B$4)*(1+Inputs!$B$5)*(1+Inputs!$B$6),Inputs!$B$2*(1+Inputs!$B$4)*(1+Inputs!$B$5)),IF(MONTH($A20)>=Inputs!#REF!,Inputs!$B$2*(1+Inputs!$B$4)*(1+Inputs!$B$5)*(1+Inputs!$B$6)*(1+Inputs!$B$7),Inputs!$B$2*(1+Inputs!$B$4)*(1+Inputs!$B$5)*(1+Inputs!$B$6)))))))/12)*(MIN(Inputs!$B$17,Inputs!$B$18)*(1+Inputs!$B$19)+Inputs!$B$17*Inputs!$B$20),0) -> 0 | H20: =SUM(B20:G20) -> 4291.6667 | I20: =$H20-J20-K20 -> 3369 | J20: =_xlfn.SINGLE(_xlfn.LET(_xlpm.d, $A20, _xlpm.ys, YEAR(_xlfn.SINGLE(_xlpm.d)) - IF(MONTH(_xlfn.SINGLE(_xlpm.d)) < UK_TaxYear_Start_Month, 1, 0), _xlpm.start, DATE(_xlfn.SINGLE(_xlpm.ys), UK_TaxYear_Start_Month, 1), _xlpm.m, DATEDIF(_xlfn.SINGLE(_xlpm.start), _xlfn.SINGLE(_xlpm.d), "m") + 1, _xlpm.cum, SUMIFS($H$2:$H$54, $A$2:$A$54, ">=" & _xlfn.SINGLE(_xlpm.start), $A$2:$A$54, "<=" & _xlfn.SINGLE(_xlpm.d)), _xlpm.pa, UK_Personal_Allowance_Annual / 12 * _xlfn.SINGLE(_xlpm.m), _xlpm.br, (UK_Basic_Band_Upper_Annual - UK_Personal_Allowance_Annual) / 12 * _xlfn.SINGLE(_xlpm.m), _xlpm.hr, (UK_Higher_Band_Upper_Annual - UK_Basic_Band_Upper_Annual) / 12 * _xlfn.SINGLE(_xlpm.m), _xlpm.taxable, MAX(0, _xlfn.SINGLE(_xlpm.cum) - _xlfn.SINGLE(_xlpm.pa)), _xlpm.tax_to_date, UK_Basic_Rate * MIN(_xlpm.taxable, _xlpm.br) + UK_Higher_Rate * MIN(MAX(_xlfn.SINGLE(_xlpm.taxable) - _xlfn.SINGLE(_xlpm.br), 0), _xlpm.hr) + UK_Additional_Rate * MAX(_xlfn.SINGLE(_xlpm.taxable) - _xlfn.SINGLE(_xlpm.br) - _xlfn.SINGLE(_xlpm.hr), 0), _xlpm.prior, SUMIFS($J$2:$J$54, $A$2:$A$54, ">=" & _xlfn.SINGLE(_xlpm.start), $A$2:$A$54, "<" & _xlfn.SINGLE(_xlpm.d)), MAX(0, _xlfn.SINGLE(_xlpm.tax_to_date) - _xlfn.SINGLE(_xlpm.prior)))) -> 669.33333 | K20: =_xlfn.SINGLE(_xlfn.LET(_xlpm.g, $H20, _xlpm.pt, UK_NI_PT_Monthly, _xlpm.uel, UK_NI_UEL_Monthly, IF(_xlfn.SINGLE(_xlpm.g) <= _xlfn.SINGLE(_xlpm.pt), 0, UK_NI_Main_Rate * MIN(_xlfn.SINGLE(_xlpm.g) - _xlfn.SINGLE(_xlpm.pt), _xlfn.SINGLE(_xlpm.uel) - _xlfn.SINGLE(_xlpm.pt)) + UK_NI_Upper_Rate * MAX(_xlfn.SINGLE(_xlpm.g) - _xlfn.SINGLE(_xlpm.uel), 0)))) -> 253.33333 | L20: =IF($A20<DATE(2026,10,1),Bonus_Pct_Aug2026_to_Sep2026,IF($A20<DATE(2027,10,1),Bonus_Pct_Oct2026_to_Sep2027,IF($A20<DATE(2028,10,1),Bonus_Pct_Oct2027_to_Sep2028,IF($A20<DATE(2029,10,1),Bonus_Pct_Oct2028_to_Sep2029,Bonus_Pct_Oct2029_onwards)))) -> 0.08
A21: 46813 | B21: =(IF(YEAR($A21)=2026,Base_Annual_Salary_GBP,IF(YEAR($A21)=2027,Base_Annual_Salary_GBP*(IF(MONTH($A21)>=4,(1+Raise_Pct_Apr2027),1)*IF(MONTH($A21)>=10,(1+Raise_Pct_Nov2027),1)),IF(YEAR($A21)=2028,Base_Annual_Salary_GBP*((1+Raise_Pct_Apr2027)*(1+Raise_Pct_Nov2027))*(IF(MONTH($A21)>=4,(1+Raise_Pct_Apr2028),1)*IF(MONTH($A21)>=10,(1+Raise_Pct_Nov2028),1)),IF(YEAR($A21)=2029,Base_Annual_Salary_GBP*((1+Raise_Pct_Apr2027)*(1+Raise_Pct_Nov2027)*(1+Raise_Pct_Apr2028)*(1+Raise_Pct_Nov2028))*(IF(MONTH($A21)>=4,(1+Raise_Pct_Apr2029),1)*IF(MONTH($A21)>=10,(1+Raise_Pct_Nov2029),1)),Base_Annual_Salary_GBP*((1+Raise_Pct_Apr2027)*(1+Raise_Pct_Nov2027)*(1+Raise_Pct_Apr2028)*(1+Raise_Pct_Nov2028)*(1+Raise_Pct_Apr2029)*(1+Raise_Pct_Nov2029))*(IF(MONTH($A21)>=4,(1+Raise_Pct_Apr2030),1)*IF(MONTH($A21)>=10,(1+Raise_Pct_Nov2030),1)))))))/12 -> 4291.6667 | C21: =IF(MONTH($A21)=11,((IF(DATE(YEAR($A21),4,1)<DATE(2026,10,1),Bonus_Pct_Aug2026_to_Sep2026,IF(DATE(YEAR($A21),4,1)<DATE(2027,10,1),Bonus_Pct_Oct2026_to_Sep2027,IF(DATE(YEAR($A21),4,1)<DATE(2028,10,1),Bonus_Pct_Oct2027_to_Sep2028,IF(DATE(YEAR($A21),4,1)<DATE(2029,10,1),Bonus_Pct_Oct2028_to_Sep2029,Bonus_Pct_Oct2029_onwards)))))/2)*($B21*12) / (1 + IF(YEAR($A21)=2027,Raise_Pct_Nov2027,IF(YEAR($A21)=2028,Raise_Pct_Nov2028,IF(YEAR($A21)=2029,Raise_Pct_Nov2029,IF(YEAR($A21)=2030,Raise_Pct_Nov2030,0))))) * IF(YEAR($A21)=2026,2/6,1),IF(MONTH($A21)=5,((IF(DATE(YEAR($A21)-1,10,1)<DATE(2026,10,1),Bonus_Pct_Aug2026_to_Sep2026,IF(DATE(YEAR($A21)-1,10,1)<DATE(2027,10,1),Bonus_Pct_Oct2026_to_Sep2027,IF(DATE(YEAR($A21)-1,10,1)<DATE(2028,10,1),Bonus_Pct_Oct2027_to_Sep2028,IF(DATE(YEAR($A21)-1,10,1)<DATE(2029,10,1),Bonus_Pct_Oct2028_to_Sep2029,Bonus_Pct_Oct2029_onwards)))))/2)*($B21*12) / (1 + IF(YEAR($A21)=2027,Raise_Pct_Apr2027,IF(YEAR($A21)=2028,Raise_Pct_Apr2028,IF(YEAR($A21)=2029,Raise_Pct_Apr2029,IF(YEAR($A21)=2030,Raise_Pct_Apr2030,0))))),0)) -> 0 | D21: =IF(OR($A21=DATE(2027,9,1),$A21=EDATE(DATE(2027,9,1),12),$A21=EDATE(DATE(2027,9,1),24)),(New_Hire_Stock_Grant_USD/3)/FX_USD_per_GBP*(1+IF(YEAR($A21)=2027,Inputs!$B$56,IF(YEAR($A21)=2028,Inputs!$B$57,IF(YEAR($A21)=2029,Inputs!$B$58,0)))),0)+IF(OR($A21=DATE(2028,11,1),$A21=DATE(2029,11,1),$A21=DATE(2030,11,1)),(RSU_Grant_Nov2027_USD/3)/FX_USD_per_GBP*(1+RSU_Price_Change_Pct)^(YEAR($A21)-2028),0)+IF(OR($A21=DATE(2029,11,1),$A21=DATE(2030,11,1)),(RSU_Grant_Nov2028_USD/3)/FX_USD_per_GBP*(1+RSU_Price_Change_Pct)^(YEAR($A21)-2029),0)+IF($A21=DATE(2030,11,1),(RSU_Grant_Nov2029_USD/3)/FX_USD_per_GBP*(1+RSU_Price_Change_Pct)^(YEAR($A21)-2030),0) -> 0 | E21: =IF($A21=EDATE(DATE(2026,8,1),Inputs!$B$9),Inputs!$B$8,0) -> 0 | F21: =IF($A21=EDATE(DATE(2026,8,1),Inputs!$B$11),Inputs!$B$10,0) -> 0 | G21: =IF(Inputs!$B$16=1,((IF(YEAR($A21)=2026,Inputs!$B$2,IF(YEAR($A21)=2027,IF(MONTH($A21)>=Inputs!#REF!,Inputs!$B$2*(1+Inputs!$B$4),Inputs!$B$2),IF(YEAR($A21)=2028,IF(MONTH($A21)>=Inputs!#REF!,Inputs!$B$2*(1+Inputs!$B$4)*(1+Inputs!$B$5),Inputs!$B$2*(1+Inputs!$B$4)),IF(YEAR($A21)=2029,IF(MONTH($A21)>=Inputs!#REF!,Inputs!$B$2*(1+Inputs!$B$4)*(1+Inputs!$B$5)*(1+Inputs!$B$6),Inputs!$B$2*(1+Inputs!$B$4)*(1+Inputs!$B$5)),IF(MONTH($A21)>=Inputs!#REF!,Inputs!$B$2*(1+Inputs!$B$4)*(1+Inputs!$B$5)*(1+Inputs!$B$6)*(1+Inputs!$B$7),Inputs!$B$2*(1+Inputs!$B$4)*(1+Inputs!$B$5)*(1+Inputs!$B$6)))))))/12)*(MIN(Inputs!$B$17,Inputs!$B$18)*(1+Inputs!$B$19)+Inputs!$B$17*Inputs!$B$20),0) -> 0 | H21: =SUM(B21:G21) -> 4291.6667 | I21: =$H21-J21-K21 -> 3369 | J21: =_xlfn.SINGLE(_xlfn.LET(_xlpm.d, $A21, _xlpm.ys, YEAR(_xlfn.SINGLE(_xlpm.d)) - IF(MONTH(_xlfn.SINGLE(_xlpm.d)) < UK_TaxYear_Start_Month, 1, 0), _xlpm.start, DATE(_xlfn.SINGLE(_xlpm.ys), UK_TaxYear_Start_Month, 1), _xlpm.m, DATEDIF(_xlfn.SINGLE(_xlpm.start), _xlfn.SINGLE(_xlpm.d), "m") + 1, _xlpm.cum, SUMIFS($H$2:$H$54, $A$2:$A$54, ">=" & _xlfn.SINGLE(_xlpm.start), $A$2:$A$54, "<=" & _xlfn.SINGLE(_xlpm.d)), _xlpm.pa, UK_Personal_Allowance_Annual / 12 * _xlfn.SINGLE(_xlpm.m), _xlpm.br, (UK_Basic_Band_Upper_Annual - UK_Personal_Allowance_Annual) / 12 * _xlfn.SINGLE(_xlpm.m), _xlpm.hr, (UK_Higher_Band_Upper_Annual - UK_Basic_Band_Upper_Annual) / 12 * _xlfn.SINGLE(_xlpm.m), _xlpm.taxable, MAX(0, _xlfn.SINGLE(_xlpm.cum) - _xlfn.SINGLE(_xlpm.pa)), _xlpm.tax_to_date, UK_Basic_Rate * MIN(_xlpm.taxable, _xlpm.br) + UK_Higher_Rate * MIN(MAX(_xlfn.SINGLE(_xlpm.taxable) - _xlfn.SINGLE(_xlpm.br), 0), _xlpm.hr) + UK_Additional_Rate * MAX(_xlfn.SINGLE(_xlpm.taxable) - _xlfn.SINGLE(_xlpm.br) - _xlfn.SINGLE(_xlpm.hr), 0), _xlpm.prior, SUMIFS($J$2:$J$54, $A$2:$A$54, ">=" & _xlfn.SINGLE(_xlpm.start), $A$2:$A$54, "<" & _xlfn.SINGLE(_xlpm.d)), MAX(0, _xlfn.SINGLE(_xlpm.tax_to_date) - _xlfn.SINGLE(_xlpm.prior)))) -> 669.33333 | K21: =_xlfn.SINGLE(_xlfn.LET(_xlpm.g, $H21, _xlpm.pt, UK_NI_PT_Monthly, _xlpm.uel, UK_NI_UEL_Monthly, IF(_xlfn.SINGLE(_xlpm.g) <= _xlfn.SINGLE(_xlpm.pt), 0, UK_NI_Main_Rate * MIN(_xlfn.SINGLE(_xlpm.g) - _xlfn.SINGLE(_xlpm.pt), _xlfn.SINGLE(_xlpm.uel) - _xlfn.SINGLE(_xlpm.pt)) + UK_NI_Upper_Rate * MAX(_xlfn.SINGLE(_xlpm.g) - _xlfn.SINGLE(_xlpm.uel), 0)))) -> 253.33333 | L21: =IF($A21<DATE(2026,10,1),Bonus_Pct_Aug2026_to_Sep2026,IF($A21<DATE(2027,10,1),Bonus_Pct_Oct2026_to_Sep2027,IF($A21<DATE(2028,10,1),Bonus_Pct_Oct2027_to_Sep2028,IF($A21<DATE(2029,10,1),Bonus_Pct_Oct2028_to_Sep2029,Bonus_Pct_Oct2029_onwards)))) -> 0.08
A22: 46844 | B22: =(IF(YEAR($A22)=2026,Base_Annual_Salary_GBP,IF(YEAR($A22)=2027,Base_Annual_Salary_GBP*(IF(MONTH($A22)>=4,(1+Raise_Pct_Apr2027),1)*IF(MONTH($A22)>=10,(1+Raise_Pct_Nov2027),1)),IF(YEAR($A22)=2028,Base_Annual_Salary_GBP*((1+Raise_Pct_Apr2027)*(1+Raise_Pct_Nov2027))*(IF(MONTH($A22)>=4,(1+Raise_Pct_Apr2028),1)*IF(MONTH($A22)>=10,(1+Raise_Pct_Nov2028),1)),IF(YEAR($A22)=2029,Base_Annual_Salary_GBP*((1+Raise_Pct_Apr2027)*(1+Raise_Pct_Nov2027)*(1+Raise_Pct_Apr2028)*(1+Raise_Pct_Nov2028))*(IF(MONTH($A22)>=4,(1+Raise_Pct_Apr2029),1)*IF(MONTH($A22)>=10,(1+Raise_Pct_Nov2029),1)),Base_Annual_Salary_GBP*((1+Raise_Pct_Apr2027)*(1+Raise_Pct_Nov2027)*(1+Raise_Pct_Apr2028)*(1+Raise_Pct_Nov2028)*(1+Raise_Pct_Apr2029)*(1+Raise_Pct_Nov2029))*(IF(MONTH($A22)>=4,(1+Raise_Pct_Apr2030),1)*IF(MONTH($A22)>=10,(1+Raise_Pct_Nov2030),1)))))))/12 -> 4420.4167 | C22: =IF(MONTH($A22)=11,((IF(DATE(YEAR($A22),4,1)<DATE(2026,10,1),Bonus_Pct_Aug2026_to_Sep2026,IF(DATE(YEAR($A22),4,1)<DATE(2027,10,1),Bonus_Pct_Oct2026_to_Sep2027,IF(DATE(YEAR($A22),4,1)<DATE(2028,10,1),Bonus_Pct_Oct2027_to_Sep2028,IF(DATE(YEAR($A22),4,1)<DATE(2029,10,1),Bonus_Pct_Oct2028_to_Sep2029,Bonus_Pct_Oct2029_onwards)))))/2)*($B22*12) / (1 + IF(YEAR($A22)=2027,Raise_Pct_Nov2027,IF(YEAR($A22)=2028,Raise_Pct_Nov2028,IF(YEAR($A22)=2029,Raise_Pct_Nov2029,IF(YEAR($A22)=2030,Raise_Pct_Nov2030,0))))) * IF(YEAR($A22)=2026,2/6,1),IF(MONTH($A22)=5,((IF(DATE(YEAR($A22)-1,10,1)<DATE(2026,10,1),Bonus_Pct_Aug2026_to_Sep2026,IF(DATE(YEAR($A22)-1,10,1)<DATE(2027,10,1),Bonus_Pct_Oct2026_to_Sep2027,IF(DATE(YEAR($A22)-1,10,1)<DATE(2028,10,1),Bonus_Pct_Oct2027_to_Sep2028,IF(DATE(YEAR($A22)-1,10,1)<DATE(2029,10,1),Bonus_Pct_Oct2028_to_Sep2029,Bonus_Pct_Oct2029_onwards)))))/2)*($B22*12) / (1 + IF(YEAR($A22)=2027,Raise_Pct_Apr2027,IF(YEAR($A22)=2028,Raise_Pct_Apr2028,IF(YEAR($A22)=2029,Raise_Pct_Apr2029,IF(YEAR($A22)=2030,Raise_Pct_Apr2030,0))))),0)) -> 0 | D22: =IF(OR($A22=DATE(2027,9,1),$A22=EDATE(DATE(2027,9,1),12),$A22=EDATE(DATE(2027,9,1),24)),(New_Hire_Stock_Grant_USD/3)/FX_USD_per_GBP*(1+IF(YEAR($A22)=2027,Inputs!$B$56,IF(YEAR($A22)=2028,Inputs!$B$57,IF(YEAR($A22)=2029,Inputs!$B$58,0)))),0)+IF(OR($A22=DATE(2028,11,1),$A22=DATE(2029,11,1),$A22=DATE(2030,11,1)),(RSU_Grant_Nov2027_USD/3)/FX_USD_per_GBP*(1+RSU_Price_Change_Pct)^(YEAR($A22)-2028),0)+IF(OR($A22=DATE(2029,11,1),$A22=DATE(2030,11,1)),(RSU_Grant_Nov2028_USD/3)/FX_USD_per_GBP*(1+RSU_Price_Change_Pct)^(YEAR($A22)-2029),0)+IF($A22=DATE(2030,11,1),(RSU_Grant_Nov2029_USD/3)/FX_USD_per_GBP*(1+RSU_Price_Change_Pct)^(YEAR($A22)-2030),0) -> 0 | E22: =IF($A22=EDATE(DATE(2026,8,1),Inputs!$B$9),Inputs!$B$8,0) -> 0 | F22: =IF($A22=EDATE(DATE(2026,8,1),Inputs!$B$11),Inputs!$B$10,0) -> 0 | G22: =IF(Inputs!$B$16=1,((IF(YEAR($A22)=2026,Inputs!$B$2,IF(YEAR($A22)=2027,IF(MONTH($A22)>=Inputs!#REF!,Inputs!$B$2*(1+Inputs!$B$4),Inputs!$B$2),IF(YEAR($A22)=2028,IF(MONTH($A22)>=Inputs!#REF!,Inputs!$B$2*(1+Inputs!$B$4)*(1+Inputs!$B$5),Inputs!$B$2*(1+Inputs!$B$4)),IF(YEAR($A22)=2029,IF(MONTH($A22)>=Inputs!#REF!,Inputs!$B$2*(1+Inputs!$B$4)*(1+Inputs!$B$5)*(1+Inputs!$B$6),Inputs!$B$2*(1+Inputs!$B$4)*(1+Inputs!$B$5)),IF(MONTH($A22)>=Inputs!#REF!,Inputs!$B$2*(1+Inputs!$B$4)*(1+Inputs!$B$5)*(1+Inputs!$B$6)*(1+Inputs!$B$7),Inputs!$B$2*(1+Inputs!$B$4)*(1+Inputs!$B$5)*(1+Inputs!$B$6)))))))/12)*(MIN(Inputs!$B$17,Inputs!$B$18)*(1+Inputs!$B$19)+Inputs!$B$17*Inputs!$B$20),0) -> 0 | H22: =SUM(B22:G22) -> 4420.4167 | I22: =$H22-J22-K22 -> 3443.675 | J22: =_xlfn.SINGLE(_xlfn.LET(_xlpm.d, $A22, _xlpm.ys, YEAR(_xlfn.SINGLE(_xlpm.d)) - IF(MONTH(_xlfn.SINGLE(_xlpm.d)) < UK_TaxYear_Start_Month, 1, 0), _xlpm.start, DATE(_xlfn.SINGLE(_xlpm.ys), UK_TaxYear_Start_Month, 1), _xlpm.m, DATEDIF(_xlfn.SINGLE(_xlpm.start), _xlfn.SINGLE(_xlpm.d), "m") + 1, _xlpm.cum, SUMIFS($H$2:$H$54, $A$2:$A$54, ">=" & _xlfn.SINGLE(_xlpm.start), $A$2:$A$54, "<=" & _xlfn.SINGLE(_xlpm.d)), _xlpm.pa, UK_Personal_Allowance_Annual / 12 * _xlfn.SINGLE(_xlpm.m), _xlpm.br, (UK_Basic_Band_Upper_Annual - UK_Personal_Allowance_Annual) / 12 * _xlfn.SINGLE(_xlpm.m), _xlpm.hr, (UK_Higher_Band_Upper_Annual - UK_Basic_Band_Upper_Annual) / 12 * _xlfn.SINGLE(_xlpm.m), _xlpm.taxable, MAX(0, _xlfn.SINGLE(_xlpm.cum) - _xlfn.SINGLE(_xlpm.pa)), _xlpm.tax_to_date, UK_Basic_Rate * MIN(_xlpm.taxable, _xlpm.br) + UK_Higher_Rate * MIN(MAX(_xlfn.SINGLE(_xlpm.taxable) - _xlfn.SINGLE(_xlpm.br), 0), _xlpm.hr) + UK_Additional_Rate * MAX(_xlfn.SINGLE(_xlpm.taxable) - _xlfn.SINGLE(_xlpm.br) - _xlfn.SINGLE(_xlpm.hr), 0), _xlpm.prior, SUMIFS($J$2:$J$54, $A$2:$A$54, ">=" & _xlfn.SINGLE(_xlpm.start), $A$2:$A$54, "<" & _xlfn.SINGLE(_xlpm.d)), MAX(0, _xlfn.SINGLE(_xlpm.tax_to_date) - _xlfn.SINGLE(_xlpm.prior)))) -> 720.83333 | K22: =_xlfn.SINGLE(_xlfn.LET(_xlpm.g, $H22, _xlpm.pt, UK_NI_PT_Monthly, _xlpm.uel, UK_NI_UEL_Monthly, IF(_xlfn.SINGLE(_xlpm.g) <= _xlfn.SINGLE(_xlpm.pt), 0, UK_NI_Main_Rate * MIN(_xlfn.SINGLE(_xlpm.g) - _xlfn.SINGLE(_xlpm.pt), _xlfn.SINGLE(_xlpm.uel) - _xlfn.SINGLE(_xlpm.pt)) + UK_NI_Upper_Rate * MAX(_xlfn.SINGLE(_xlpm.g) - _xlfn.SINGLE(_xlpm.uel), 0)))) -> 255.90833 | L22: =IF($A22<DATE(2026,10,1),Bonus_Pct_Aug2026_to_Sep2026,IF($A22<DATE(2027,10,1),Bonus_Pct_Oct2026_to_Sep2027,IF($A22<DATE(2028,10,1),Bonus_Pct_Oct2027_to_Sep2028,IF($A22<DATE(2029,10,1),Bonus_Pct_Oct2028_to_Sep2029,Bonus_Pct_Oct2029_onwards)))) -> 0.08
A23: 46874 | B23: =(IF(YEAR($A23)=2026,Base_Annual_Salary_GBP,IF(YEAR($A23)=2027,Base_Annual_Salary_GBP*(IF(MONTH($A23)>=4,(1+Raise_Pct_Apr2027),1)*IF(MONTH($A23)>=10,(1+Raise_Pct_Nov2027),1)),IF(YEAR($A23)=2028,Base_Annual_Salary_GBP*((1+Raise_Pct_Apr2027)*(1+Raise_Pct_Nov2027))*(IF(MONTH($A23)>=4,(1+Raise_Pct_Apr2028),1)*IF(MONTH($A23)>=10,(1+Raise_Pct_Nov2028),1)),IF(YEAR($A23)=2029,Base_Annual_Salary_GBP*((1+Raise_Pct_Apr2027)*(1+Raise_Pct_Nov2027)*(1+Raise_Pct_Apr2028)*(1+Raise_Pct_Nov2028))*(IF(MONTH($A23)>=4,(1+Raise_Pct_Apr2029),1)*IF(MONTH($A23)>=10,(1+Raise_Pct_Nov2029),1)),Base_Annual_Salary_GBP*((1+Raise_Pct_Apr2027)*(1+Raise_Pct_Nov2027)*(1+Raise_Pct_Apr2028)*(1+Raise_Pct_Nov2028)*(1+Raise_Pct_Apr2029)*(1+Raise_Pct_Nov2029))*(IF(MONTH($A23)>=4,(1+Raise_Pct_Apr2030),1)*IF(MONTH($A23)>=10,(1+Raise_Pct_Nov2030),1)))))))/12 -> 4420.4167 | C23: =IF(MONTH($A23)=11,((IF(DATE(YEAR($A23),4,1)<DATE(2026,10,1),Bonus_Pct_Aug2026_to_Sep2026,IF(DATE(YEAR($A23),4,1)<DATE(2027,10,1),Bonus_Pct_Oct2026_to_Sep2027,IF(DATE(YEAR($A23),4,1)<DATE(2028,10,1),Bonus_Pct_Oct2027_to_Sep2028,IF(DATE(YEAR($A23),4,1)<DATE(2029,10,1),Bonus_Pct_Oct2028_to_Sep2029,Bonus_Pct_Oct2029_onwards)))))/2)*($B23*12) / (1 + IF(YEAR($A23)=2027,Raise_Pct_Nov2027,IF(YEAR($A23)=2028,Raise_Pct_Nov2028,IF(YEAR($A23)=2029,Raise_Pct_Nov2029,IF(YEAR($A23)=2030,Raise_Pct_Nov2030,0))))) * IF(YEAR($A23)=2026,2/6,1),IF(MONTH($A23)=5,((IF(DATE(YEAR($A23)-1,10,1)<DATE(2026,10,1),Bonus_Pct_Aug2026_to_Sep2026,IF(DATE(YEAR($A23)-1,10,1)<DATE(2027,10,1),Bonus_Pct_Oct2026_to_Sep2027,IF(DATE(YEAR($A23)-1,10,1)<DATE(2028,10,1),Bonus_Pct_Oct2027_to_Sep2028,IF(DATE(YEAR($A23)-1,10,1)<DATE(2029,10,1),Bonus_Pct_Oct2028_to_Sep2029,Bonus_Pct_Oct2029_onwards)))))/2)*($B23*12) / (1 + IF(YEAR($A23)=2027,Raise_Pct_Apr2027,IF(YEAR($A23)=2028,Raise_Pct_Apr2028,IF(YEAR($A23)=2029,Raise_Pct_Apr2029,IF(YEAR($A23)=2030,Raise_Pct_Apr2030,0))))),0)) -> 2060 | D23: =IF(OR($A23=DATE(2027,9,1),$A23=EDATE(DATE(2027,9,1),12),$A23=EDATE(DATE(2027,9,1),24)),(New_Hire_Stock_Grant_USD/3)/FX_USD_per_GBP*(1+IF(YEAR($A23)=2027,Inputs!$B$56,IF(YEAR($A23)=2028,Inputs!$B$57,IF(YEAR($A23)=2029,Inputs!$B$58,0)))),0)+IF(OR($A23=DATE(2028,11,1),$A23=DATE(2029,11,1),$A23=DATE(2030,11,1)),(RSU_Grant_Nov2027_USD/3)/FX_USD_per_GBP*(1+RSU_Price_Change_Pct)^(YEAR($A23)-2028),0)+IF(OR($A23=DATE(2029,11,1),$A23=DATE(2030,11,1)),(RSU_Grant_Nov2028_USD/3)/FX_USD_per_GBP*(1+RSU_Price_Change_Pct)^(YEAR($A23)-2029),0)+IF($A23=DATE(2030,11,1),(RSU_Grant_Nov2029_USD/3)/FX_USD_per_GBP*(1+RSU_Price_Change_Pct)^(YEAR($A23)-2030),0) -> 0 | E23: =IF($A23=EDATE(DATE(2026,8,1),Inputs!$B$9),Inputs!$B$8,0) -> 0 | F23: =IF($A23=EDATE(DATE(2026,8,1),Inputs!$B$11),Inputs!$B$10,0) -> 0 | G23: =IF(Inputs!$B$16=1,((IF(YEAR($A23)=2026,Inputs!$B$2,IF(YEAR($A23)=2027,IF(MONTH($A23)>=Inputs!#REF!,Inputs!$B$2*(1+Inputs!$B$4),Inputs!$B$2),IF(YEAR($A23)=2028,IF(MONTH($A23)>=Inputs!#REF!,Inputs!$B$2*(1+Inputs!$B$4)*(1+Inputs!$B$5),Inputs!$B$2*(1+Inputs!$B$4)),IF(YEAR($A23)=2029,IF(MONTH($A23)>=Inputs!#REF!,Inputs!$B$2*(1+Inputs!$B$4)*(1+Inputs!$B$5)*(1+Inputs!$B$6),Inputs!$B$2*(1+Inputs!$B$4)*(1+Inputs!$B$5)),IF(MONTH($A23)>=Inputs!#REF!,Inputs!$B$2*(1+Inputs!$B$4)*(1+Inputs!$B$5)*(1+Inputs!$B$6)*(1+Inputs!$B$7),Inputs!$B$2*(1+Inputs!$B$4)*(1+Inputs!$B$5)*(1+Inputs!$B$6)))))))/12)*(MIN(Inputs!$B$17,Inputs!$B$18)*(1+Inputs!$B$19)+Inputs!$B$17*Inputs!$B$20),0) -> 0 | H23: =SUM(B23:G23) -> 6480.4167 | I23: =$H23-J23-K23 -> 4638.475 | J23: =_xlfn.SINGLE(_xlfn.LET(_xlpm.d, $A23, _xlpm.ys, YEAR(_xlfn.SINGLE(_xlpm.d)) - IF(MONTH(_xlfn.SINGLE(_xlpm.d)) < UK_TaxYear_Start_Month, 1, 0), _xlpm.start, DATE(_xlfn.SINGLE(_xlpm.ys), UK_TaxYear_Start_Month, 1), _xlpm.m, DATEDIF(_xlfn.SINGLE(_xlpm.start), _xlfn.SINGLE(_xlpm.d), "m") + 1, _xlpm.cum, SUMIFS($H$2:$H$54, $A$2:$A$54, ">=" & _xlfn.SINGLE(_xlpm.start), $A$2:$A$54, "<=" & _xlfn.SINGLE(_xlpm.d)), _xlpm.pa, UK_Personal_Allowance_Annual / 12 * _xlfn.SINGLE(_xlpm.m), _xlpm.br, (UK_Basic_Band_Upper_Annual - UK_Personal_Allowance_Annual) / 12 * _xlfn.SINGLE(_xlpm.m), _xlpm.hr, (UK_Higher_Band_Upper_Annual - UK_Basic_Band_Upper_Annual) / 12 * _xlfn.SINGLE(_xlpm.m), _xlpm.taxable, MAX(0, _xlfn.SINGLE(_xlpm.cum) - _xlfn.SINGLE(_xlpm.pa)), _xlpm.tax_to_date, UK_Basic_Rate * MIN(_xlpm.taxable, _xlpm.br) + UK_Higher_Rate * MIN(MAX(_xlfn.SINGLE(_xlpm.taxable) - _xlfn.SINGLE(_xlpm.br), 0), _xlpm.hr) + UK_Additional_Rate * MAX(_xlfn.SINGLE(_xlpm.taxable) - _xlfn.SINGLE(_xlpm.br) - _xlfn.SINGLE(_xlpm.hr), 0), _xlpm.prior, SUMIFS($J$2:$J$54, $A$2:$A$54, ">=" & _xlfn.SINGLE(_xlpm.start), $A$2:$A$54, "<" & _xlfn.SINGLE(_xlpm.d)), MAX(0, _xlfn.SINGLE(_xlpm.tax_to_date) - _xlfn.SINGLE(_xlpm.prior)))) -> 1544.8333 | K23: =_xlfn.SINGLE(_xlfn.LET(_xlpm.g, $H23, _xlpm.pt, UK_NI_PT_Monthly, _xlpm.uel, UK_NI_UEL_Monthly, IF(_xlfn.SINGLE(_xlpm.g) <= _xlfn.SINGLE(_xlpm.pt), 0, UK_NI_Main_Rate * MIN(_xlfn.SINGLE(_xlpm.g) - _xlfn.SINGLE(_xlpm.pt), _xlfn.SINGLE(_xlpm.uel) - _xlfn.SINGLE(_xlpm.pt)) + UK_NI_Upper_Rate * MAX(_xlfn.SINGLE(_xlpm.g) - _xlfn.SINGLE(_xlpm.uel), 0)))) -> 297.10833 | L23: =IF($A23<DATE(2026,10,1),Bonus_Pct_Aug2026_to_Sep2026,IF($A23<DATE(2027,10,1),Bonus_Pct_Oct2026_to_Sep2027,IF($A23<DATE(2028,10,1),Bonus_Pct_Oct2027_to_Sep2028,IF($A23<DATE(2029,10,1),Bonus_Pct_Oct2028_to_Sep2029,Bonus_Pct_Oct2029_onwards)))) -> 0.08 | M23: =3293.34-2400 -> 893.34
A24: 46905 | B24: =(IF(YEAR($A24)=2026,Base_Annual_Salary_GBP,IF(YEAR($A24)=2027,Base_Annual_Salary_GBP*(IF(MONTH($A24)>=4,(1+Raise_Pct_Apr2027),1)*IF(MONTH($A24)>=10,(1+Raise_Pct_Nov2027),1)),IF(YEAR($A24)=2028,Base_Annual_Salary_GBP*((1+Raise_Pct_Apr2027)*(1+Raise_Pct_Nov2027))*(IF(MONTH($A24)>=4,(1+Raise_Pct_Apr2028),1)*IF(MONTH($A24)>=10,(1+Raise_Pct_Nov2028),1)),IF(YEAR($A24)=2029,Base_Annual_Salary_GBP*((1+Raise_Pct_Apr2027)*(1+Raise_Pct_Nov2027)*(1+Raise_Pct_Apr2028)*(1+Raise_Pct_Nov2028))*(IF(MONTH($A24)>=4,(1+Raise_Pct_Apr2029),1)*IF(MONTH($A24)>=10,(1+Raise_Pct_Nov2029),1)),Base_Annual_Salary_GBP*((1+Raise_Pct_Apr2027)*(1+Raise_Pct_Nov2027)*(1+Raise_Pct_Apr2028)*(1+Raise_Pct_Nov2028)*(1+Raise_Pct_Apr2029)*(1+Raise_Pct_Nov2029))*(IF(MONTH($A24)>=4,(1+Raise_Pct_Apr2030),1)*IF(MONTH($A24)>=10,(1+Raise_Pct_Nov2030),1)))))))/12 -> 4420.4167 | C24: =IF(MONTH($A24)=11,((IF(DATE(YEAR($A24),4,1)<DATE(2026,10,1),Bonus_Pct_Aug2026_to_Sep2026,IF(DATE(YEAR($A24),4,1)<DATE(2027,10,1),Bonus_Pct_Oct2026_to_Sep2027,IF(DATE(YEAR($A24),4,1)<DATE(2028,10,1),Bonus_Pct_Oct2027_to_Sep2028,IF(DATE(YEAR($A24),4,1)<DATE(2029,10,1),Bonus_Pct_Oct2028_to_Sep2029,Bonus_Pct_Oct2029_onwards)))))/2)*($B24*12) / (1 + IF(YEAR($A24)=2027,Raise_Pct_Nov2027,IF(YEAR($A24)=2028,Raise_Pct_Nov2028,IF(YEAR($A24)=2029,Raise_Pct_Nov2029,IF(YEAR($A24)=2030,Raise_Pct_Nov2030,0))))) * IF(YEAR($A24)=2026,2/6,1),IF(MONTH($A24)=5,((IF(DATE(YEAR($A24)-1,10,1)<DATE(2026,10,1),Bonus_Pct_Aug2026_to_Sep2026,IF(DATE(YEAR($A24)-1,10,1)<DATE(2027,10,1),Bonus_Pct_Oct2026_to_Sep2027,IF(DATE(YEAR($A24)-1,10,1)<DATE(2028,10,1),Bonus_Pct_Oct2027_to_Sep2028,IF(DATE(YEAR($A24)-1,10,1)<DATE(2029,10,1),Bonus_Pct_Oct2028_to_Sep2029,Bonus_Pct_Oct2029_onwards)))))/2)*($B24*12) / (1 + IF(YEAR($A24)=2027,Raise_Pct_Apr2027,IF(YEAR($A24)=2028,Raise_Pct_Apr2028,IF(YEAR($A24)=2029,Raise_Pct_Apr2029,IF(YEAR($A24)=2030,Raise_Pct_Apr2030,0))))),0)) -> 0 | D24: =IF(OR($A24=DATE(2027,9,1),$A24=EDATE(DATE(2027,9,1),12),$A24=EDATE(DATE(2027,9,1),24)),(New_Hire_Stock_Grant_USD/3)/FX_USD_per_GBP*(1+IF(YEAR($A24)=2027,Inputs!$B$56,IF(YEAR($A24)=2028,Inputs!$B$57,IF(YEAR($A24)=2029,Inputs!$B$58,0)))),0)+IF(OR($A24=DATE(2028,11,1),$A24=DATE(2029,11,1),$A24=DATE(2030,11,1)),(RSU_Grant_Nov2027_USD/3)/FX_USD_per_GBP*(1+RSU_Price_Change_Pct)^(YEAR($A24)-2028),0)+IF(OR($A24=DATE(2029,11,1),$A24=DATE(2030,11,1)),(RSU_Grant_Nov2028_USD/3)/FX_USD_per_GBP*(1+RSU_Price_Change_Pct)^(YEAR($A24)-2029),0)+IF($A24=DATE(2030,11,1),(RSU_Grant_Nov2029_USD/3)/FX_USD_per_GBP*(1+RSU_Price_Change_Pct)^(YEAR($A24)-2030),0) -> 0 | E24: =IF($A24=EDATE(DATE(2026,8,1),Inputs!$B$9),Inputs!$B$8,0) -> 0 | F24: =IF($A24=EDATE(DATE(2026,8,1),Inputs!$B$11),Inputs!$B$10,0) -> 0 | G24: =IF(Inputs!$B$16=1,((IF(YEAR($A24)=2026,Inputs!$B$2,IF(YEAR($A24)=2027,IF(MONTH($A24)>=Inputs!#REF!,Inputs!$B$2*(1+Inputs!$B$4),Inputs!$B$2),IF(YEAR($A24)=2028,IF(MONTH($A24)>=Inputs!#REF!,Inputs!$B$2*(1+Inputs!$B$4)*(1+Inputs!$B$5),Inputs!$B$2*(1+Inputs!$B$4)),IF(YEAR($A24)=2029,IF(MONTH($A24)>=Inputs!#REF!,Inputs!$B$2*(1+Inputs!$B$4)*(1+Inputs!$B$5)*(1+Inputs!$B$6),Inputs!$B$2*(1+Inputs!$B$4)*(1+Inputs!$B$5)),IF(MONTH($A24)>=Inputs!#REF!,Inputs!$B$2*(1+Inputs!$B$4)*(1+Inputs!$B$5)*(1+Inputs!$B$6)*(1+Inputs!$B$7),Inputs!$B$2*(1+Inputs!$B$4)*(1+Inputs!$B$5)*(1+Inputs!$B$6)))))))/12)*(MIN(Inputs!$B$17,Inputs!$B$18)*(1+Inputs!$B$19)+Inputs!$B$17*Inputs!$B$20),0) -> 0 | H24: =SUM(B24:G24) -> 4420.4167 | I24: =$H24-J24-K24 -> 3443.675 | J24: =_xlfn.SINGLE(_xlfn.LET(_xlpm.d, $A24, _xlpm.ys, YEAR(_xlfn.SINGLE(_xlpm.d)) - IF(MONTH(_xlfn.SINGLE(_xlpm.d)) < UK_TaxYear_Start_Month, 1, 0), _xlpm.start, DATE(_xlfn.SINGLE(_xlpm.ys), UK_TaxYear_Start_Month, 1), _xlpm.m, DATEDIF(_xlfn.SINGLE(_xlpm.start), _xlfn.SINGLE(_xlpm.d), "m") + 1, _xlpm.cum, SUMIFS($H$2:$H$54, $A$2:$A$54, ">=" & _xlfn.SINGLE(_xlpm.start), $A$2:$A$54, "<=" & _xlfn.SINGLE(_xlpm.d)), _xlpm.pa, UK_Personal_Allowance_Annual / 12 * _xlfn.SINGLE(_xlpm.m), _xlpm.br, (UK_Basic_Band_Upper_Annual - UK_Personal_Allowance_Annual) / 12 * _xlfn.SINGLE(_xlpm.m), _xlpm.hr, (UK_Higher_Band_Upper_Annual - UK_Basic_Band_Upper_Annual) / 12 * _xlfn.SINGLE(_xlpm.m), _xlpm.taxable, MAX(0, _xlfn.SINGLE(_xlpm.cum) - _xlfn.SINGLE(_xlpm.pa)), _xlpm.tax_to_date, UK_Basic_Rate * MIN(_xlpm.taxable, _xlpm.br) + UK_Higher_Rate * MIN(MAX(_xlfn.SINGLE(_xlpm.taxable) - _xlfn.SINGLE(_xlpm.br), 0), _xlpm.hr) + UK_Additional_Rate * MAX(_xlfn.SINGLE(_xlpm.taxable) - _xlfn.SINGLE(_xlpm.br) - _xlfn.SINGLE(_xlpm.hr), 0), _xlpm.prior, SUMIFS($J$2:$J$54, $A$2:$A$54, ">=" & _xlfn.SINGLE(_xlpm.start), $A$2:$A$54, "<" & _xlfn.SINGLE(_xlpm.d)), MAX(0, _xlfn.SINGLE(_xlpm.tax_to_date) - _xlfn.SINGLE(_xlpm.prior)))) -> 720.83333 | K24: =_xlfn.SINGLE(_xlfn.LET(_xlpm.g, $H24, _xlpm.pt, UK_NI_PT_Monthly, _xlpm.uel, UK_NI_UEL_Monthly, IF(_xlfn.SINGLE(_xlpm.g) <= _xlfn.SINGLE(_xlpm.pt), 0, UK_NI_Main_Rate * MIN(_xlfn.SINGLE(_xlpm.g) - _xlfn.SINGLE(_xlpm.pt), _xlfn.SINGLE(_xlpm.uel) - _xlfn.SINGLE(_xlpm.pt)) + UK_NI_Upper_Rate * MAX(_xlfn.SINGLE(_xlpm.g) - _xlfn.SINGLE(_xlpm.uel), 0)))) -> 255.90833 | L24: =IF($A24<DATE(2026,10,1),Bonus_Pct_Aug2026_to_Sep2026,IF($A24<DATE(2027,10,1),Bonus_Pct_Oct2026_to_Sep2027,IF($A24<DATE(2028,10,1),Bonus_Pct_Oct2027_to_Sep2028,IF($A24<DATE(2029,10,1),Bonus_Pct_Oct2028_to_Sep2029,Bonus_Pct_Oct2029_onwards)))) -> 0.08 | M24: =M23*12 -> 10720.08
A25: 46935 | B25: =(IF(YEAR($A25)=2026,Base_Annual_Salary_GBP,IF(YEAR($A25)=2027,Base_Annual_Salary_GBP*(IF(MONTH($A25)>=4,(1+Raise_Pct_Apr2027),1)*IF(MONTH($A25)>=10,(1+Raise_Pct_Nov2027),1)),IF(YEAR($A25)=2028,Base_Annual_Salary_GBP*((1+Raise_Pct_Apr2027)*(1+Raise_Pct_Nov2027))*(IF(MONTH($A25)>=4,(1+Raise_Pct_Apr2028),1)*IF(MONTH($A25)>=10,(1+Raise_Pct_Nov2028),1)),IF(YEAR($A25)=2029,Base_Annual_Salary_GBP*((1+Raise_Pct_Apr2027)*(1+Raise_Pct_Nov2027)*(1+Raise_Pct_Apr2028)*(1+Raise_Pct_Nov2028))*(IF(MONTH($A25)>=4,(1+Raise_Pct_Apr2029),1)*IF(MONTH($A25)>=10,(1+Raise_Pct_Nov2029),1)),Base_Annual_Salary_GBP*((1+Raise_Pct_Apr2027)*(1+Raise_Pct_Nov2027)*(1+Raise_Pct_Apr2028)*(1+Raise_Pct_Nov2028)*(1+Raise_Pct_Apr2029)*(1+Raise_Pct_Nov2029))*(IF(MONTH($A25)>=4,(1+Raise_Pct_Apr2030),1)*IF(MONTH($A25)>=10,(1+Raise_Pct_Nov2030),1)))))))/12 -> 4420.4167 | C25: =IF(MONTH($A25)=11,((IF(DATE(YEAR($A25),4,1)<DATE(2026,10,1),Bonus_Pct_Aug2026_to_Sep2026,IF(DATE(YEAR($A25),4,1)<DATE(2027,10,1),Bonus_Pct_Oct2026_to_Sep2027,IF(DATE(YEAR($A25),4,1)<DATE(2028,10,1),Bonus_Pct_Oct2027_to_Sep2028,IF(DATE(YEAR($A25),4,1)<DATE(2029,10,1),Bonus_Pct_Oct2028_to_Sep2029,Bonus_Pct_Oct2029_onwards)))))/2)*($B25*12) / (1 + IF(YEAR($A25)=2027,Raise_Pct_Nov2027,IF(YEAR($A25)=2028,Raise_Pct_Nov2028,IF(YEAR($A25)=2029,Raise_Pct_Nov2029,IF(YEAR($A25)=2030,Raise_Pct_Nov2030,0))))) * IF(YEAR($A25)=2026,2/6,1),IF(MONTH($A25)=5,((IF(DATE(YEAR($A25)-1,10,1)<DATE(2026,10,1),Bonus_Pct_Aug2026_to_Sep2026,IF(DATE(YEAR($A25)-1,10,1)<DATE(2027,10,1),Bonus_Pct_Oct2026_to_Sep2027,IF(DATE(YEAR($A25)-1,10,1)<DATE(2028,10,1),Bonus_Pct_Oct2027_to_Sep2028,IF(DATE(YEAR($A25)-1,10,1)<DATE(2029,10,1),Bonus_Pct_Oct2028_to_Sep2029,Bonus_Pct_Oct2029_onwards)))))/2)*($B25*12) / (1 + IF(YEAR($A25)=2027,Raise_Pct_Apr2027,IF(YEAR($A25)=2028,Raise_Pct_Apr2028,IF(YEAR($A25)=2029,Raise_Pct_Apr2029,IF(YEAR($A25)=2030,Raise_Pct_Apr2030,0))))),0)) -> 0 | D25: =IF(OR($A25=DATE(2027,9,1),$A25=EDATE(DATE(2027,9,1),12),$A25=EDATE(DATE(2027,9,1),24)),(New_Hire_Stock_Grant_USD/3)/FX_USD_per_GBP*(1+IF(YEAR($A25)=2027,Inputs!$B$56,IF(YEAR($A25)=2028,Inputs!$B$57,IF(YEAR($A25)=2029,Inputs!$B$58,0)))),0)+IF(OR($A25=DATE(2028,11,1),$A25=DATE(2029,11,1),$A25=DATE(2030,11,1)),(RSU_Grant_Nov2027_USD/3)/FX_USD_per_GBP*(1+RSU_Price_Change_Pct)^(YEAR($A25)-2028),0)+IF(OR($A25=DATE(2029,11,1),$A25=DATE(2030,11,1)),(RSU_Grant_Nov2028_USD/3)/FX_USD_per_GBP*(1+RSU_Price_Change_Pct)^(YEAR($A25)-2029),0)+IF($A25=DATE(2030,11,1),(RSU_Grant_Nov2029_USD/3)/FX_USD_per_GBP*(1+RSU_Price_Change_Pct)^(YEAR($A25)-2030),0) -> 0 | E25: =IF($A25=EDATE(DATE(2026,8,1),Inputs!$B$9),Inputs!$B$8,0) -> 0 | F25: =IF($A25=EDATE(DATE(2026,8,1),Inputs!$B$11),Inputs!$B$10,0) -> 0 | G25: =IF(Inputs!$B$16=1,((IF(YEAR($A25)=2026,Inputs!$B$2,IF(YEAR($A25)=2027,IF(MONTH($A25)>=Inputs!#REF!,Inputs!$B$2*(1+Inputs!$B$4),Inputs!$B$2),IF(YEAR($A25)=2028,IF(MONTH($A25)>=Inputs!#REF!,Inputs!$B$2*(1+Inputs!$B$4)*(1+Inputs!$B$5),Inputs!$B$2*(1+Inputs!$B$4)),IF(YEAR($A25)=2029,IF(MONTH($A25)>=Inputs!#REF!,Inputs!$B$2*(1+Inputs!$B$4)*(1+Inputs!$B$5)*(1+Inputs!$B$6),Inputs!$B$2*(1+Inputs!$B$4)*(1+Inputs!$B$5)),IF(MONTH($A25)>=Inputs!#REF!,Inputs!$B$2*(1+Inputs!$B$4)*(1+Inputs!$B$5)*(1+Inputs!$B$6)*(1+Inputs!$B$7),Inputs!$B$2*(1+Inputs!$B$4)*(1+Inputs!$B$5)*(1+Inputs!$B$6)))))))/12)*(MIN(Inputs!$B$17,Inputs!$B$18)*(1+Inputs!$B$19)+Inputs!$B$17*Inputs!$B$20),0) -> 0 | H25: =SUM(B25:G25) -> 4420.4167 | I25: =$H25-J25-K25 -> 3443.675 | J25: =_xlfn.SINGLE(_xlfn.LET(_xlpm.d, $A25, _xlpm.ys, YEAR(_xlfn.SINGLE(_xlpm.d)) - IF(MONTH(_xlfn.SINGLE(_xlpm.d)) < UK_TaxYear_Start_Month, 1, 0), _xlpm.start, DATE(_xlfn.SINGLE(_xlpm.ys), UK_TaxYear_Start_Month, 1), _xlpm.m, DATEDIF(_xlfn.SINGLE(_xlpm.start), _xlfn.SINGLE(_xlpm.d), "m") + 1, _xlpm.cum, SUMIFS($H$2:$H$54, $A$2:$A$54, ">=" & _xlfn.SINGLE(_xlpm.start), $A$2:$A$54, "<=" & _xlfn.SINGLE(_xlpm.d)), _xlpm.pa, UK_Personal_Allowance_Annual / 12 * _xlfn.SINGLE(_xlpm.m), _xlpm.br, (UK_Basic_Band_Upper_Annual - UK_Personal_Allowance_Annual) / 12 * _xlfn.SINGLE(_xlpm.m), _xlpm.hr, (UK_Higher_Band_Upper_Annual - UK_Basic_Band_Upper_Annual) / 12 * _xlfn.SINGLE(_xlpm.m), _xlpm.taxable, MAX(0, _xlfn.SINGLE(_xlpm.cum) - _xlfn.SINGLE(_xlpm.pa)), _xlpm.tax_to_date, UK_Basic_Rate * MIN(_xlpm.taxable, _xlpm.br) + UK_Higher_Rate * MIN(MAX(_xlfn.SINGLE(_xlpm.taxable) - _xlfn.SINGLE(_xlpm.br), 0), _xlpm.hr) + UK_Additional_Rate * MAX(_xlfn.SINGLE(_xlpm.taxable) - _xlfn.SINGLE(_xlpm.br) - _xlfn.SINGLE(_xlpm.hr), 0), _xlpm.prior, SUMIFS($J$2:$J$54, $A$2:$A$54, ">=" & _xlfn.SINGLE(_xlpm.start), $A$2:$A$54, "<" & _xlfn.SINGLE(_xlpm.d)), MAX(0, _xlfn.SINGLE(_xlpm.tax_to_date) - _xlfn.SINGLE(_xlpm.prior)))) -> 720.83333 | K25: =_xlfn.SINGLE(_xlfn.LET(_xlpm.g, $H25, _xlpm.pt, UK_NI_PT_Monthly, _xlpm.uel, UK_NI_UEL_Monthly, IF(_xlfn.SINGLE(_xlpm.g) <= _xlfn.SINGLE(_xlpm.pt), 0, UK_NI_Main_Rate * MIN(_xlfn.SINGLE(_xlpm.g) - _xlfn.SINGLE(_xlpm.pt), _xlfn.SINGLE(_xlpm.uel) - _xlfn.SINGLE(_xlpm.pt)) + UK_NI_Upper_Rate * MAX(_xlfn.SINGLE(_xlpm.g) - _xlfn.SINGLE(_xlpm.uel), 0)))) -> 255.90833 | L25: =IF($A25<DATE(2026,10,1),Bonus_Pct_Aug2026_to_Sep2026,IF($A25<DATE(2027,10,1),Bonus_Pct_Oct2026_to_Sep2027,IF($A25<DATE(2028,10,1),Bonus_Pct_Oct2027_to_Sep2028,IF($A25<DATE(2029,10,1),Bonus_Pct_Oct2028_to_Sep2029,Bonus_Pct_Oct2029_onwards)))) -> 0.08
A26: 46966 | B26: =(IF(YEAR($A26)=2026,Base_Annual_Salary_GBP,IF(YEAR($A26)=2027,Base_Annual_Salary_GBP*(IF(MONTH($A26)>=4,(1+Raise_Pct_Apr2027),1)*IF(MONTH($A26)>=10,(1+Raise_Pct_Nov2027),1)),IF(YEAR($A26)=2028,Base_Annual_Salary_GBP*((1+Raise_Pct_Apr2027)*(1+Raise_Pct_Nov2027))*(IF(MONTH($A26)>=4,(1+Raise_Pct_Apr2028),1)*IF(MONTH($A26)>=10,(1+Raise_Pct_Nov2028),1)),IF(YEAR($A26)=2029,Base_Annual_Salary_GBP*((1+Raise_Pct_Apr2027)*(1+Raise_Pct_Nov2027)*(1+Raise_Pct_Apr2028)*(1+Raise_Pct_Nov2028))*(IF(MONTH($A26)>=4,(1+Raise_Pct_Apr2029),1)*IF(MONTH($A26)>=10,(1+Raise_Pct_Nov2029),1)),Base_Annual_Salary_GBP*((1+Raise_Pct_Apr2027)*(1+Raise_Pct_Nov2027)*(1+Raise_Pct_Apr2028)*(1+Raise_Pct_Nov2028)*(1+Raise_Pct_Apr2029)*(1+Raise_Pct_Nov2029))*(IF(MONTH($A26)>=4,(1+Raise_Pct_Apr2030),1)*IF(MONTH($A26)>=10,(1+Raise_Pct_Nov2030),1)))))))/12 -> 4420.4167 | C26: =IF(MONTH($A26)=11,((IF(DATE(YEAR($A26),4,1)<DATE(2026,10,1),Bonus_Pct_Aug2026_to_Sep2026,IF(DATE(YEAR($A26),4,1)<DATE(2027,10,1),Bonus_Pct_Oct2026_to_Sep2027,IF(DATE(YEAR($A26),4,1)<DATE(2028,10,1),Bonus_Pct_Oct2027_to_Sep2028,IF(DATE(YEAR($A26),4,1)<DATE(2029,10,1),Bonus_Pct_Oct2028_to_Sep2029,Bonus_Pct_Oct2029_onwards)))))/2)*($B26*12) / (1 + IF(YEAR($A26)=2027,Raise_Pct_Nov2027,IF(YEAR($A26)=2028,Raise_Pct_Nov2028,IF(YEAR($A26)=2029,Raise_Pct_Nov2029,IF(YEAR($A26)=2030,Raise_Pct_Nov2030,0))))) * IF(YEAR($A26)=2026,2/6,1),IF(MONTH($A26)=5,((IF(DATE(YEAR($A26)-1,10,1)<DATE(2026,10,1),Bonus_Pct_Aug2026_to_Sep2026,IF(DATE(YEAR($A26)-1,10,1)<DATE(2027,10,1),Bonus_Pct_Oct2026_to_Sep2027,IF(DATE(YEAR($A26)-1,10,1)<DATE(2028,10,1),Bonus_Pct_Oct2027_to_Sep2028,IF(DATE(YEAR($A26)-1,10,1)<DATE(2029,10,1),Bonus_Pct_Oct2028_to_Sep2029,Bonus_Pct_Oct2029_onwards)))))/2)*($B26*12) / (1 + IF(YEAR($A26)=2027,Raise_Pct_Apr2027,IF(YEAR($A26)=2028,Raise_Pct_Apr2028,IF(YEAR($A26)=2029,Raise_Pct_Apr2029,IF(YEAR($A26)=2030,Raise_Pct_Apr2030,0))))),0)) -> 0 | D26: =IF(OR($A26=DATE(2027,9,1),$A26=EDATE(DATE(2027,9,1),12),$A26=EDATE(DATE(2027,9,1),24)),(New_Hire_Stock_Grant_USD/3)/FX_USD_per_GBP*(1+IF(YEAR($A26)=2027,Inputs!$B$56,IF(YEAR($A26)=2028,Inputs!$B$57,IF(YEAR($A26)=2029,Inputs!$B$58,0)))),0)+IF(OR($A26=DATE(2028,11,1),$A26=DATE(2029,11,1),$A26=DATE(2030,11,1)),(RSU_Grant_Nov2027_USD/3)/FX_USD_per_GBP*(1+RSU_Price_Change_Pct)^(YEAR($A26)-2028),0)+IF(OR($A26=DATE(2029,11,1),$A26=DATE(2030,11,1)),(RSU_Grant_Nov2028_USD/3)/FX_USD_per_GBP*(1+RSU_Price_Change_Pct)^(YEAR($A26)-2029),0)+IF($A26=DATE(2030,11,1),(RSU_Grant_Nov2029_USD/3)/FX_USD_per_GBP*(1+RSU_Price_Change_Pct)^(YEAR($A26)-2030),0) -> 0 | E26: =IF($A26=EDATE(DATE(2026,8,1),Inputs!$B$9),Inputs!$B$8,0) -> 0 | F26: =IF($A26=EDATE(DATE(2026,8,1),Inputs!$B$11),Inputs!$B$10,0) -> 0 | G26: =IF(Inputs!$B$16=1,((IF(YEAR($A26)=2026,Inputs!$B$2,IF(YEAR($A26)=2027,IF(MONTH($A26)>=Inputs!#REF!,Inputs!$B$2*(1+Inputs!$B$4),Inputs!$B$2),IF(YEAR($A26)=2028,IF(MONTH($A26)>=Inputs!#REF!,Inputs!$B$2*(1+Inputs!$B$4)*(1+Inputs!$B$5),Inputs!$B$2*(1+Inputs!$B$4)),IF(YEAR($A26)=2029,IF(MONTH($A26)>=Inputs!#REF!,Inputs!$B$2*(1+Inputs!$B$4)*(1+Inputs!$B$5)*(1+Inputs!$B$6),Inputs!$B$2*(1+Inputs!$B$4)*(1+Inputs!$B$5)),IF(MONTH($A26)>=Inputs!#REF!,Inputs!$B$2*(1+Inputs!$B$4)*(1+Inputs!$B$5)*(1+Inputs!$B$6)*(1+Inputs!$B$7),Inputs!$B$2*(1+Inputs!$B$4)*(1+Inputs!$B$5)*(1+Inputs!$B$6)))))))/12)*(MIN(Inputs!$B$17,Inputs!$B$18)*(1+Inputs!$B$19)+Inputs!$B$17*Inputs!$B$20),0) -> 0 | H26: =SUM(B26:G26) -> 4420.4167 | I26: =$H26-J26-K26 -> 3443.675 | J26: =_xlfn.SINGLE(_xlfn.LET(_xlpm.d, $A26, _xlpm.ys, YEAR(_xlfn.SINGLE(_xlpm.d)) - IF(MONTH(_xlfn.SINGLE(_xlpm.d)) < UK_TaxYear_Start_Month, 1, 0), _xlpm.start, DATE(_xlfn.SINGLE(_xlpm.ys), UK_TaxYear_Start_Month, 1), _xlpm.m, DATEDIF(_xlfn.SINGLE(_xlpm.start), _xlfn.SINGLE(_xlpm.d), "m") + 1, _xlpm.cum, SUMIFS($H$2:$H$54, $A$2:$A$54, ">=" & _xlfn.SINGLE(_xlpm.start), $A$2:$A$54, "<=" & _xlfn.SINGLE(_xlpm.d)), _xlpm.pa, UK_Personal_Allowance_Annual / 12 * _xlfn.SINGLE(_xlpm.m), _xlpm.br, (UK_Basic_Band_Upper_Annual - UK_Personal_Allowance_Annual) / 12 * _xlfn.SINGLE(_xlpm.m), _xlpm.hr, (UK_Higher_Band_Upper_Annual - UK_Basic_Band_Upper_Annual) / 12 * _xlfn.SINGLE(_xlpm.m), _xlpm.taxable, MAX(0, _xlfn.SINGLE(_xlpm.cum) - _xlfn.SINGLE(_xlpm.pa)), _xlpm.tax_to_date, UK_Basic_Rate * MIN(_xlpm.taxable, _xlpm.br) + UK_Higher_Rate * MIN(MAX(_xlfn.SINGLE(_xlpm.taxable) - _xlfn.SINGLE(_xlpm.br), 0), _xlpm.hr) + UK_Additional_Rate * MAX(_xlfn.SINGLE(_xlpm.taxable) - _xlfn.SINGLE(_xlpm.br) - _xlfn.SINGLE(_xlpm.hr), 0), _xlpm.prior, SUMIFS($J$2:$J$54, $A$2:$A$54, ">=" & _xlfn.SINGLE(_xlpm.start), $A$2:$A$54, "<" & _xlfn.SINGLE(_xlpm.d)), MAX(0, _xlfn.SINGLE(_xlpm.tax_to_date) - _xlfn.SINGLE(_xlpm.prior)))) -> 720.83333 | K26: =_xlfn.SINGLE(_xlfn.LET(_xlpm.g, $H26, _xlpm.pt, UK_NI_PT_Monthly, _xlpm.uel, UK_NI_UEL_Monthly, IF(_xlfn.SINGLE(_xlpm.g) <= _xlfn.SINGLE(_xlpm.pt), 0, UK_NI_Main_Rate * MIN(_xlfn.SINGLE(_xlpm.g) - _xlfn.SINGLE(_xlpm.pt), _xlfn.SINGLE(_xlpm.uel) - _xlfn.SINGLE(_xlpm.pt)) + UK_NI_Upper_Rate * MAX(_xlfn.SINGLE(_xlpm.g) - _xlfn.SINGLE(_xlpm.uel), 0)))) -> 255.90833 | L26: =IF($A26<DATE(2026,10,1),Bonus_Pct_Aug2026_to_Sep2026,IF($A26<DATE(2027,10,1),Bonus_Pct_Oct2026_to_Sep2027,IF($A26<DATE(2028,10,1),Bonus_Pct_Oct2027_to_Sep2028,IF($A26<DATE(2029,10,1),Bonus_Pct_Oct2028_to_Sep2029,Bonus_Pct_Oct2029_onwards)))) -> 0.08 | M26: =13772/12 -> 1147.6667
A27: 46997 | B27: =(IF(YEAR($A27)=2026,Base_Annual_Salary_GBP,IF(YEAR($A27)=2027,Base_Annual_Salary_GBP*(IF(MONTH($A27)>=4,(1+Raise_Pct_Apr2027),1)*IF(MONTH($A27)>=10,(1+Raise_Pct_Nov2027),1)),IF(YEAR($A27)=2028,Base_Annual_Salary_GBP*((1+Raise_Pct_Apr2027)*(1+Raise_Pct_Nov2027))*(IF(MONTH($A27)>=4,(1+Raise_Pct_Apr2028),1)*IF(MONTH($A27)>=10,(1+Raise_Pct_Nov2028),1)),IF(YEAR($A27)=2029,Base_Annual_Salary_GBP*((1+Raise_Pct_Apr2027)*(1+Raise_Pct_Nov2027)*(1+Raise_Pct_Apr2028)*(1+Raise_Pct_Nov2028))*(IF(MONTH($A27)>=4,(1+Raise_Pct_Apr2029),1)*IF(MONTH($A27)>=10,(1+Raise_Pct_Nov2029),1)),Base_Annual_Salary_GBP*((1+Raise_Pct_Apr2027)*(1+Raise_Pct_Nov2027)*(1+Raise_Pct_Apr2028)*(1+Raise_Pct_Nov2028)*(1+Raise_Pct_Apr2029)*(1+Raise_Pct_Nov2029))*(IF(MONTH($A27)>=4,(1+Raise_Pct_Apr2030),1)*IF(MONTH($A27)>=10,(1+Raise_Pct_Nov2030),1)))))))/12 -> 4420.4167 | C27: =IF(MONTH($A27)=11,((IF(DATE(YEAR($A27),4,1)<DATE(2026,10,1),Bonus_Pct_Aug2026_to_Sep2026,IF(DATE(YEAR($A27),4,1)<DATE(2027,10,1),Bonus_Pct_Oct2026_to_Sep2027,IF(DATE(YEAR($A27),4,1)<DATE(2028,10,1),Bonus_Pct_Oct2027_to_Sep2028,IF(DATE(YEAR($A27),4,1)<DATE(2029,10,1),Bonus_Pct_Oct2028_to_Sep2029,Bonus_Pct_Oct2029_onwards)))))/2)*($B27*12) / (1 + IF(YEAR($A27)=2027,Raise_Pct_Nov2027,IF(YEAR($A27)=2028,Raise_Pct_Nov2028,IF(YEAR($A27)=2029,Raise_Pct_Nov2029,IF(YEAR($A27)=2030,Raise_Pct_Nov2030,0))))) * IF(YEAR($A27)=2026,2/6,1),IF(MONTH($A27)=5,((IF(DATE(YEAR($A27)-1,10,1)<DATE(2026,10,1),Bonus_Pct_Aug2026_to_Sep2026,IF(DATE(YEAR($A27)-1,10,1)<DATE(2027,10,1),Bonus_Pct_Oct2026_to_Sep2027,IF(DATE(YEAR($A27)-1,10,1)<DATE(2028,10,1),Bonus_Pct_Oct2027_to_Sep2028,IF(DATE(YEAR($A27)-1,10,1)<DATE(2029,10,1),Bonus_Pct_Oct2028_to_Sep2029,Bonus_Pct_Oct2029_onwards)))))/2)*($B27*12) / (1 + IF(YEAR($A27)=2027,Raise_Pct_Apr2027,IF(YEAR($A27)=2028,Raise_Pct_Apr2028,IF(YEAR($A27)=2029,Raise_Pct_Apr2029,IF(YEAR($A27)=2030,Raise_Pct_Apr2030,0))))),0)) -> 0 | D27: =IF(OR($A27=DATE(2027,9,1),$A27=EDATE(DATE(2027,9,1),12),$A27=EDATE(DATE(2027,9,1),24)),(New_Hire_Stock_Grant_USD/3)/FX_USD_per_GBP*(1+IF(YEAR($A27)=2027,Inputs!$B$56,IF(YEAR($A27)=2028,Inputs!$B$57,IF(YEAR($A27)=2029,Inputs!$B$58,0)))),0)+IF(OR($A27=DATE(2028,11,1),$A27=DATE(2029,11,1),$A27=DATE(2030,11,1)),(RSU_Grant_Nov2027_USD/3)/FX_USD_per_GBP*(1+RSU_Price_Change_Pct)^(YEAR($A27)-2028),0)+IF(OR($A27=DATE(2029,11,1),$A27=DATE(2030,11,1)),(RSU_Grant_Nov2028_USD/3)/FX_USD_per_GBP*(1+RSU_Price_Change_Pct)^(YEAR($A27)-2029),0)+IF($A27=DATE(2030,11,1),(RSU_Grant_Nov2029_USD/3)/FX_USD_per_GBP*(1+RSU_Price_Change_Pct)^(YEAR($A27)-2030),0) -> 7352.9412 | E27: =IF($A27=EDATE(DATE(2026,8,1),Inputs!$B$9),Inputs!$B$8,0) -> 0 | F27: =IF($A27=EDATE(DATE(2026,8,1),Inputs!$B$11),Inputs!$B$10,0) -> 0 | G27: =IF(Inputs!$B$16=1,((IF(YEAR($A27)=2026,Inputs!$B$2,IF(YEAR($A27)=2027,IF(MONTH($A27)>=Inputs!#REF!,Inputs!$B$2*(1+Inputs!$B$4),Inputs!$B$2),IF(YEAR($A27)=2028,IF(MONTH($A27)>=Inputs!#REF!,Inputs!$B$2*(1+Inputs!$B$4)*(1+Inputs!$B$5),Inputs!$B$2*(1+Inputs!$B$4)),IF(YEAR($A27)=2029,IF(MONTH($A27)>=Inputs!#REF!,Inputs!$B$2*(1+Inputs!$B$4)*(1+Inputs!$B$5)*(1+Inputs!$B$6),Inputs!$B$2*(1+Inputs!$B$4)*(1+Inputs!$B$5)),IF(MONTH($A27)>=Inputs!#REF!,Inputs!$B$2*(1+Inputs!$B$4)*(1+Inputs!$B$5)*(1+Inputs!$B$6)*(1+Inputs!$B$7),Inputs!$B$2*(1+Inputs!$B$4)*(1+Inputs!$B$5)*(1+Inputs!$B$6)))))))/12)*(MIN(Inputs!$B$17,Inputs!$B$18)*(1+Inputs!$B$19)+Inputs!$B$17*Inputs!$B$20),0) -> 0 | H27: =SUM(B27:G27) -> 11773.358 | I27: =$H27-J27-K27 -> 7708.3809 | J27: =_xlfn.SINGLE(_xlfn.LET(_xlpm.d, $A27, _xlpm.ys, YEAR(_xlfn.SINGLE(_xlpm.d)) - IF(MONTH(_xlfn.SINGLE(_xlpm.d)) < UK_TaxYear_Start_Month, 1, 0), _xlpm.start, DATE(_xlfn.SINGLE(_xlpm.ys), UK_TaxYear_Start_Month, 1), _xlpm.m, DATEDIF(_xlfn.SINGLE(_xlpm.start), _xlfn.SINGLE(_xlpm.d), "m") + 1, _xlpm.cum, SUMIFS($H$2:$H$54, $A$2:$A$54, ">=" & _xlfn.SINGLE(_xlpm.start), $A$2:$A$54, "<=" & _xlfn.SINGLE(_xlpm.d)), _xlpm.pa, UK_Personal_Allowance_Annual / 12 * _xlfn.SINGLE(_xlpm.m), _xlpm.br, (UK_Basic_Band_Upper_Annual - UK_Personal_Allowance_Annual) / 12 * _xlfn.SINGLE(_xlpm.m), _xlpm.hr, (UK_Higher_Band_Upper_Annual - UK_Basic_Band_Upper_Annual) / 12 * _xlfn.SINGLE(_xlpm.m), _xlpm.taxable, MAX(0, _xlfn.SINGLE(_xlpm.cum) - _xlfn.SINGLE(_xlpm.pa)), _xlpm.tax_to_date, UK_Basic_Rate * MIN(_xlpm.taxable, _xlpm.br) + UK_Higher_Rate * MIN(MAX(_xlfn.SINGLE(_xlpm.taxable) - _xlfn.SINGLE(_xlpm.br), 0), _xlpm.hr) + UK_Additional_Rate * MAX(_xlfn.SINGLE(_xlpm.taxable) - _xlfn.SINGLE(_xlpm.br) - _xlfn.SINGLE(_xlpm.hr), 0), _xlpm.prior, SUMIFS($J$2:$J$54, $A$2:$A$54, ">=" & _xlfn.SINGLE(_xlpm.start), $A$2:$A$54, "<" & _xlfn.SINGLE(_xlpm.d)), MAX(0, _xlfn.SINGLE(_xlpm.tax_to_date) - _xlfn.SINGLE(_xlpm.prior)))) -> 3662.0098 | K27: =_xlfn.SINGLE(_xlfn.LET(_xlpm.g, $H27, _xlpm.pt, UK_NI_PT_Monthly, _xlpm.uel, UK_NI_UEL_Monthly, IF(_xlfn.SINGLE(_xlpm.g) <= _xlfn.SINGLE(_xlpm.pt), 0, UK_NI_Main_Rate * MIN(_xlfn.SINGLE(_xlpm.g) - _xlfn.SINGLE(_xlpm.pt), _xlfn.SINGLE(_xlpm.uel) - _xlfn.SINGLE(_xlpm.pt)) + UK_NI_Upper_Rate * MAX(_xlfn.SINGLE(_xlpm.g) - _xlfn.SINGLE(_xlpm.uel), 0)))) -> 402.96716 | L27: =IF($A27<DATE(2026,10,1),Bonus_Pct_Aug2026_to_Sep2026,IF($A27<DATE(2027,10,1),Bonus_Pct_Oct2026_to_Sep2027,IF($A27<DATE(2028,10,1),Bonus_Pct_Oct2027_to_Sep2028,IF($A27<DATE(2029,10,1),Bonus_Pct_Oct2028_to_Sep2029,Bonus_Pct_Oct2029_onwards)))) -> 0.08
A28: 47027 | B28: =(IF(YEAR($A28)=2026,Base_Annual_Salary_GBP,IF(YEAR($A28)=2027,Base_Annual_Salary_GBP*(IF(MONTH($A28)>=4,(1+Raise_Pct_Apr2027),1)*IF(MONTH($A28)>=10,(1+Raise_Pct_Nov2027),1)),IF(YEAR($A28)=2028,Base_Annual_Salary_GBP*((1+Raise_Pct_Apr2027)*(1+Raise_Pct_Nov2027))*(IF(MONTH($A28)>=4,(1+Raise_Pct_Apr2028),1)*IF(MONTH($A28)>=10,(1+Raise_Pct_Nov2028),1)),IF(YEAR($A28)=2029,Base_Annual_Salary_GBP*((1+Raise_Pct_Apr2027)*(1+Raise_Pct_Nov2027)*(1+Raise_Pct_Apr2028)*(1+Raise_Pct_Nov2028))*(IF(MONTH($A28)>=4,(1+Raise_Pct_Apr2029),1)*IF(MONTH($A28)>=10,(1+Raise_Pct_Nov2029),1)),Base_Annual_Salary_GBP*((1+Raise_Pct_Apr2027)*(1+Raise_Pct_Nov2027)*(1+Raise_Pct_Apr2028)*(1+Raise_Pct_Nov2028)*(1+Raise_Pct_Apr2029)*(1+Raise_Pct_Nov2029))*(IF(MONTH($A28)>=4,(1+Raise_Pct_Apr2030),1)*IF(MONTH($A28)>=10,(1+Raise_Pct_Nov2030),1)))))))/12 -> 4553.0292 | C28: =IF(MONTH($A28)=11,((IF(DATE(YEAR($A28),4,1)<DATE(2026,10,1),Bonus_Pct_Aug2026_to_Sep2026,IF(DATE(YEAR($A28),4,1)<DATE(2027,10,1),Bonus_Pct_Oct2026_to_Sep2027,IF(DATE(YEAR($A28),4,1)<DATE(2028,10,1),Bonus_Pct_Oct2027_to_Sep2028,IF(DATE(YEAR($A28),4,1)<DATE(2029,10,1),Bonus_Pct_Oct2028_to_Sep2029,Bonus_Pct_Oct2029_onwards)))))/2)*($B28*12) / (1 + IF(YEAR($A28)=2027,Raise_Pct_Nov2027,IF(YEAR($A28)=2028,Raise_Pct_Nov2028,IF(YEAR($A28)=2029,Raise_Pct_Nov2029,IF(YEAR($A28)=2030,Raise_Pct_Nov2030,0))))) * IF(YEAR($A28)=2026,2/6,1),IF(MONTH($A28)=5,((IF(DATE(YEAR($A28)-1,10,1)<DATE(2026,10,1),Bonus_Pct_Aug2026_to_Sep2026,IF(DATE(YEAR($A28)-1,10,1)<DATE(2027,10,1),Bonus_Pct_Oct2026_to_Sep2027,IF(DATE(YEAR($A28)-1,10,1)<DATE(2028,10,1),Bonus_Pct_Oct2027_to_Sep2028,IF(DATE(YEAR($A28)-1,10,1)<DATE(2029,10,1),Bonus_Pct_Oct2028_to_Sep2029,Bonus_Pct_Oct2029_onwards)))))/2)*($B28*12) / (1 + IF(YEAR($A28)=2027,Raise_Pct_Apr2027,IF(YEAR($A28)=2028,Raise_Pct_Apr2028,IF(YEAR($A28)=2029,Raise_Pct_Apr2029,IF(YEAR($A28)=2030,Raise_Pct_Apr2030,0))))),0)) -> 0 | D28: =IF(OR($A28=DATE(2027,9,1),$A28=EDATE(DATE(2027,9,1),12),$A28=EDATE(DATE(2027,9,1),24)),(New_Hire_Stock_Grant_USD/3)/FX_USD_per_GBP*(1+IF(YEAR($A28)=2027,Inputs!$B$56,IF(YEAR($A28)=2028,Inputs!$B$57,IF(YEAR($A28)=2029,Inputs!$B$58,0)))),0)+IF(OR($A28=DATE(2028,11,1),$A28=DATE(2029,11,1),$A28=DATE(2030,11,1)),(RSU_Grant_Nov2027_USD/3)/FX_USD_per_GBP*(1+RSU_Price_Change_Pct)^(YEAR($A28)-2028),0)+IF(OR($A28=DATE(2029,11,1),$A28=DATE(2030,11,1)),(RSU_Grant_Nov2028_USD/3)/FX_USD_per_GBP*(1+RSU_Price_Change_Pct)^(YEAR($A28)-2029),0)+IF($A28=DATE(2030,11,1),(RSU_Grant_Nov2029_USD/3)/FX_USD_per_GBP*(1+RSU_Price_Change_Pct)^(YEAR($A28)-2030),0) -> 0 | E28: =IF($A28=EDATE(DATE(2026,8,1),Inputs!$B$9),Inputs!$B$8,0) -> 0 | F28: =IF($A28=EDATE(DATE(2026,8,1),Inputs!$B$11),Inputs!$B$10,0) -> 0 | G28: =IF(Inputs!$B$16=1,((IF(YEAR($A28)=2026,Inputs!$B$2,IF(YEAR($A28)=2027,IF(MONTH($A28)>=Inputs!#REF!,Inputs!$B$2*(1+Inputs!$B$4),Inputs!$B$2),IF(YEAR($A28)=2028,IF(MONTH($A28)>=Inputs!#REF!,Inputs!$B$2*(1+Inputs!$B$4)*(1+Inputs!$B$5),Inputs!$B$2*(1+Inputs!$B$4)),IF(YEAR($A28)=2029,IF(MONTH($A28)>=Inputs!#REF!,Inputs!$B$2*(1+Inputs!$B$4)*(1+Inputs!$B$5)*(1+Inputs!$B$6),Inputs!$B$2*(1+Inputs!$B$4)*(1+Inputs!$B$5)),IF(MONTH($A28)>=Inputs!#REF!,Inputs!$B$2*(1+Inputs!$B$4)*(1+Inputs!$B$5)*(1+Inputs!$B$6)*(1+Inputs!$B$7),Inputs!$B$2*(1+Inputs!$B$4)*(1+Inputs!$B$5)*(1+Inputs!$B$6)))))))/12)*(MIN(Inputs!$B$17,Inputs!$B$18)*(1+Inputs!$B$19)+Inputs!$B$17*Inputs!$B$20),0) -> 0 | H28: =SUM(B28:G28) -> 4553.0292 | I28: =$H28-J28-K28 -> 3520.5902 | J28: =_xlfn.SINGLE(_xlfn.LET(_xlpm.d, $A28, _xlpm.ys, YEAR(_xlfn.SINGLE(_xlpm.d)) - IF(MONTH(_xlfn.SINGLE(_xlpm.d)) < UK_TaxYear_Start_Month, 1, 0), _xlpm.start, DATE(_xlfn.SINGLE(_xlpm.ys), UK_TaxYear_Start_Month, 1), _xlpm.m, DATEDIF(_xlfn.SINGLE(_xlpm.start), _xlfn.SINGLE(_xlpm.d), "m") + 1, _xlpm.cum, SUMIFS($H$2:$H$54, $A$2:$A$54, ">=" & _xlfn.SINGLE(_xlpm.start), $A$2:$A$54, "<=" & _xlfn.SINGLE(_xlpm.d)), _xlpm.pa, UK_Personal_Allowance_Annual / 12 * _xlfn.SINGLE(_xlpm.m), _xlpm.br, (UK_Basic_Band_Upper_Annual - UK_Personal_Allowance_Annual) / 12 * _xlfn.SINGLE(_xlpm.m), _xlpm.hr, (UK_Higher_Band_Upper_Annual - UK_Basic_Band_Upper_Annual) / 12 * _xlfn.SINGLE(_xlpm.m), _xlpm.taxable, MAX(0, _xlfn.SINGLE(_xlpm.cum) - _xlfn.SINGLE(_xlpm.pa)), _xlpm.tax_to_date, UK_Basic_Rate * MIN(_xlpm.taxable, _xlpm.br) + UK_Higher_Rate * MIN(MAX(_xlfn.SINGLE(_xlpm.taxable) - _xlfn.SINGLE(_xlpm.br), 0), _xlpm.hr) + UK_Additional_Rate * MAX(_xlfn.SINGLE(_xlpm.taxable) - _xlfn.SINGLE(_xlpm.br) - _xlfn.SINGLE(_xlpm.hr), 0), _xlpm.prior, SUMIFS($J$2:$J$54, $A$2:$A$54, ">=" & _xlfn.SINGLE(_xlpm.start), $A$2:$A$54, "<" & _xlfn.SINGLE(_xlpm.d)), MAX(0, _xlfn.SINGLE(_xlpm.tax_to_date) - _xlfn.SINGLE(_xlpm.prior)))) -> 773.87833 | K28: =_xlfn.SINGLE(_xlfn.LET(_xlpm.g, $H28, _xlpm.pt, UK_NI_PT_Monthly, _xlpm.uel, UK_NI_UEL_Monthly, IF(_xlfn.SINGLE(_xlpm.g) <= _xlfn.SINGLE(_xlpm.pt), 0, UK_NI_Main_Rate * MIN(_xlfn.SINGLE(_xlpm.g) - _xlfn.SINGLE(_xlpm.pt), _xlfn.SINGLE(_xlpm.uel) - _xlfn.SINGLE(_xlpm.pt)) + UK_NI_Upper_Rate * MAX(_xlfn.SINGLE(_xlpm.g) - _xlfn.SINGLE(_xlpm.uel), 0)))) -> 258.56058 | L28: =IF($A28<DATE(2026,10,1),Bonus_Pct_Aug2026_to_Sep2026,IF($A28<DATE(2027,10,1),Bonus_Pct_Oct2026_to_Sep2027,IF($A28<DATE(2028,10,1),Bonus_Pct_Oct2027_to_Sep2028,IF($A28<DATE(2029,10,1),Bonus_Pct_Oct2028_to_Sep2029,Bonus_Pct_Oct2029_onwards)))) -> 0.1
A29: 47058 | B29: =(IF(YEAR($A29)=2026,Base_Annual_Salary_GBP,IF(YEAR($A29)=2027,Base_Annual_Salary_GBP*(IF(MONTH($A29)>=4,(1+Raise_Pct_Apr2027),1)*IF(MONTH($A29)>=10,(1+Raise_Pct_Nov2027),1)),IF(YEAR($A29)=2028,Base_Annual_Salary_GBP*((1+Raise_Pct_Apr2027)*(1+Raise_Pct_Nov2027))*(IF(MONTH($A29)>=4,(1+Raise_Pct_Apr2028),1)*IF(MONTH($A29)>=10,(1+Raise_Pct_Nov2028),1)),IF(YEAR($A29)=2029,Base_Annual_Salary_GBP*((1+Raise_Pct_Apr2027)*(1+Raise_Pct_Nov2027)*(1+Raise_Pct_Apr2028)*(1+Raise_Pct_Nov2028))*(IF(MONTH($A29)>=4,(1+Raise_Pct_Apr2029),1)*IF(MONTH($A29)>=10,(1+Raise_Pct_Nov2029),1)),Base_Annual_Salary_GBP*((1+Raise_Pct_Apr2027)*(1+Raise_Pct_Nov2027)*(1+Raise_Pct_Apr2028)*(1+Raise_Pct_Nov2028)*(1+Raise_Pct_Apr2029)*(1+Raise_Pct_Nov2029))*(IF(MONTH($A29)>=4,(1+Raise_Pct_Apr2030),1)*IF(MONTH($A29)>=10,(1+Raise_Pct_Nov2030),1)))))))/12 -> 4553.0292 | C29: =IF(MONTH($A29)=11,((IF(DATE(YEAR($A29),4,1)<DATE(2026,10,1),Bonus_Pct_Aug2026_to_Sep2026,IF(DATE(YEAR($A29),4,1)<DATE(2027,10,1),Bonus_Pct_Oct2026_to_Sep2027,IF(DATE(YEAR($A29),4,1)<DATE(2028,10,1),Bonus_Pct_Oct2027_to_Sep2028,IF(DATE(YEAR($A29),4,1)<DATE(2029,10,1),Bonus_Pct_Oct2028_to_Sep2029,Bonus_Pct_Oct2029_onwards)))))/2)*($B29*12) / (1 + IF(YEAR($A29)=2027,Raise_Pct_Nov2027,IF(YEAR($A29)=2028,Raise_Pct_Nov2028,IF(YEAR($A29)=2029,Raise_Pct_Nov2029,IF(YEAR($A29)=2030,Raise_Pct_Nov2030,0))))) * IF(YEAR($A29)=2026,2/6,1),IF(MONTH($A29)=5,((IF(DATE(YEAR($A29)-1,10,1)<DATE(2026,10,1),Bonus_Pct_Aug2026_to_Sep2026,IF(DATE(YEAR($A29)-1,10,1)<DATE(2027,10,1),Bonus_Pct_Oct2026_to_Sep2027,IF(DATE(YEAR($A29)-1,10,1)<DATE(2028,10,1),Bonus_Pct_Oct2027_to_Sep2028,IF(DATE(YEAR($A29)-1,10,1)<DATE(2029,10,1),Bonus_Pct_Oct2028_to_Sep2029,Bonus_Pct_Oct2029_onwards)))))/2)*($B29*12) / (1 + IF(YEAR($A29)=2027,Raise_Pct_Apr2027,IF(YEAR($A29)=2028,Raise_Pct_Apr2028,IF(YEAR($A29)=2029,Raise_Pct_Apr2029,IF(YEAR($A29)=2030,Raise_Pct_Apr2030,0))))),0)) -> 2121.8 | D29: =IF(OR($A29=DATE(2027,9,1),$A29=EDATE(DATE(2027,9,1),12),$A29=EDATE(DATE(2027,9,1),24)),(New_Hire_Stock_Grant_USD/3)/FX_USD_per_GBP*(1+IF(YEAR($A29)=2027,Inputs!$B$56,IF(YEAR($A29)=2028,Inputs!$B$57,IF(YEAR($A29)=2029,Inputs!$B$58,0)))),0)+IF(OR($A29=DATE(2028,11,1),$A29=DATE(2029,11,1),$A29=DATE(2030,11,1)),(RSU_Grant_Nov2027_USD/3)/FX_USD_per_GBP*(1+RSU_Price_Change_Pct)^(YEAR($A29)-2028),0)+IF(OR($A29=DATE(2029,11,1),$A29=DATE(2030,11,1)),(RSU_Grant_Nov2028_USD/3)/FX_USD_per_GBP*(1+RSU_Price_Change_Pct)^(YEAR($A29)-2029),0)+IF($A29=DATE(2030,11,1),(RSU_Grant_Nov2029_USD/3)/FX_USD_per_GBP*(1+RSU_Price_Change_Pct)^(YEAR($A29)-2030),0) -> 0 | E29: =IF($A29=EDATE(DATE(2026,8,1),Inputs!$B$9),Inputs!$B$8,0) -> 0 | F29: =IF($A29=EDATE(DATE(2026,8,1),Inputs!$B$11),Inputs!$B$10,0) -> 0 | G29: =IF(Inputs!$B$16=1,((IF(YEAR($A29)=2026,Inputs!$B$2,IF(YEAR($A29)=2027,IF(MONTH($A29)>=Inputs!#REF!,Inputs!$B$2*(1+Inputs!$B$4),Inputs!$B$2),IF(YEAR($A29)=2028,IF(MONTH($A29)>=Inputs!#REF!,Inputs!$B$2*(1+Inputs!$B$4)*(1+Inputs!$B$5),Inputs!$B$2*(1+Inputs!$B$4)),IF(YEAR($A29)=2029,IF(MONTH($A29)>=Inputs!#REF!,Inputs!$B$2*(1+Inputs!$B$4)*(1+Inputs!$B$5)*(1+Inputs!$B$6),Inputs!$B$2*(1+Inputs!$B$4)*(1+Inputs!$B$5)),IF(MONTH($A29)>=Inputs!#REF!,Inputs!$B$2*(1+Inputs!$B$4)*(1+Inputs!$B$5)*(1+Inputs!$B$6)*(1+Inputs!$B$7),Inputs!$B$2*(1+Inputs!$B$4)*(1+Inputs!$B$5)*(1+Inputs!$B$6)))))))/12)*(MIN(Inputs!$B$17,Inputs!$B$18)*(1+Inputs!$B$19)+Inputs!$B$17*Inputs!$B$20),0) -> 0 | H29: =SUM(B29:G29) -> 6674.8292 | I29: =$H29-J29-K29 -> 4751.2342 | J29: =_xlfn.SINGLE(_xlfn.LET(_xlpm.d, $A29, _xlpm.ys, YEAR(_xlfn.SINGLE(_xlpm.d)) - IF(MONTH(_xlfn.SINGLE(_xlpm.d)) < UK_TaxYear_Start_Month, 1, 0), _xlpm.start, DATE(_xlfn.SINGLE(_xlpm.ys), UK_TaxYear_Start_Month, 1), _xlpm.m, DATEDIF(_xlfn.SINGLE(_xlpm.start), _xlfn.SINGLE(_xlpm.d), "m") + 1, _xlpm.cum, SUMIFS($H$2:$H$54, $A$2:$A$54, ">=" & _xlfn.SINGLE(_xlpm.start), $A$2:$A$54, "<=" & _xlfn.SINGLE(_xlpm.d)), _xlpm.pa, UK_Personal_Allowance_Annual / 12 * _xlfn.SINGLE(_xlpm.m), _xlpm.br, (UK_Basic_Band_Upper_Annual - UK_Personal_Allowance_Annual) / 12 * _xlfn.SINGLE(_xlpm.m), _xlpm.hr, (UK_Higher_Band_Upper_Annual - UK_Basic_Band_Upper_Annual) / 12 * _xlfn.SINGLE(_xlpm.m), _xlpm.taxable, MAX(0, _xlfn.SINGLE(_xlpm.cum) - _xlfn.SINGLE(_xlpm.pa)), _xlpm.tax_to_date, UK_Basic_Rate * MIN(_xlpm.taxable, _xlpm.br) + UK_Higher_Rate * MIN(MAX(_xlfn.SINGLE(_xlpm.taxable) - _xlfn.SINGLE(_xlpm.br), 0), _xlpm.hr) + UK_Additional_Rate * MAX(_xlfn.SINGLE(_xlpm.taxable) - _xlfn.SINGLE(_xlpm.br) - _xlfn.SINGLE(_xlpm.hr), 0), _xlpm.prior, SUMIFS($J$2:$J$54, $A$2:$A$54, ">=" & _xlfn.SINGLE(_xlpm.start), $A$2:$A$54, "<" & _xlfn.SINGLE(_xlpm.d)), MAX(0, _xlfn.SINGLE(_xlpm.tax_to_date) - _xlfn.SINGLE(_xlpm.prior)))) -> 1622.5983 | K29: =_xlfn.SINGLE(_xlfn.LET(_xlpm.g, $H29, _xlpm.pt, UK_NI_PT_Monthly, _xlpm.uel, UK_NI_UEL_Monthly, IF(_xlfn.SINGLE(_xlpm.g) <= _xlfn.SINGLE(_xlpm.pt), 0, UK_NI_Main_Rate * MIN(_xlfn.SINGLE(_xlpm.g) - _xlfn.SINGLE(_xlpm.pt), _xlfn.SINGLE(_xlpm.uel) - _xlfn.SINGLE(_xlpm.pt)) + UK_NI_Upper_Rate * MAX(_xlfn.SINGLE(_xlpm.g) - _xlfn.SINGLE(_xlpm.uel), 0)))) -> 300.99658 | L29: =IF($A29<DATE(2026,10,1),Bonus_Pct_Aug2026_to_Sep2026,IF($A29<DATE(2027,10,1),Bonus_Pct_Oct2026_to_Sep2027,IF($A29<DATE(2028,10,1),Bonus_Pct_Oct2027_to_Sep2028,IF($A29<DATE(2029,10,1),Bonus_Pct_Oct2028_to_Sep2029,Bonus_Pct_Oct2029_onwards)))) -> 0.1
A30: 47088 | B30: =(IF(YEAR($A30)=2026,Base_Annual_Salary_GBP,IF(YEAR($A30)=2027,Base_Annual_Salary_GBP*(IF(MONTH($A30)>=4,(1+Raise_Pct_Apr2027),1)*IF(MONTH($A30)>=10,(1+Raise_Pct_Nov2027),1)),IF(YEAR($A30)=2028,Base_Annual_Salary_GBP*((1+Raise_Pct_Apr2027)*(1+Raise_Pct_Nov2027))*(IF(MONTH($A30)>=4,(1+Raise_Pct_Apr2028),1)*IF(MONTH($A30)>=10,(1+Raise_Pct_Nov2028),1)),IF(YEAR($A30)=2029,Base_Annual_Salary_GBP*((1+Raise_Pct_Apr2027)*(1+Raise_Pct_Nov2027)*(1+Raise_Pct_Apr2028)*(1+Raise_Pct_Nov2028))*(IF(MONTH($A30)>=4,(1+Raise_Pct_Apr2029),1)*IF(MONTH($A30)>=10,(1+Raise_Pct_Nov2029),1)),Base_Annual_Salary_GBP*((1+Raise_Pct_Apr2027)*(1+Raise_Pct_Nov2027)*(1+Raise_Pct_Apr2028)*(1+Raise_Pct_Nov2028)*(1+Raise_Pct_Apr2029)*(1+Raise_Pct_Nov2029))*(IF(MONTH($A30)>=4,(1+Raise_Pct_Apr2030),1)*IF(MONTH($A30)>=10,(1+Raise_Pct_Nov2030),1)))))))/12 -> 4553.0292 | C30: =IF(MONTH($A30)=11,((IF(DATE(YEAR($A30),4,1)<DATE(2026,10,1),Bonus_Pct_Aug2026_to_Sep2026,IF(DATE(YEAR($A30),4,1)<DATE(2027,10,1),Bonus_Pct_Oct2026_to_Sep2027,IF(DATE(YEAR($A30),4,1)<DATE(2028,10,1),Bonus_Pct_Oct2027_to_Sep2028,IF(DATE(YEAR($A30),4,1)<DATE(2029,10,1),Bonus_Pct_Oct2028_to_Sep2029,Bonus_Pct_Oct2029_onwards)))))/2)*($B30*12) / (1 + IF(YEAR($A30)=2027,Raise_Pct_Nov2027,IF(YEAR($A30)=2028,Raise_Pct_Nov2028,IF(YEAR($A30)=2029,Raise_Pct_Nov2029,IF(YEAR($A30)=2030,Raise_Pct_Nov2030,0))))) * IF(YEAR($A30)=2026,2/6,1),IF(MONTH($A30)=5,((IF(DATE(YEAR($A30)-1,10,1)<DATE(2026,10,1),Bonus_Pct_Aug2026_to_Sep2026,IF(DATE(YEAR($A30)-1,10,1)<DATE(2027,10,1),Bonus_Pct_Oct2026_to_Sep2027,IF(DATE(YEAR($A30)-1,10,1)<DATE(2028,10,1),Bonus_Pct_Oct2027_to_Sep2028,IF(DATE(YEAR($A30)-1,10,1)<DATE(2029,10,1),Bonus_Pct_Oct2028_to_Sep2029,Bonus_Pct_Oct2029_onwards)))))/2)*($B30*12) / (1 + IF(YEAR($A30)=2027,Raise_Pct_Apr2027,IF(YEAR($A30)=2028,Raise_Pct_Apr2028,IF(YEAR($A30)=2029,Raise_Pct_Apr2029,IF(YEAR($A30)=2030,Raise_Pct_Apr2030,0))))),0)) -> 0 | D30: =IF(OR($A30=DATE(2027,9,1),$A30=EDATE(DATE(2027,9,1),12),$A30=EDATE(DATE(2027,9,1),24)),(New_Hire_Stock_Grant_USD/3)/FX_USD_per_GBP*(1+IF(YEAR($A30)=2027,Inputs!$B$56,IF(YEAR($A30)=2028,Inputs!$B$57,IF(YEAR($A30)=2029,Inputs!$B$58,0)))),0)+IF(OR($A30=DATE(2028,11,1),$A30=DATE(2029,11,1),$A30=DATE(2030,11,1)),(RSU_Grant_Nov2027_USD/3)/FX_USD_per_GBP*(1+RSU_Price_Change_Pct)^(YEAR($A30)-2028),0)+IF(OR($A30=DATE(2029,11,1),$A30=DATE(2030,11,1)),(RSU_Grant_Nov2028_USD/3)/FX_USD_per_GBP*(1+RSU_Price_Change_Pct)^(YEAR($A30)-2029),0)+IF($A30=DATE(2030,11,1),(RSU_Grant_Nov2029_USD/3)/FX_USD_per_GBP*(1+RSU_Price_Change_Pct)^(YEAR($A30)-2030),0) -> 0 | E30: =IF($A30=EDATE(DATE(2026,8,1),Inputs!$B$9),Inputs!$B$8,0) -> 0 | F30: =IF($A30=EDATE(DATE(2026,8,1),Inputs!$B$11),Inputs!$B$10,0) -> 0 | G30: =IF(Inputs!$B$16=1,((IF(YEAR($A30)=2026,Inputs!$B$2,IF(YEAR($A30)=2027,IF(MONTH($A30)>=Inputs!#REF!,Inputs!$B$2*(1+Inputs!$B$4),Inputs!$B$2),IF(YEAR($A30)=2028,IF(MONTH($A30)>=Inputs!#REF!,Inputs!$B$2*(1+Inputs!$B$4)*(1+Inputs!$B$5),Inputs!$B$2*(1+Inputs!$B$4)),IF(YEAR($A30)=2029,IF(MONTH($A30)>=Inputs!#REF!,Inputs!$B$2*(1+Inputs!$B$4)*(1+Inputs!$B$5)*(1+Inputs!$B$6),Inputs!$B$2*(1+Inputs!$B$4)*(1+Inputs!$B$5)),IF(MONTH($A30)>=Inputs!#REF!,Inputs!$B$2*(1+Inputs!$B$4)*(1+Inputs!$B$5)*(1+Inputs!$B$6)*(1+Inputs!$B$7),Inputs!$B$2*(1+Inputs!$B$4)*(1+Inputs!$B$5)*(1+Inputs!$B$6)))))))/12)*(MIN(Inputs!$B$17,Inputs!$B$18)*(1+Inputs!$B$19)+Inputs!$B$17*Inputs!$B$20),0) -> 0 | H30: =SUM(B30:G30) -> 4553.0292 | I30: =$H30-J30-K30 -> 3520.5902 | J30: =_xlfn.SINGLE(_xlfn.LET(_xlpm.d, $A30, _xlpm.ys, YEAR(_xlfn.SINGLE(_xlpm.d)) - IF(MONTH(_xlfn.SINGLE(_xlpm.d)) < UK_TaxYear_Start_Month, 1, 0), _xlpm.start, DATE(_xlfn.SINGLE(_xlpm.ys), UK_TaxYear_Start_Month, 1), _xlpm.m, DATEDIF(_xlfn.SINGLE(_xlpm.start), _xlfn.SINGLE(_xlpm.d), "m") + 1, _xlpm.cum, SUMIFS($H$2:$H$54, $A$2:$A$54, ">=" & _xlfn.SINGLE(_xlpm.start), $A$2:$A$54, "<=" & _xlfn.SINGLE(_xlpm.d)), _xlpm.pa, UK_Personal_Allowance_Annual / 12 * _xlfn.SINGLE(_xlpm.m), _xlpm.br, (UK_Basic_Band_Upper_Annual - UK_Personal_Allowance_Annual) / 12 * _xlfn.SINGLE(_xlpm.m), _xlpm.hr, (UK_Higher_Band_Upper_Annual - UK_Basic_Band_Upper_Annual) / 12 * _xlfn.SINGLE(_xlpm.m), _xlpm.taxable, MAX(0, _xlfn.SINGLE(_xlpm.cum) - _xlfn.SINGLE(_xlpm.pa)), _xlpm.tax_to_date, UK_Basic_Rate * MIN(_xlpm.taxable, _xlpm.br) + UK_Higher_Rate * MIN(MAX(_xlfn.SINGLE(_xlpm.taxable) - _xlfn.SINGLE(_xlpm.br), 0), _xlpm.hr) + UK_Additional_Rate * MAX(_xlfn.SINGLE(_xlpm.taxable) - _xlfn.SINGLE(_xlpm.br) - _xlfn.SINGLE(_xlpm.hr), 0), _xlpm.prior, SUMIFS($J$2:$J$54, $A$2:$A$54, ">=" & _xlfn.SINGLE(_xlpm.start), $A$2:$A$54, "<" & _xlfn.SINGLE(_xlpm.d)), MAX(0, _xlfn.SINGLE(_xlpm.tax_to_date) - _xlfn.SINGLE(_xlpm.prior)))) -> 773.87833 | K30: =_xlfn.SINGLE(_xlfn.LET(_xlpm.g, $H30, _xlpm.pt, UK_NI_PT_Monthly, _xlpm.uel, UK_NI_UEL_Monthly, IF(_xlfn.SINGLE(_xlpm.g) <= _xlfn.SINGLE(_xlpm.pt), 0, UK_NI_Main_Rate * MIN(_xlfn.SINGLE(_xlpm.g) - _xlfn.SINGLE(_xlpm.pt), _xlfn.SINGLE(_xlpm.uel) - _xlfn.SINGLE(_xlpm.pt)) + UK_NI_Upper_Rate * MAX(_xlfn.SINGLE(_xlpm.g) - _xlfn.SINGLE(_xlpm.uel), 0)))) -> 258.56058 | L30: =IF($A30<DATE(2026,10,1),Bonus_Pct_Aug2026_to_Sep2026,IF($A30<DATE(2027,10,1),Bonus_Pct_Oct2026_to_Sep2027,IF($A30<DATE(2028,10,1),Bonus_Pct_Oct2027_to_Sep2028,IF($A30<DATE(2029,10,1),Bonus_Pct_Oct2028_to_Sep2029,Bonus_Pct_Oct2029_onwards)))) -> 0.1
A31: 47119 | B31: =(IF(YEAR($A31)=2026,Base_Annual_Salary_GBP,IF(YEAR($A31)=2027,Base_Annual_Salary_GBP*(IF(MONTH($A31)>=4,(1+Raise_Pct_Apr2027),1)*IF(MONTH($A31)>=10,(1+Raise_Pct_Nov2027),1)),IF(YEAR($A31)=2028,Base_Annual_Salary_GBP*((1+Raise_Pct_Apr2027)*(1+Raise_Pct_Nov2027))*(IF(MONTH($A31)>=4,(1+Raise_Pct_Apr2028),1)*IF(MONTH($A31)>=10,(1+Raise_Pct_Nov2028),1)),IF(YEAR($A31)=2029,Base_Annual_Salary_GBP*((1+Raise_Pct_Apr2027)*(1+Raise_Pct_Nov2027)*(1+Raise_Pct_Apr2028)*(1+Raise_Pct_Nov2028))*(IF(MONTH($A31)>=4,(1+Raise_Pct_Apr2029),1)*IF(MONTH($A31)>=10,(1+Raise_Pct_Nov2029),1)),Base_Annual_Salary_GBP*((1+Raise_Pct_Apr2027)*(1+Raise_Pct_Nov2027)*(1+Raise_Pct_Apr2028)*(1+Raise_Pct_Nov2028)*(1+Raise_Pct_Apr2029)*(1+Raise_Pct_Nov2029))*(IF(MONTH($A31)>=4,(1+Raise_Pct_Apr2030),1)*IF(MONTH($A31)>=10,(1+Raise_Pct_Nov2030),1)))))))/12 -> 4553.0292 | C31: =IF(MONTH($A31)=11,((IF(DATE(YEAR($A31),4,1)<DATE(2026,10,1),Bonus_Pct_Aug2026_to_Sep2026,IF(DATE(YEAR($A31),4,1)<DATE(2027,10,1),Bonus_Pct_Oct2026_to_Sep2027,IF(DATE(YEAR($A31),4,1)<DATE(2028,10,1),Bonus_Pct_Oct2027_to_Sep2028,IF(DATE(YEAR($A31),4,1)<DATE(2029,10,1),Bonus_Pct_Oct2028_to_Sep2029,Bonus_Pct_Oct2029_onwards)))))/2)*($B31*12) / (1 + IF(YEAR($A31)=2027,Raise_Pct_Nov2027,IF(YEAR($A31)=2028,Raise_Pct_Nov2028,IF(YEAR($A31)=2029,Raise_Pct_Nov2029,IF(YEAR($A31)=2030,Raise_Pct_Nov2030,0))))) * IF(YEAR($A31)=2026,2/6,1),IF(MONTH($A31)=5,((IF(DATE(YEAR($A31)-1,10,1)<DATE(2026,10,1),Bonus_Pct_Aug2026_to_Sep2026,IF(DATE(YEAR($A31)-1,10,1)<DATE(2027,10,1),Bonus_Pct_Oct2026_to_Sep2027,IF(DATE(YEAR($A31)-1,10,1)<DATE(2028,10,1),Bonus_Pct_Oct2027_to_Sep2028,IF(DATE(YEAR($A31)-1,10,1)<DATE(2029,10,1),Bonus_Pct_Oct2028_to_Sep2029,Bonus_Pct_Oct2029_onwards)))))/2)*($B31*12) / (1 + IF(YEAR($A31)=2027,Raise_Pct_Apr2027,IF(YEAR($A31)=2028,Raise_Pct_Apr2028,IF(YEAR($A31)=2029,Raise_Pct_Apr2029,IF(YEAR($A31)=2030,Raise_Pct_Apr2030,0))))),0)) -> 0 | D31: =IF(OR($A31=DATE(2027,9,1),$A31=EDATE(DATE(2027,9,1),12),$A31=EDATE(DATE(2027,9,1),24)),(New_Hire_Stock_Grant_USD/3)/FX_USD_per_GBP*(1+IF(YEAR($A31)=2027,Inputs!$B$56,IF(YEAR($A31)=2028,Inputs!$B$57,IF(YEAR($A31)=2029,Inputs!$B$58,0)))),0)+IF(OR($A31=DATE(2028,11,1),$A31=DATE(2029,11,1),$A31=DATE(2030,11,1)),(RSU_Grant_Nov2027_USD/3)/FX_USD_per_GBP*(1+RSU_Price_Change_Pct)^(YEAR($A31)-2028),0)+IF(OR($A31=DATE(2029,11,1),$A31=DATE(2030,11,1)),(RSU_Grant_Nov2028_USD/3)/FX_USD_per_GBP*(1+RSU_Price_Change_Pct)^(YEAR($A31)-2029),0)+IF($A31=DATE(2030,11,1),(RSU_Grant_Nov2029_USD/3)/FX_USD_per_GBP*(1+RSU_Price_Change_Pct)^(YEAR($A31)-2030),0) -> 0 | E31: =IF($A31=EDATE(DATE(2026,8,1),Inputs!$B$9),Inputs!$B$8,0) -> 0 | F31: =IF($A31=EDATE(DATE(2026,8,1),Inputs!$B$11),Inputs!$B$10,0) -> 0 | G31: =IF(Inputs!$B$16=1,((IF(YEAR($A31)=2026,Inputs!$B$2,IF(YEAR($A31)=2027,IF(MONTH($A31)>=Inputs!#REF!,Inputs!$B$2*(1+Inputs!$B$4),Inputs!$B$2),IF(YEAR($A31)=2028,IF(MONTH($A31)>=Inputs!#REF!,Inputs!$B$2*(1+Inputs!$B$4)*(1+Inputs!$B$5),Inputs!$B$2*(1+Inputs!$B$4)),IF(YEAR($A31)=2029,IF(MONTH($A31)>=Inputs!#REF!,Inputs!$B$2*(1+Inputs!$B$4)*(1+Inputs!$B$5)*(1+Inputs!$B$6),Inputs!$B$2*(1+Inputs!$B$4)*(1+Inputs!$B$5)),IF(MONTH($A31)>=Inputs!#REF!,Inputs!$B$2*(1+Inputs!$B$4)*(1+Inputs!$B$5)*(1+Inputs!$B$6)*(1+Inputs!$B$7),Inputs!$B$2*(1+Inputs!$B$4)*(1+Inputs!$B$5)*(1+Inputs!$B$6)))))))/12)*(MIN(Inputs!$B$17,Inputs!$B$18)*(1+Inputs!$B$19)+Inputs!$B$17*Inputs!$B$20),0) -> 0 | H31: =SUM(B31:G31) -> 4553.0292 | I31: =$H31-J31-K31 -> 3520.5902 | J31: =_xlfn.SINGLE(_xlfn.LET(_xlpm.d, $A31, _xlpm.ys, YEAR(_xlfn.SINGLE(_xlpm.d)) - IF(MONTH(_xlfn.SINGLE(_xlpm.d)) < UK_TaxYear_Start_Month, 1, 0), _xlpm.start, DATE(_xlfn.SINGLE(_xlpm.ys), UK_TaxYear_Start_Month, 1), _xlpm.m, DATEDIF(_xlfn.SINGLE(_xlpm.start), _xlfn.SINGLE(_xlpm.d), "m") + 1, _xlpm.cum, SUMIFS($H$2:$H$54, $A$2:$A$54, ">=" & _xlfn.SINGLE(_xlpm.start), $A$2:$A$54, "<=" & _xlfn.SINGLE(_xlpm.d)), _xlpm.pa, UK_Personal_Allowance_Annual / 12 * _xlfn.SINGLE(_xlpm.m), _xlpm.br, (UK_Basic_Band_Upper_Annual - UK_Personal_Allowance_Annual) / 12 * _xlfn.SINGLE(_xlpm.m), _xlpm.hr, (UK_Higher_Band_Upper_Annual - UK_Basic_Band_Upper_Annual) / 12 * _xlfn.SINGLE(_xlpm.m), _xlpm.taxable, MAX(0, _xlfn.SINGLE(_xlpm.cum) - _xlfn.SINGLE(_xlpm.pa)), _xlpm.tax_to_date, UK_Basic_Rate * MIN(_xlpm.taxable, _xlpm.br) + UK_Higher_Rate * MIN(MAX(_xlfn.SINGLE(_xlpm.taxable) - _xlfn.SINGLE(_xlpm.br), 0), _xlpm.hr) + UK_Additional_Rate * MAX(_xlfn.SINGLE(_xlpm.taxable) - _xlfn.SINGLE(_xlpm.br) - _xlfn.SINGLE(_xlpm.hr), 0), _xlpm.prior, SUMIFS($J$2:$J$54, $A$2:$A$54, ">=" & _xlfn.SINGLE(_xlpm.start), $A$2:$A$54, "<" & _xlfn.SINGLE(_xlpm.d)), MAX(0, _xlfn.SINGLE(_xlpm.tax_to_date) - _xlfn.SINGLE(_xlpm.prior)))) -> 773.87833 | K31: =_xlfn.SINGLE(_xlfn.LET(_xlpm.g, $H31, _xlpm.pt, UK_NI_PT_Monthly, _xlpm.uel, UK_NI_UEL_Monthly, IF(_xlfn.SINGLE(_xlpm.g) <= _xlfn.SINGLE(_xlpm.pt), 0, UK_NI_Main_Rate * MIN(_xlfn.SINGLE(_xlpm.g) - _xlfn.SINGLE(_xlpm.pt), _xlfn.SINGLE(_xlpm.uel) - _xlfn.SINGLE(_xlpm.pt)) + UK_NI_Upper_Rate * MAX(_xlfn.SINGLE(_xlpm.g) - _xlfn.SINGLE(_xlpm.uel), 0)))) -> 258.56058 | L31: =IF($A31<DATE(2026,10,1),Bonus_Pct_Aug2026_to_Sep2026,IF($A31<DATE(2027,10,1),Bonus_Pct_Oct2026_to_Sep2027,IF($A31<DATE(2028,10,1),Bonus_Pct_Oct2027_to_Sep2028,IF($A31<DATE(2029,10,1),Bonus_Pct_Oct2028_to_Sep2029,Bonus_Pct_Oct2029_onwards)))) -> 0.1
A32: 47150 | B32: =(IF(YEAR($A32)=2026,Base_Annual_Salary_GBP,IF(YEAR($A32)=2027,Base_Annual_Salary_GBP*(IF(MONTH($A32)>=4,(1+Raise_Pct_Apr2027),1)*IF(MONTH($A32)>=10,(1+Raise_Pct_Nov2027),1)),IF(YEAR($A32)=2028,Base_Annual_Salary_GBP*((1+Raise_Pct_Apr2027)*(1+Raise_Pct_Nov2027))*(IF(MONTH($A32)>=4,(1+Raise_Pct_Apr2028),1)*IF(MONTH($A32)>=10,(1+Raise_Pct_Nov2028),1)),IF(YEAR($A32)=2029,Base_Annual_Salary_GBP*((1+Raise_Pct_Apr2027)*(1+Raise_Pct_Nov2027)*(1+Raise_Pct_Apr2028)*(1+Raise_Pct_Nov2028))*(IF(MONTH($A32)>=4,(1+Raise_Pct_Apr2029),1)*IF(MONTH($A32)>=10,(1+Raise_Pct_Nov2029),1)),Base_Annual_Salary_GBP*((1+Raise_Pct_Apr2027)*(1+Raise_Pct_Nov2027)*(1+Raise_Pct_Apr2028)*(1+Raise_Pct_Nov2028)*(1+Raise_Pct_Apr2029)*(1+Raise_Pct_Nov2029))*(IF(MONTH($A32)>=4,(1+Raise_Pct_Apr2030),1)*IF(MONTH($A32)>=10,(1+Raise_Pct_Nov2030),1)))))))/12 -> 4553.0292 | C32: =IF(MONTH($A32)=11,((IF(DATE(YEAR($A32),4,1)<DATE(2026,10,1),Bonus_Pct_Aug2026_to_Sep2026,IF(DATE(YEAR($A32),4,1)<DATE(2027,10,1),Bonus_Pct_Oct2026_to_Sep2027,IF(DATE(YEAR($A32),4,1)<DATE(2028,10,1),Bonus_Pct_Oct2027_to_Sep2028,IF(DATE(YEAR($A32),4,1)<DATE(2029,10,1),Bonus_Pct_Oct2028_to_Sep2029,Bonus_Pct_Oct2029_onwards)))))/2)*($B32*12) / (1 + IF(YEAR($A32)=2027,Raise_Pct_Nov2027,IF(YEAR($A32)=2028,Raise_Pct_Nov2028,IF(YEAR($A32)=2029,Raise_Pct_Nov2029,IF(YEAR($A32)=2030,Raise_Pct_Nov2030,0))))) * IF(YEAR($A32)=2026,2/6,1),IF(MONTH($A32)=5,((IF(DATE(YEAR($A32)-1,10,1)<DATE(2026,10,1),Bonus_Pct_Aug2026_to_Sep2026,IF(DATE(YEAR($A32)-1,10,1)<DATE(2027,10,1),Bonus_Pct_Oct2026_to_Sep2027,IF(DATE(YEAR($A32)-1,10,1)<DATE(2028,10,1),Bonus_Pct_Oct2027_to_Sep2028,IF(DATE(YEAR($A32)-1,10,1)<DATE(2029,10,1),Bonus_Pct_Oct2028_to_Sep2029,Bonus_Pct_Oct2029_onwards)))))/2)*($B32*12) / (1 + IF(YEAR($A32)=2027,Raise_Pct_Apr2027,IF(YEAR($A32)=2028,Raise_Pct_Apr2028,IF(YEAR($A32)=2029,Raise_Pct_Apr2029,IF(YEAR($A32)=2030,Raise_Pct_Apr2030,0))))),0)) -> 0 | D32: =IF(OR($A32=DATE(2027,9,1),$A32=EDATE(DATE(2027,9,1),12),$A32=EDATE(DATE(2027,9,1),24)),(New_Hire_Stock_Grant_USD/3)/FX_USD_per_GBP*(1+IF(YEAR($A32)=2027,Inputs!$B$56,IF(YEAR($A32)=2028,Inputs!$B$57,IF(YEAR($A32)=2029,Inputs!$B$58,0)))),0)+IF(OR($A32=DATE(2028,11,1),$A32=DATE(2029,11,1),$A32=DATE(2030,11,1)),(RSU_Grant_Nov2027_USD/3)/FX_USD_per_GBP*(1+RSU_Price_Change_Pct)^(YEAR($A32)-2028),0)+IF(OR($A32=DATE(2029,11,1),$A32=DATE(2030,11,1)),(RSU_Grant_Nov2028_USD/3)/FX_USD_per_GBP*(1+RSU_Price_Change_Pct)^(YEAR($A32)-2029),0)+IF($A32=DATE(2030,11,1),(RSU_Grant_Nov2029_USD/3)/FX_USD_per_GBP*(1+RSU_Price_Change_Pct)^(YEAR($A32)-2030),0) -> 0 | E32: =IF($A32=EDATE(DATE(2026,8,1),Inputs!$B$9),Inputs!$B$8,0) -> 0 | F32: =IF($A32=EDATE(DATE(2026,8,1),Inputs!$B$11),Inputs!$B$10,0) -> 0 | G32: =IF(Inputs!$B$16=1,((IF(YEAR($A32)=2026,Inputs!$B$2,IF(YEAR($A32)=2027,IF(MONTH($A32)>=Inputs!#REF!,Inputs!$B$2*(1+Inputs!$B$4),Inputs!$B$2),IF(YEAR($A32)=2028,IF(MONTH($A32)>=Inputs!#REF!,Inputs!$B$2*(1+Inputs!$B$4)*(1+Inputs!$B$5),Inputs!$B$2*(1+Inputs!$B$4)),IF(YEAR($A32)=2029,IF(MONTH($A32)>=Inputs!#REF!,Inputs!$B$2*(1+Inputs!$B$4)*(1+Inputs!$B$5)*(1+Inputs!$B$6),Inputs!$B$2*(1+Inputs!$B$4)*(1+Inputs!$B$5)),IF(MONTH($A32)>=Inputs!#REF!,Inputs!$B$2*(1+Inputs!$B$4)*(1+Inputs!$B$5)*(1+Inputs!$B$6)*(1+Inputs!$B$7),Inputs!$B$2*(1+Inputs!$B$4)*(1+Inputs!$B$5)*(1+Inputs!$B$6)))))))/12)*(MIN(Inputs!$B$17,Inputs!$B$18)*(1+Inputs!$B$19)+Inputs!$B$17*Inputs!$B$20),0) -> 0 | H32: =SUM(B32:G32) -> 4553.0292 | I32: =$H32-J32-K32 -> 3520.5902 | J32: =_xlfn.SINGLE(_xlfn.LET(_xlpm.d, $A32, _xlpm.ys, YEAR(_xlfn.SINGLE(_xlpm.d)) - IF(MONTH(_xlfn.SINGLE(_xlpm.d)) < UK_TaxYear_Start_Month, 1, 0), _xlpm.start, DATE(_xlfn.SINGLE(_xlpm.ys), UK_TaxYear_Start_Month, 1), _xlpm.m, DATEDIF(_xlfn.SINGLE(_xlpm.start), _xlfn.SINGLE(_xlpm.d), "m") + 1, _xlpm.cum, SUMIFS($H$2:$H$54, $A$2:$A$54, ">=" & _xlfn.SINGLE(_xlpm.start), $A$2:$A$54, "<=" & _xlfn.SINGLE(_xlpm.d)), _xlpm.pa, UK_Personal_Allowance_Annual / 12 * _xlfn.SINGLE(_xlpm.m), _xlpm.br, (UK_Basic_Band_Upper_Annual - UK_Personal_Allowance_Annual) / 12 * _xlfn.SINGLE(_xlpm.m), _xlpm.hr, (UK_Higher_Band_Upper_Annual - UK_Basic_Band_Upper_Annual) / 12 * _xlfn.SINGLE(_xlpm.m), _xlpm.taxable, MAX(0, _xlfn.SINGLE(_xlpm.cum) - _xlfn.SINGLE(_xlpm.pa)), _xlpm.tax_to_date, UK_Basic_Rate * MIN(_xlpm.taxable, _xlpm.br) + UK_Higher_Rate * MIN(MAX(_xlfn.SINGLE(_xlpm.taxable) - _xlfn.SINGLE(_xlpm.br), 0), _xlpm.hr) + UK_Additional_Rate * MAX(_xlfn.SINGLE(_xlpm.taxable) - _xlfn.SINGLE(_xlpm.br) - _xlfn.SINGLE(_xlpm.hr), 0), _xlpm.prior, SUMIFS($J$2:$J$54, $A$2:$A$54, ">=" & _xlfn.SINGLE(_xlpm.start), $A$2:$A$54, "<" & _xlfn.SINGLE(_xlpm.d)), MAX(0, _xlfn.SINGLE(_xlpm.tax_to_date) - _xlfn.SINGLE(_xlpm.prior)))) -> 773.87833 | K32: =_xlfn.SINGLE(_xlfn.LET(_xlpm.g, $H32, _xlpm.pt, UK_NI_PT_Monthly, _xlpm.uel, UK_NI_UEL_Monthly, IF(_xlfn.SINGLE(_xlpm.g) <= _xlfn.SINGLE(_xlpm.pt), 0, UK_NI_Main_Rate * MIN(_xlfn.SINGLE(_xlpm.g) - _xlfn.SINGLE(_xlpm.pt), _xlfn.SINGLE(_xlpm.uel) - _xlfn.SINGLE(_xlpm.pt)) + UK_NI_Upper_Rate * MAX(_xlfn.SINGLE(_xlpm.g) - _xlfn.SINGLE(_xlpm.uel), 0)))) -> 258.56058 | L32: =IF($A32<DATE(2026,10,1),Bonus_Pct_Aug2026_to_Sep2026,IF($A32<DATE(2027,10,1),Bonus_Pct_Oct2026_to_Sep2027,IF($A32<DATE(2028,10,1),Bonus_Pct_Oct2027_to_Sep2028,IF($A32<DATE(2029,10,1),Bonus_Pct_Oct2028_to_Sep2029,Bonus_Pct_Oct2029_onwards)))) -> 0.1
A33: 47178 | B33: =(IF(YEAR($A33)=2026,Base_Annual_Salary_GBP,IF(YEAR($A33)=2027,Base_Annual_Salary_GBP*(IF(MONTH($A33)>=4,(1+Raise_Pct_Apr2027),1)*IF(MONTH($A33)>=10,(1+Raise_Pct_Nov2027),1)),IF(YEAR($A33)=2028,Base_Annual_Salary_GBP*((1+Raise_Pct_Apr2027)*(1+Raise_Pct_Nov2027))*(IF(MONTH($A33)>=4,(1+Raise_Pct_Apr2028),1)*IF(MONTH($A33)>=10,(1+Raise_Pct_Nov2028),1)),IF(YEAR($A33)=2029,Base_Annual_Salary_GBP*((1+Raise_Pct_Apr2027)*(1+Raise_Pct_Nov2027)*(1+Raise_Pct_Apr2028)*(1+Raise_Pct_Nov2028))*(IF(MONTH($A33)>=4,(1+Raise_Pct_Apr2029),1)*IF(MONTH($A33)>=10,(1+Raise_Pct_Nov2029),1)),Base_Annual_Salary_GBP*((1+Raise_Pct_Apr2027)*(1+Raise_Pct_Nov2027)*(1+Raise_Pct_Apr2028)*(1+Raise_Pct_Nov2028)*(1+Raise_Pct_Apr2029)*(1+Raise_Pct_Nov2029))*(IF(MONTH($A33)>=4,(1+Raise_Pct_Apr2030),1)*IF(MONTH($A33)>=10,(1+Raise_Pct_Nov2030),1)))))))/12 -> 4553.0292 | C33: =IF(MONTH($A33)=11,((IF(DATE(YEAR($A33),4,1)<DATE(2026,10,1),Bonus_Pct_Aug2026_to_Sep2026,IF(DATE(YEAR($A33),4,1)<DATE(2027,10,1),Bonus_Pct_Oct2026_to_Sep2027,IF(DATE(YEAR($A33),4,1)<DATE(2028,10,1),Bonus_Pct_Oct2027_to_Sep2028,IF(DATE(YEAR($A33),4,1)<DATE(2029,10,1),Bonus_Pct_Oct2028_to_Sep2029,Bonus_Pct_Oct2029_onwards)))))/2)*($B33*12) / (1 + IF(YEAR($A33)=2027,Raise_Pct_Nov2027,IF(YEAR($A33)=2028,Raise_Pct_Nov2028,IF(YEAR($A33)=2029,Raise_Pct_Nov2029,IF(YEAR($A33)=2030,Raise_Pct_Nov2030,0))))) * IF(YEAR($A33)=2026,2/6,1),IF(MONTH($A33)=5,((IF(DATE(YEAR($A33)-1,10,1)<DATE(2026,10,1),Bonus_Pct_Aug2026_to_Sep2026,IF(DATE(YEAR($A33)-1,10,1)<DATE(2027,10,1),Bonus_Pct_Oct2026_to_Sep2027,IF(DATE(YEAR($A33)-1,10,1)<DATE(2028,10,1),Bonus_Pct_Oct2027_to_Sep2028,IF(DATE(YEAR($A33)-1,10,1)<DATE(2029,10,1),Bonus_Pct_Oct2028_to_Sep2029,Bonus_Pct_Oct2029_onwards)))))/2)*($B33*12) / (1 + IF(YEAR($A33)=2027,Raise_Pct_Apr2027,IF(YEAR($A33)=2028,Raise_Pct_Apr2028,IF(YEAR($A33)=2029,Raise_Pct_Apr2029,IF(YEAR($A33)=2030,Raise_Pct_Apr2030,0))))),0)) -> 0 | D33: =IF(OR($A33=DATE(2027,9,1),$A33=EDATE(DATE(2027,9,1),12),$A33=EDATE(DATE(2027,9,1),24)),(New_Hire_Stock_Grant_USD/3)/FX_USD_per_GBP*(1+IF(YEAR($A33)=2027,Inputs!$B$56,IF(YEAR($A33)=2028,Inputs!$B$57,IF(YEAR($A33)=2029,Inputs!$B$58,0)))),0)+IF(OR($A33=DATE(2028,11,1),$A33=DATE(2029,11,1),$A33=DATE(2030,11,1)),(RSU_Grant_Nov2027_USD/3)/FX_USD_per_GBP*(1+RSU_Price_Change_Pct)^(YEAR($A33)-2028),0)+IF(OR($A33=DATE(2029,11,1),$A33=DATE(2030,11,1)),(RSU_Grant_Nov2028_USD/3)/FX_USD_per_GBP*(1+RSU_Price_Change_Pct)^(YEAR($A33)-2029),0)+IF($A33=DATE(2030,11,1),(RSU_Grant_Nov2029_USD/3)/FX_USD_per_GBP*(1+RSU_Price_Change_Pct)^(YEAR($A33)-2030),0) -> 0 | E33: =IF($A33=EDATE(DATE(2026,8,1),Inputs!$B$9),Inputs!$B$8,0) -> 0 | F33: =IF($A33=EDATE(DATE(2026,8,1),Inputs!$B$11),Inputs!$B$10,0) -> 0 | G33: =IF(Inputs!$B$16=1,((IF(YEAR($A33)=2026,Inputs!$B$2,IF(YEAR($A33)=2027,IF(MONTH($A33)>=Inputs!#REF!,Inputs!$B$2*(1+Inputs!$B$4),Inputs!$B$2),IF(YEAR($A33)=2028,IF(MONTH($A33)>=Inputs!#REF!,Inputs!$B$2*(1+Inputs!$B$4)*(1+Inputs!$B$5),Inputs!$B$2*(1+Inputs!$B$4)),IF(YEAR($A33)=2029,IF(MONTH($A33)>=Inputs!#REF!,Inputs!$B$2*(1+Inputs!$B$4)*(1+Inputs!$B$5)*(1+Inputs!$B$6),Inputs!$B$2*(1+Inputs!$B$4)*(1+Inputs!$B$5)),IF(MONTH($A33)>=Inputs!#REF!,Inputs!$B$2*(1+Inputs!$B$4)*(1+Inputs!$B$5)*(1+Inputs!$B$6)*(1+Inputs!$B$7),Inputs!$B$2*(1+Inputs!$B$4)*(1+Inputs!$B$5)*(1+Inputs!$B$6)))))))/12)*(MIN(Inputs!$B$17,Inputs!$B$18)*(1+Inputs!$B$19)+Inputs!$B$17*Inputs!$B$20),0) -> 0 | H33: =SUM(B33:G33) -> 4553.0292 | I33: =$H33-J33-K33 -> 3520.5903 | J33: =_xlfn.SINGLE(_xlfn.LET(_xlpm.d, $A33, _xlpm.ys, YEAR(_xlfn.SINGLE(_xlpm.d)) - IF(MONTH(_xlfn.SINGLE(_xlpm.d)) < UK_TaxYear_Start_Month, 1, 0), _xlpm.start, DATE(_xlfn.SINGLE(_xlpm.ys), UK_TaxYear_Start_Month, 1), _xlpm.m, DATEDIF(_xlfn.SINGLE(_xlpm.start), _xlfn.SINGLE(_xlpm.d), "m") + 1, _xlpm.cum, SUMIFS($H$2:$H$54, $A$2:$A$54, ">=" & _xlfn.SINGLE(_xlpm.start), $A$2:$A$54, "<=" & _xlfn.SINGLE(_xlpm.d)), _xlpm.pa, UK_Personal_Allowance_Annual / 12 * _xlfn.SINGLE(_xlpm.m), _xlpm.br, (UK_Basic_Band_Upper_Annual - UK_Personal_Allowance_Annual) / 12 * _xlfn.SINGLE(_xlpm.m), _xlpm.hr, (UK_Higher_Band_Upper_Annual - UK_Basic_Band_Upper_Annual) / 12 * _xlfn.SINGLE(_xlpm.m), _xlpm.taxable, MAX(0, _xlfn.SINGLE(_xlpm.cum) - _xlfn.SINGLE(_xlpm.pa)), _xlpm.tax_to_date, UK_Basic_Rate * MIN(_xlpm.taxable, _xlpm.br) + UK_Higher_Rate * MIN(MAX(_xlfn.SINGLE(_xlpm.taxable) - _xlfn.SINGLE(_xlpm.br), 0), _xlpm.hr) + UK_Additional_Rate * MAX(_xlfn.SINGLE(_xlpm.taxable) - _xlfn.SINGLE(_xlpm.br) - _xlfn.SINGLE(_xlpm.hr), 0), _xlpm.prior, SUMIFS($J$2:$J$54, $A$2:$A$54, ">=" & _xlfn.SINGLE(_xlpm.start), $A$2:$A$54, "<" & _xlfn.SINGLE(_xlpm.d)), MAX(0, _xlfn.SINGLE(_xlpm.tax_to_date) - _xlfn.SINGLE(_xlpm.prior)))) -> 773.87833 | K33: =_xlfn.SINGLE(_xlfn.LET(_xlpm.g, $H33, _xlpm.pt, UK_NI_PT_Monthly, _xlpm.uel, UK_NI_UEL_Monthly, IF(_xlfn.SINGLE(_xlpm.g) <= _xlfn.SINGLE(_xlpm.pt), 0, UK_NI_Main_Rate * MIN(_xlfn.SINGLE(_xlpm.g) - _xlfn.SINGLE(_xlpm.pt), _xlfn.SINGLE(_xlpm.uel) - _xlfn.SINGLE(_xlpm.pt)) + UK_NI_Upper_Rate * MAX(_xlfn.SINGLE(_xlpm.g) - _xlfn.SINGLE(_xlpm.uel), 0)))) -> 258.56058 | L33: =IF($A33<DATE(2026,10,1),Bonus_Pct_Aug2026_to_Sep2026,IF($A33<DATE(2027,10,1),Bonus_Pct_Oct2026_to_Sep2027,IF($A33<DATE(2028,10,1),Bonus_Pct_Oct2027_to_Sep2028,IF($A33<DATE(2029,10,1),Bonus_Pct_Oct2028_to_Sep2029,Bonus_Pct_Oct2029_onwards)))) -> 0.1
A34: 47209 | B34: =(IF(YEAR($A34)=2026,Base_Annual_Salary_GBP,IF(YEAR($A34)=2027,Base_Annual_Salary_GBP*(IF(MONTH($A34)>=4,(1+Raise_Pct_Apr2027),1)*IF(MONTH($A34)>=10,(1+Raise_Pct_Nov2027),1)),IF(YEAR($A34)=2028,Base_Annual_Salary_GBP*((1+Raise_Pct_Apr2027)*(1+Raise_Pct_Nov2027))*(IF(MONTH($A34)>=4,(1+Raise_Pct_Apr2028),1)*IF(MONTH($A34)>=10,(1+Raise_Pct_Nov2028),1)),IF(YEAR($A34)=2029,Base_Annual_Salary_GBP*((1+Raise_Pct_Apr2027)*(1+Raise_Pct_Nov2027)*(1+Raise_Pct_Apr2028)*(1+Raise_Pct_Nov2028))*(IF(MONTH($A34)>=4,(1+Raise_Pct_Apr2029),1)*IF(MONTH($A34)>=10,(1+Raise_Pct_Nov2029),1)),Base_Annual_Salary_GBP*((1+Raise_Pct_Apr2027)*(1+Raise_Pct_Nov2027)*(1+Raise_Pct_Apr2028)*(1+Raise_Pct_Nov2028)*(1+Raise_Pct_Apr2029)*(1+Raise_Pct_Nov2029))*(IF(MONTH($A34)>=4,(1+Raise_Pct_Apr2030),1)*IF(MONTH($A34)>=10,(1+Raise_Pct_Nov2030),1)))))))/12 -> 4689.62 | C34: =IF(MONTH($A34)=11,((IF(DATE(YEAR($A34),4,1)<DATE(2026,10,1),Bonus_Pct_Aug2026_to_Sep2026,IF(DATE(YEAR($A34),4,1)<DATE(2027,10,1),Bonus_Pct_Oct2026_to_Sep2027,IF(DATE(YEAR($A34),4,1)<DATE(2028,10,1),Bonus_Pct_Oct2027_to_Sep2028,IF(DATE(YEAR($A34),4,1)<DATE(2029,10,1),Bonus_Pct_Oct2028_to_Sep2029,Bonus_Pct_Oct2029_onwards)))))/2)*($B34*12) / (1 + IF(YEAR($A34)=2027,Raise_Pct_Nov2027,IF(YEAR($A34)=2028,Raise_Pct_Nov2028,IF(YEAR($A34)=2029,Raise_Pct_Nov2029,IF(YEAR($A34)=2030,Raise_Pct_Nov2030,0))))) * IF(YEAR($A34)=2026,2/6,1),IF(MONTH($A34)=5,((IF(DATE(YEAR($A34)-1,10,1)<DATE(2026,10,1),Bonus_Pct_Aug2026_to_Sep2026,IF(DATE(YEAR($A34)-1,10,1)<DATE(2027,10,1),Bonus_Pct_Oct2026_to_Sep2027,IF(DATE(YEAR($A34)-1,10,1)<DATE(2028,10,1),Bonus_Pct_Oct2027_to_Sep2028,IF(DATE(YEAR($A34)-1,10,1)<DATE(2029,10,1),Bonus_Pct_Oct2028_to_Sep2029,Bonus_Pct_Oct2029_onwards)))))/2)*($B34*12) / (1 + IF(YEAR($A34)=2027,Raise_Pct_Apr2027,IF(YEAR($A34)=2028,Raise_Pct_Apr2028,IF(YEAR($A34)=2029,Raise_Pct_Apr2029,IF(YEAR($A34)=2030,Raise_Pct_Apr2030,0))))),0)) -> 0 | D34: =IF(OR($A34=DATE(2027,9,1),$A34=EDATE(DATE(2027,9,1),12),$A34=EDATE(DATE(2027,9,1),24)),(New_Hire_Stock_Grant_USD/3)/FX_USD_per_GBP*(1+IF(YEAR($A34)=2027,Inputs!$B$56,IF(YEAR($A34)=2028,Inputs!$B$57,IF(YEAR($A34)=2029,Inputs!$B$58,0)))),0)+IF(OR($A34=DATE(2028,11,1),$A34=DATE(2029,11,1),$A34=DATE(2030,11,1)),(RSU_Grant_Nov2027_USD/3)/FX_USD_per_GBP*(1+RSU_Price_Change_Pct)^(YEAR($A34)-2028),0)+IF(OR($A34=DATE(2029,11,1),$A34=DATE(2030,11,1)),(RSU_Grant_Nov2028_USD/3)/FX_USD_per_GBP*(1+RSU_Price_Change_Pct)^(YEAR($A34)-2029),0)+IF($A34=DATE(2030,11,1),(RSU_Grant_Nov2029_USD/3)/FX_USD_per_GBP*(1+RSU_Price_Change_Pct)^(YEAR($A34)-2030),0) -> 0 | E34: =IF($A34=EDATE(DATE(2026,8,1),Inputs!$B$9),Inputs!$B$8,0) -> 0 | F34: =IF($A34=EDATE(DATE(2026,8,1),Inputs!$B$11),Inputs!$B$10,0) -> 0 | G34: =IF(Inputs!$B$16=1,((IF(YEAR($A34)=2026,Inputs!$B$2,IF(YEAR($A34)=2027,IF(MONTH($A34)>=Inputs!#REF!,Inputs!$B$2*(1+Inputs!$B$4),Inputs!$B$2),IF(YEAR($A34)=2028,IF(MONTH($A34)>=Inputs!#REF!,Inputs!$B$2*(1+Inputs!$B$4)*(1+Inputs!$B$5),Inputs!$B$2*(1+Inputs!$B$4)),IF(YEAR($A34)=2029,IF(MONTH($A34)>=Inputs!#REF!,Inputs!$B$2*(1+Inputs!$B$4)*(1+Inputs!$B$5)*(1+Inputs!$B$6),Inputs!$B$2*(1+Inputs!$B$4)*(1+Inputs!$B$5)),IF(MONTH($A34)>=Inputs!#REF!,Inputs!$B$2*(1+Inputs!$B$4)*(1+Inputs!$B$5)*(1+Inputs!$B$6)*(1+Inputs!$B$7),Inputs!$B$2*(1+Inputs!$B$4)*(1+Inputs!$B$5)*(1+Inputs!$B$6)))))))/12)*(MIN(Inputs!$B$17,Inputs!$B$18)*(1+Inputs!$B$19)+Inputs!$B$17*Inputs!$B$20),0) -> 0 | H34: =SUM(B34:G34) -> 4689.62 | I34: =$H34-J34-K34 -> 3599.813 | J34: =_xlfn.SINGLE(_xlfn.LET(_xlpm.d, $A34, _xlpm.ys, YEAR(_xlfn.SINGLE(_xlpm.d)) - IF(MONTH(_xlfn.SINGLE(_xlpm.d)) < UK_TaxYear_Start_Month, 1, 0), _xlpm.start, DATE(_xlfn.SINGLE(_xlpm.ys), UK_TaxYear_Start_Month, 1), _xlpm.m, DATEDIF(_xlfn.SINGLE(_xlpm.start), _xlfn.SINGLE(_xlpm.d), "m") + 1, _xlpm.cum, SUMIFS($H$2:$H$54, $A$2:$A$54, ">=" & _xlfn.SINGLE(_xlpm.start), $A$2:$A$54, "<=" & _xlfn.SINGLE(_xlpm.d)), _xlpm.pa, UK_Personal_Allowance_Annual / 12 * _xlfn.SINGLE(_xlpm.m), _xlpm.br, (UK_Basic_Band_Upper_Annual - UK_Personal_Allowance_Annual) / 12 * _xlfn.SINGLE(_xlpm.m), _xlpm.hr, (UK_Higher_Band_Upper_Annual - UK_Basic_Band_Upper_Annual) / 12 * _xlfn.SINGLE(_xlpm.m), _xlpm.taxable, MAX(0, _xlfn.SINGLE(_xlpm.cum) - _xlfn.SINGLE(_xlpm.pa)), _xlpm.tax_to_date, UK_Basic_Rate * MIN(_xlpm.taxable, _xlpm.br) + UK_Higher_Rate * MIN(MAX(_xlfn.SINGLE(_xlpm.taxable) - _xlfn.SINGLE(_xlpm.br), 0), _xlpm.hr) + UK_Additional_Rate * MAX(_xlfn.SINGLE(_xlpm.taxable) - _xlfn.SINGLE(_xlpm.br) - _xlfn.SINGLE(_xlpm.hr), 0), _xlpm.prior, SUMIFS($J$2:$J$54, $A$2:$A$54, ">=" & _xlfn.SINGLE(_xlpm.start), $A$2:$A$54, "<" & _xlfn.SINGLE(_xlpm.d)), MAX(0, _xlfn.SINGLE(_xlpm.tax_to_date) - _xlfn.SINGLE(_xlpm.prior)))) -> 828.51468 | K34: =_xlfn.SINGLE(_xlfn.LET(_xlpm.g, $H34, _xlpm.pt, UK_NI_PT_Monthly, _xlpm.uel, UK_NI_UEL_Monthly, IF(_xlfn.SINGLE(_xlpm.g) <= _xlfn.SINGLE(_xlpm.pt), 0, UK_NI_Main_Rate * MIN(_xlfn.SINGLE(_xlpm.g) - _xlfn.SINGLE(_xlpm.pt), _xlfn.SINGLE(_xlpm.uel) - _xlfn.SINGLE(_xlpm.pt)) + UK_NI_Upper_Rate * MAX(_xlfn.SINGLE(_xlpm.g) - _xlfn.SINGLE(_xlpm.uel), 0)))) -> 261.2924 | L34: =IF($A34<DATE(2026,10,1),Bonus_Pct_Aug2026_to_Sep2026,IF($A34<DATE(2027,10,1),Bonus_Pct_Oct2026_to_Sep2027,IF($A34<DATE(2028,10,1),Bonus_Pct_Oct2027_to_Sep2028,IF($A34<DATE(2029,10,1),Bonus_Pct_Oct2028_to_Sep2029,Bonus_Pct_Oct2029_onwards)))) -> 0.1
A35: 47239 | B35: =(IF(YEAR($A35)=2026,Base_Annual_Salary_GBP,IF(YEAR($A35)=2027,Base_Annual_Salary_GBP*(IF(MONTH($A35)>=4,(1+Raise_Pct_Apr2027),1)*IF(MONTH($A35)>=10,(1+Raise_Pct_Nov2027),1)),IF(YEAR($A35)=2028,Base_Annual_Salary_GBP*((1+Raise_Pct_Apr2027)*(1+Raise_Pct_Nov2027))*(IF(MONTH($A35)>=4,(1+Raise_Pct_Apr2028),1)*IF(MONTH($A35)>=10,(1+Raise_Pct_Nov2028),1)),IF(YEAR($A35)=2029,Base_Annual_Salary_GBP*((1+Raise_Pct_Apr2027)*(1+Raise_Pct_Nov2027)*(1+Raise_Pct_Apr2028)*(1+Raise_Pct_Nov2028))*(IF(MONTH($A35)>=4,(1+Raise_Pct_Apr2029),1)*IF(MONTH($A35)>=10,(1+Raise_Pct_Nov2029),1)),Base_Annual_Salary_GBP*((1+Raise_Pct_Apr2027)*(1+Raise_Pct_Nov2027)*(1+Raise_Pct_Apr2028)*(1+Raise_Pct_Nov2028)*(1+Raise_Pct_Apr2029)*(1+Raise_Pct_Nov2029))*(IF(MONTH($A35)>=4,(1+Raise_Pct_Apr2030),1)*IF(MONTH($A35)>=10,(1+Raise_Pct_Nov2030),1)))))))/12 -> 4689.62 | C35: =IF(MONTH($A35)=11,((IF(DATE(YEAR($A35),4,1)<DATE(2026,10,1),Bonus_Pct_Aug2026_to_Sep2026,IF(DATE(YEAR($A35),4,1)<DATE(2027,10,1),Bonus_Pct_Oct2026_to_Sep2027,IF(DATE(YEAR($A35),4,1)<DATE(2028,10,1),Bonus_Pct_Oct2027_to_Sep2028,IF(DATE(YEAR($A35),4,1)<DATE(2029,10,1),Bonus_Pct_Oct2028_to_Sep2029,Bonus_Pct_Oct2029_onwards)))))/2)*($B35*12) / (1 + IF(YEAR($A35)=2027,Raise_Pct_Nov2027,IF(YEAR($A35)=2028,Raise_Pct_Nov2028,IF(YEAR($A35)=2029,Raise_Pct_Nov2029,IF(YEAR($A35)=2030,Raise_Pct_Nov2030,0))))) * IF(YEAR($A35)=2026,2/6,1),IF(MONTH($A35)=5,((IF(DATE(YEAR($A35)-1,10,1)<DATE(2026,10,1),Bonus_Pct_Aug2026_to_Sep2026,IF(DATE(YEAR($A35)-1,10,1)<DATE(2027,10,1),Bonus_Pct_Oct2026_to_Sep2027,IF(DATE(YEAR($A35)-1,10,1)<DATE(2028,10,1),Bonus_Pct_Oct2027_to_Sep2028,IF(DATE(YEAR($A35)-1,10,1)<DATE(2029,10,1),Bonus_Pct_Oct2028_to_Sep2029,Bonus_Pct_Oct2029_onwards)))))/2)*($B35*12) / (1 + IF(YEAR($A35)=2027,Raise_Pct_Apr2027,IF(YEAR($A35)=2028,Raise_Pct_Apr2028,IF(YEAR($A35)=2029,Raise_Pct_Apr2029,IF(YEAR($A35)=2030,Raise_Pct_Apr2030,0))))),0)) -> 2731.8175 | D35: =IF(OR($A35=DATE(2027,9,1),$A35=EDATE(DATE(2027,9,1),12),$A35=EDATE(DATE(2027,9,1),24)),(New_Hire_Stock_Grant_USD/3)/FX_USD_per_GBP*(1+IF(YEAR($A35)=2027,Inputs!$B$56,IF(YEAR($A35)=2028,Inputs!$B$57,IF(YEAR($A35)=2029,Inputs!$B$58,0)))),0)+IF(OR($A35=DATE(2028,11,1),$A35=DATE(2029,11,1),$A35=DATE(2030,11,1)),(RSU_Grant_Nov2027_USD/3)/FX_USD_per_GBP*(1+RSU_Price_Change_Pct)^(YEAR($A35)-2028),0)+IF(OR($A35=DATE(2029,11,1),$A35=DATE(2030,11,1)),(RSU_Grant_Nov2028_USD/3)/FX_USD_per_GBP*(1+RSU_Price_Change_Pct)^(YEAR($A35)-2029),0)+IF($A35=DATE(2030,11,1),(RSU_Grant_Nov2029_USD/3)/FX_USD_per_GBP*(1+RSU_Price_Change_Pct)^(YEAR($A35)-2030),0) -> 0 | E35: =IF($A35=EDATE(DATE(2026,8,1),Inputs!$B$9),Inputs!$B$8,0) -> 0 | F35: =IF($A35=EDATE(DATE(2026,8,1),Inputs!$B$11),Inputs!$B$10,0) -> 0 | G35: =IF(Inputs!$B$16=1,((IF(YEAR($A35)=2026,Inputs!$B$2,IF(YEAR($A35)=2027,IF(MONTH($A35)>=Inputs!#REF!,Inputs!$B$2*(1+Inputs!$B$4),Inputs!$B$2),IF(YEAR($A35)=2028,IF(MONTH($A35)>=Inputs!#REF!,Inputs!$B$2*(1+Inputs!$B$4)*(1+Inputs!$B$5),Inputs!$B$2*(1+Inputs!$B$4)),IF(YEAR($A35)=2029,IF(MONTH($A35)>=Inputs!#REF!,Inputs!$B$2*(1+Inputs!$B$4)*(1+Inputs!$B$5)*(1+Inputs!$B$6),Inputs!$B$2*(1+Inputs!$B$4)*(1+Inputs!$B$5)),IF(MONTH($A35)>=Inputs!#REF!,Inputs!$B$2*(1+Inputs!$B$4)*(1+Inputs!$B$5)*(1+Inputs!$B$6)*(1+Inputs!$B$7),Inputs!$B$2*(1+Inputs!$B$4)*(1+Inputs!$B$5)*(1+Inputs!$B$6)))))))/12)*(MIN(Inputs!$B$17,Inputs!$B$18)*(1+Inputs!$B$19)+Inputs!$B$17*Inputs!$B$20),0) -> 0 | H35: =SUM(B35:G35) -> 7421.4375 | I35: =$H35-J35-K35 -> 5184.2671 | J35: =_xlfn.SINGLE(_xlfn.LET(_xlpm.d, $A35, _xlpm.ys, YEAR(_xlfn.SINGLE(_xlpm.d)) - IF(MONTH(_xlfn.SINGLE(_xlpm.d)) < UK_TaxYear_Start_Month, 1, 0), _xlpm.start, DATE(_xlfn.SINGLE(_xlpm.ys), UK_TaxYear_Start_Month, 1), _xlpm.m, DATEDIF(_xlfn.SINGLE(_xlpm.start), _xlfn.SINGLE(_xlpm.d), "m") + 1, _xlpm.cum, SUMIFS($H$2:$H$54, $A$2:$A$54, ">=" & _xlfn.SINGLE(_xlpm.start), $A$2:$A$54, "<=" & _xlfn.SINGLE(_xlpm.d)), _xlpm.pa, UK_Personal_Allowance_Annual / 12 * _xlfn.SINGLE(_xlpm.m), _xlpm.br, (UK_Basic_Band_Upper_Annual - UK_Personal_Allowance_Annual) / 12 * _xlfn.SINGLE(_xlpm.m), _xlpm.hr, (UK_Higher_Band_Upper_Annual - UK_Basic_Band_Upper_Annual) / 12 * _xlfn.SINGLE(_xlpm.m), _xlpm.taxable, MAX(0, _xlfn.SINGLE(_xlpm.cum) - _xlfn.SINGLE(_xlpm.pa)), _xlpm.tax_to_date, UK_Basic_Rate * MIN(_xlpm.taxable, _xlpm.br) + UK_Higher_Rate * MIN(MAX(_xlfn.SINGLE(_xlpm.taxable) - _xlfn.SINGLE(_xlpm.br), 0), _xlpm.hr) + UK_Additional_Rate * MAX(_xlfn.SINGLE(_xlpm.taxable) - _xlfn.SINGLE(_xlpm.br) - _xlfn.SINGLE(_xlpm.hr), 0), _xlpm.prior, SUMIFS($J$2:$J$54, $A$2:$A$54, ">=" & _xlfn.SINGLE(_xlpm.start), $A$2:$A$54, "<" & _xlfn.SINGLE(_xlpm.d)), MAX(0, _xlfn.SINGLE(_xlpm.tax_to_date) - _xlfn.SINGLE(_xlpm.prior)))) -> 1921.2417 | K35: =_xlfn.SINGLE(_xlfn.LET(_xlpm.g, $H35, _xlpm.pt, UK_NI_PT_Monthly, _xlpm.uel, UK_NI_UEL_Monthly, IF(_xlfn.SINGLE(_xlpm.g) <= _xlfn.SINGLE(_xlpm.pt), 0, UK_NI_Main_Rate * MIN(_xlfn.SINGLE(_xlpm.g) - _xlfn.SINGLE(_xlpm.pt), _xlfn.SINGLE(_xlpm.uel) - _xlfn.SINGLE(_xlpm.pt)) + UK_NI_Upper_Rate * MAX(_xlfn.SINGLE(_xlpm.g) - _xlfn.SINGLE(_xlpm.uel), 0)))) -> 315.92875 | L35: =IF($A35<DATE(2026,10,1),Bonus_Pct_Aug2026_to_Sep2026,IF($A35<DATE(2027,10,1),Bonus_Pct_Oct2026_to_Sep2027,IF($A35<DATE(2028,10,1),Bonus_Pct_Oct2027_to_Sep2028,IF($A35<DATE(2029,10,1),Bonus_Pct_Oct2028_to_Sep2029,Bonus_Pct_Oct2029_onwards)))) -> 0.1
A36: 47270 | B36: =(IF(YEAR($A36)=2026,Base_Annual_Salary_GBP,IF(YEAR($A36)=2027,Base_Annual_Salary_GBP*(IF(MONTH($A36)>=4,(1+Raise_Pct_Apr2027),1)*IF(MONTH($A36)>=10,(1+Raise_Pct_Nov2027),1)),IF(YEAR($A36)=2028,Base_Annual_Salary_GBP*((1+Raise_Pct_Apr2027)*(1+Raise_Pct_Nov2027))*(IF(MONTH($A36)>=4,(1+Raise_Pct_Apr2028),1)*IF(MONTH($A36)>=10,(1+Raise_Pct_Nov2028),1)),IF(YEAR($A36)=2029,Base_Annual_Salary_GBP*((1+Raise_Pct_Apr2027)*(1+Raise_Pct_Nov2027)*(1+Raise_Pct_Apr2028)*(1+Raise_Pct_Nov2028))*(IF(MONTH($A36)>=4,(1+Raise_Pct_Apr2029),1)*IF(MONTH($A36)>=10,(1+Raise_Pct_Nov2029),1)),Base_Annual_Salary_GBP*((1+Raise_Pct_Apr2027)*(1+Raise_Pct_Nov2027)*(1+Raise_Pct_Apr2028)*(1+Raise_Pct_Nov2028)*(1+Raise_Pct_Apr2029)*(1+Raise_Pct_Nov2029))*(IF(MONTH($A36)>=4,(1+Raise_Pct_Apr2030),1)*IF(MONTH($A36)>=10,(1+Raise_Pct_Nov2030),1)))))))/12 -> 4689.62 | C36: =IF(MONTH($A36)=11,((IF(DATE(YEAR($A36),4,1)<DATE(2026,10,1),Bonus_Pct_Aug2026_to_Sep2026,IF(DATE(YEAR($A36),4,1)<DATE(2027,10,1),Bonus_Pct_Oct2026_to_Sep2027,IF(DATE(YEAR($A36),4,1)<DATE(2028,10,1),Bonus_Pct_Oct2027_to_Sep2028,IF(DATE(YEAR($A36),4,1)<DATE(2029,10,1),Bonus_Pct_Oct2028_to_Sep2029,Bonus_Pct_Oct2029_onwards)))))/2)*($B36*12) / (1 + IF(YEAR($A36)=2027,Raise_Pct_Nov2027,IF(YEAR($A36)=2028,Raise_Pct_Nov2028,IF(YEAR($A36)=2029,Raise_Pct_Nov2029,IF(YEAR($A36)=2030,Raise_Pct_Nov2030,0))))) * IF(YEAR($A36)=2026,2/6,1),IF(MONTH($A36)=5,((IF(DATE(YEAR($A36)-1,10,1)<DATE(2026,10,1),Bonus_Pct_Aug2026_to_Sep2026,IF(DATE(YEAR($A36)-1,10,1)<DATE(2027,10,1),Bonus_Pct_Oct2026_to_Sep2027,IF(DATE(YEAR($A36)-1,10,1)<DATE(2028,10,1),Bonus_Pct_Oct2027_to_Sep2028,IF(DATE(YEAR($A36)-1,10,1)<DATE(2029,10,1),Bonus_Pct_Oct2028_to_Sep2029,Bonus_Pct_Oct2029_onwards)))))/2)*($B36*12) / (1 + IF(YEAR($A36)=2027,Raise_Pct_Apr2027,IF(YEAR($A36)=2028,Raise_Pct_Apr2028,IF(YEAR($A36)=2029,Raise_Pct_Apr2029,IF(YEAR($A36)=2030,Raise_Pct_Apr2030,0))))),0)) -> 0 | D36: =IF(OR($A36=DATE(2027,9,1),$A36=EDATE(DATE(2027,9,1),12),$A36=EDATE(DATE(2027,9,1),24)),(New_Hire_Stock_Grant_USD/3)/FX_USD_per_GBP*(1+IF(YEAR($A36)=2027,Inputs!$B$56,IF(YEAR($A36)=2028,Inputs!$B$57,IF(YEAR($A36)=2029,Inputs!$B$58,0)))),0)+IF(OR($A36=DATE(2028,11,1),$A36=DATE(2029,11,1),$A36=DATE(2030,11,1)),(RSU_Grant_Nov2027_USD/3)/FX_USD_per_GBP*(1+RSU_Price_Change_Pct)^(YEAR($A36)-2028),0)+IF(OR($A36=DATE(2029,11,1),$A36=DATE(2030,11,1)),(RSU_Grant_Nov2028_USD/3)/FX_USD_per_GBP*(1+RSU_Price_Change_Pct)^(YEAR($A36)-2029),0)+IF($A36=DATE(2030,11,1),(RSU_Grant_Nov2029_USD/3)/FX_USD_per_GBP*(1+RSU_Price_Change_Pct)^(YEAR($A36)-2030),0) -> 0 | E36: =IF($A36=EDATE(DATE(2026,8,1),Inputs!$B$9),Inputs!$B$8,0) -> 0 | F36: =IF($A36=EDATE(DATE(2026,8,1),Inputs!$B$11),Inputs!$B$10,0) -> 0 | G36: =IF(Inputs!$B$16=1,((IF(YEAR($A36)=2026,Inputs!$B$2,IF(YEAR($A36)=2027,IF(MONTH($A36)>=Inputs!#REF!,Inputs!$B$2*(1+Inputs!$B$4),Inputs!$B$2),IF(YEAR($A36)=2028,IF(MONTH($A36)>=Inputs!#REF!,Inputs!$B$2*(1+Inputs!$B$4)*(1+Inputs!$B$5),Inputs!$B$2*(1+Inputs!$B$4)),IF(YEAR($A36)=2029,IF(MONTH($A36)>=Inputs!#REF!,Inputs!$B$2*(1+Inputs!$B$4)*(1+Inputs!$B$5)*(1+Inputs!$B$6),Inputs!$B$2*(1+Inputs!$B$4)*(1+Inputs!$B$5)),IF(MONTH($A36)>=Inputs!#REF!,Inputs!$B$2*(1+Inputs!$B$4)*(1+Inputs!$B$5)*(1+Inputs!$B$6)*(1+Inputs!$B$7),Inputs!$B$2*(1+Inputs!$B$4)*(1+Inputs!$B$5)*(1+Inputs!$B$6)))))))/12)*(MIN(Inputs!$B$17,Inputs!$B$18)*(1+Inputs!$B$19)+Inputs!$B$17*Inputs!$B$20),0) -> 0 | H36: =SUM(B36:G36) -> 4689.62 | I36: =$H36-J36-K36 -> 3599.813 | J36: =_xlfn.SINGLE(_xlfn.LET(_xlpm.d, $A36, _xlpm.ys, YEAR(_xlfn.SINGLE(_xlpm.d)) - IF(MONTH(_xlfn.SINGLE(_xlpm.d)) < UK_TaxYear_Start_Month, 1, 0), _xlpm.start, DATE(_xlfn.SINGLE(_xlpm.ys), UK_TaxYear_Start_Month, 1), _xlpm.m, DATEDIF(_xlfn.SINGLE(_xlpm.start), _xlfn.SINGLE(_xlpm.d), "m") + 1, _xlpm.cum, SUMIFS($H$2:$H$54, $A$2:$A$54, ">=" & _xlfn.SINGLE(_xlpm.start), $A$2:$A$54, "<=" & _xlfn.SINGLE(_xlpm.d)), _xlpm.pa, UK_Personal_Allowance_Annual / 12 * _xlfn.SINGLE(_xlpm.m), _xlpm.br, (UK_Basic_Band_Upper_Annual - UK_Personal_Allowance_Annual) / 12 * _xlfn.SINGLE(_xlpm.m), _xlpm.hr, (UK_Higher_Band_Upper_Annual - UK_Basic_Band_Upper_Annual) / 12 * _xlfn.SINGLE(_xlpm.m), _xlpm.taxable, MAX(0, _xlfn.SINGLE(_xlpm.cum) - _xlfn.SINGLE(_xlpm.pa)), _xlpm.tax_to_date, UK_Basic_Rate * MIN(_xlpm.taxable, _xlpm.br) + UK_Higher_Rate * MIN(MAX(_xlfn.SINGLE(_xlpm.taxable) - _xlfn.SINGLE(_xlpm.br), 0), _xlpm.hr) + UK_Additional_Rate * MAX(_xlfn.SINGLE(_xlpm.taxable) - _xlfn.SINGLE(_xlpm.br) - _xlfn.SINGLE(_xlpm.hr), 0), _xlpm.prior, SUMIFS($J$2:$J$54, $A$2:$A$54, ">=" & _xlfn.SINGLE(_xlpm.start), $A$2:$A$54, "<" & _xlfn.SINGLE(_xlpm.d)), MAX(0, _xlfn.SINGLE(_xlpm.tax_to_date) - _xlfn.SINGLE(_xlpm.prior)))) -> 828.51468 | K36: =_xlfn.SINGLE(_xlfn.LET(_xlpm.g, $H36, _xlpm.pt, UK_NI_PT_Monthly, _xlpm.uel, UK_NI_UEL_Monthly, IF(_xlfn.SINGLE(_xlpm.g) <= _xlfn.SINGLE(_xlpm.pt), 0, UK_NI_Main_Rate * MIN(_xlfn.SINGLE(_xlpm.g) - _xlfn.SINGLE(_xlpm.pt), _xlfn.SINGLE(_xlpm.uel) - _xlfn.SINGLE(_xlpm.pt)) + UK_NI_Upper_Rate * MAX(_xlfn.SINGLE(_xlpm.g) - _xlfn.SINGLE(_xlpm.uel), 0)))) -> 261.2924 | L36: =IF($A36<DATE(2026,10,1),Bonus_Pct_Aug2026_to_Sep2026,IF($A36<DATE(2027,10,1),Bonus_Pct_Oct2026_to_Sep2027,IF($A36<DATE(2028,10,1),Bonus_Pct_Oct2027_to_Sep2028,IF($A36<DATE(2029,10,1),Bonus_Pct_Oct2028_to_Sep2029,Bonus_Pct_Oct2029_onwards)))) -> 0.1
A37: 47300 | B37: =(IF(YEAR($A37)=2026,Base_Annual_Salary_GBP,IF(YEAR($A37)=2027,Base_Annual_Salary_GBP*(IF(MONTH($A37)>=4,(1+Raise_Pct_Apr2027),1)*IF(MONTH($A37)>=10,(1+Raise_Pct_Nov2027),1)),IF(YEAR($A37)=2028,Base_Annual_Salary_GBP*((1+Raise_Pct_Apr2027)*(1+Raise_Pct_Nov2027))*(IF(MONTH($A37)>=4,(1+Raise_Pct_Apr2028),1)*IF(MONTH($A37)>=10,(1+Raise_Pct_Nov2028),1)),IF(YEAR($A37)=2029,Base_Annual_Salary_GBP*((1+Raise_Pct_Apr2027)*(1+Raise_Pct_Nov2027)*(1+Raise_Pct_Apr2028)*(1+Raise_Pct_Nov2028))*(IF(MONTH($A37)>=4,(1+Raise_Pct_Apr2029),1)*IF(MONTH($A37)>=10,(1+Raise_Pct_Nov2029),1)),Base_Annual_Salary_GBP*((1+Raise_Pct_Apr2027)*(1+Raise_Pct_Nov2027)*(1+Raise_Pct_Apr2028)*(1+Raise_Pct_Nov2028)*(1+Raise_Pct_Apr2029)*(1+Raise_Pct_Nov2029))*(IF(MONTH($A37)>=4,(1+Raise_Pct_Apr2030),1)*IF(MONTH($A37)>=10,(1+Raise_Pct_Nov2030),1)))))))/12 -> 4689.62 | C37: =IF(MONTH($A37)=11,((IF(DATE(YEAR($A37),4,1)<DATE(2026,10,1),Bonus_Pct_Aug2026_to_Sep2026,IF(DATE(YEAR($A37),4,1)<DATE(2027,10,1),Bonus_Pct_Oct2026_to_Sep2027,IF(DATE(YEAR($A37),4,1)<DATE(2028,10,1),Bonus_Pct_Oct2027_to_Sep2028,IF(DATE(YEAR($A37),4,1)<DATE(2029,10,1),Bonus_Pct_Oct2028_to_Sep2029,Bonus_Pct_Oct2029_onwards)))))/2)*($B37*12) / (1 + IF(YEAR($A37)=2027,Raise_Pct_Nov2027,IF(YEAR($A37)=2028,Raise_Pct_Nov2028,IF(YEAR($A37)=2029,Raise_Pct_Nov2029,IF(YEAR($A37)=2030,Raise_Pct_Nov2030,0))))) * IF(YEAR($A37)=2026,2/6,1),IF(MONTH($A37)=5,((IF(DATE(YEAR($A37)-1,10,1)<DATE(2026,10,1),Bonus_Pct_Aug2026_to_Sep2026,IF(DATE(YEAR($A37)-1,10,1)<DATE(2027,10,1),Bonus_Pct_Oct2026_to_Sep2027,IF(DATE(YEAR($A37)-1,10,1)<DATE(2028,10,1),Bonus_Pct_Oct2027_to_Sep2028,IF(DATE(YEAR($A37)-1,10,1)<DATE(2029,10,1),Bonus_Pct_Oct2028_to_Sep2029,Bonus_Pct_Oct2029_onwards)))))/2)*($B37*12) / (1 + IF(YEAR($A37)=2027,Raise_Pct_Apr2027,IF(YEAR($A37)=2028,Raise_Pct_Apr2028,IF(YEAR($A37)=2029,Raise_Pct_Apr2029,IF(YEAR($A37)=2030,Raise_Pct_Apr2030,0))))),0)) -> 0 | D37: =IF(OR($A37=DATE(2027,9,1),$A37=EDATE(DATE(2027,9,1),12),$A37=EDATE(DATE(2027,9,1),24)),(New_Hire_Stock_Grant_USD/3)/FX_USD_per_GBP*(1+IF(YEAR($A37)=2027,Inputs!$B$56,IF(YEAR($A37)=2028,Inputs!$B$57,IF(YEAR($A37)=2029,Inputs!$B$58,0)))),0)+IF(OR($A37=DATE(2028,11,1),$A37=DATE(2029,11,1),$A37=DATE(2030,11,1)),(RSU_Grant_Nov2027_USD/3)/FX_USD_per_GBP*(1+RSU_Price_Change_Pct)^(YEAR($A37)-2028),0)+IF(OR($A37=DATE(2029,11,1),$A37=DATE(2030,11,1)),(RSU_Grant_Nov2028_USD/3)/FX_USD_per_GBP*(1+RSU_Price_Change_Pct)^(YEAR($A37)-2029),0)+IF($A37=DATE(2030,11,1),(RSU_Grant_Nov2029_USD/3)/FX_USD_per_GBP*(1+RSU_Price_Change_Pct)^(YEAR($A37)-2030),0) -> 0 | E37: =IF($A37=EDATE(DATE(2026,8,1),Inputs!$B$9),Inputs!$B$8,0) -> 0 | F37: =IF($A37=EDATE(DATE(2026,8,1),Inputs!$B$11),Inputs!$B$10,0) -> 0 | G37: =IF(Inputs!$B$16=1,((IF(YEAR($A37)=2026,Inputs!$B$2,IF(YEAR($A37)=2027,IF(MONTH($A37)>=Inputs!#REF!,Inputs!$B$2*(1+Inputs!$B$4),Inputs!$B$2),IF(YEAR($A37)=2028,IF(MONTH($A37)>=Inputs!#REF!,Inputs!$B$2*(1+Inputs!$B$4)*(1+Inputs!$B$5),Inputs!$B$2*(1+Inputs!$B$4)),IF(YEAR($A37)=2029,IF(MONTH($A37)>=Inputs!#REF!,Inputs!$B$2*(1+Inputs!$B$4)*(1+Inputs!$B$5)*(1+Inputs!$B$6),Inputs!$B$2*(1+Inputs!$B$4)*(1+Inputs!$B$5)),IF(MONTH($A37)>=Inputs!#REF!,Inputs!$B$2*(1+Inputs!$B$4)*(1+Inputs!$B$5)*(1+Inputs!$B$6)*(1+Inputs!$B$7),Inputs!$B$2*(1+Inputs!$B$4)*(1+Inputs!$B$5)*(1+Inputs!$B$6)))))))/12)*(MIN(Inputs!$B$17,Inputs!$B$18)*(1+Inputs!$B$19)+Inputs!$B$17*Inputs!$B$20),0) -> 0 | H37: =SUM(B37:G37) -> 4689.62 | I37: =$H37-J37-K37 -> 3599.813 | J37: =_xlfn.SINGLE(_xlfn.LET(_xlpm.d, $A37, _xlpm.ys, YEAR(_xlfn.SINGLE(_xlpm.d)) - IF(MONTH(_xlfn.SINGLE(_xlpm.d)) < UK_TaxYear_Start_Month, 1, 0), _xlpm.start, DATE(_xlfn.SINGLE(_xlpm.ys), UK_TaxYear_Start_Month, 1), _xlpm.m, DATEDIF(_xlfn.SINGLE(_xlpm.start), _xlfn.SINGLE(_xlpm.d), "m") + 1, _xlpm.cum, SUMIFS($H$2:$H$54, $A$2:$A$54, ">=" & _xlfn.SINGLE(_xlpm.start), $A$2:$A$54, "<=" & _xlfn.SINGLE(_xlpm.d)), _xlpm.pa, UK_Personal_Allowance_Annual / 12 * _xlfn.SINGLE(_xlpm.m), _xlpm.br, (UK_Basic_Band_Upper_Annual - UK_Personal_Allowance_Annual) / 12 * _xlfn.SINGLE(_xlpm.m), _xlpm.hr, (UK_Higher_Band_Upper_Annual - UK_Basic_Band_Upper_Annual) / 12 * _xlfn.SINGLE(_xlpm.m), _xlpm.taxable, MAX(0, _xlfn.SINGLE(_xlpm.cum) - _xlfn.SINGLE(_xlpm.pa)), _xlpm.tax_to_date, UK_Basic_Rate * MIN(_xlpm.taxable, _xlpm.br) + UK_Higher_Rate * MIN(MAX(_xlfn.SINGLE(_xlpm.taxable) - _xlfn.SINGLE(_xlpm.br), 0), _xlpm.hr) + UK_Additional_Rate * MAX(_xlfn.SINGLE(_xlpm.taxable) - _xlfn.SINGLE(_xlpm.br) - _xlfn.SINGLE(_xlpm.hr), 0), _xlpm.prior, SUMIFS($J$2:$J$54, $A$2:$A$54, ">=" & _xlfn.SINGLE(_xlpm.start), $A$2:$A$54, "<" & _xlfn.SINGLE(_xlpm.d)), MAX(0, _xlfn.SINGLE(_xlpm.tax_to_date) - _xlfn.SINGLE(_xlpm.prior)))) -> 828.51468 | K37: =_xlfn.SINGLE(_xlfn.LET(_xlpm.g, $H37, _xlpm.pt, UK_NI_PT_Monthly, _xlpm.uel, UK_NI_UEL_Monthly, IF(_xlfn.SINGLE(_xlpm.g) <= _xlfn.SINGLE(_xlpm.pt), 0, UK_NI_Main_Rate * MIN(_xlfn.SINGLE(_xlpm.g) - _xlfn.SINGLE(_xlpm.pt), _xlfn.SINGLE(_xlpm.uel) - _xlfn.SINGLE(_xlpm.pt)) + UK_NI_Upper_Rate * MAX(_xlfn.SINGLE(_xlpm.g) - _xlfn.SINGLE(_xlpm.uel), 0)))) -> 261.2924 | L37: =IF($A37<DATE(2026,10,1),Bonus_Pct_Aug2026_to_Sep2026,IF($A37<DATE(2027,10,1),Bonus_Pct_Oct2026_to_Sep2027,IF($A37<DATE(2028,10,1),Bonus_Pct_Oct2027_to_Sep2028,IF($A37<DATE(2029,10,1),Bonus_Pct_Oct2028_to_Sep2029,Bonus_Pct_Oct2029_onwards)))) -> 0.1
